Workbook

Sheet ReadMe
B1: Oman Climate Transition Stress Test | v4 | Sector-level stressed PD
B3: Scope | C3: Transition risk AND acute physical risk, both expressed through stressed PD. Output is a stressed PD by sector and master rating grade for four NGFS scenarios. No customer or ECL layer. No LGD. Chronic physical risk through the macro channel is NOT included: see the scope note below.
B5: Core formula | C5: stressed_PD = NORMSDIST( NORMSINV(PD_0) + push + macro_shift )
C6: push = k x LN(1 + cost_ratio); cost_ratio = carbon price x deflator x intensity x intensity_index x (1 - pass_through) / (1,000,000 x GVA_index)
C7: macro_shift = beta x GDP_level_deviation x macro_beta_sector
C8: Pure probit shift. Returns PD_0 exactly at zero stress, so no de-stress artefact is possible. Asset correlation rho does not appear.
B10: Sector taxonomy | C10: The Verification tab records, for every input number, what it was checked against and what the check found. Quality_Checks then reports the live state of the model. Physical risk enters as a second cost ratio added to the carbon cost ratio inside the same push transform.
B12: Read this first | C12: The Verification tab records, for every input number, what it was checked against and what the check found. Four numbers changed as a result and three could not be verified from any public source. Quality_Checks then reports the live state of the model.
B14: Colour legend
B15: Blue font | C15: Bank input or editable assumption.
B16: Black font | C16: Live formula or verified constant.
B17: Green font | C17: Cross-sheet link.
B18: Yellow fill | C18: Unverified, placeholder, or requires a decision. Counted live on Quality_Checks.
B19: Lilac fill | C19: Illustrative sample, not used for calibration.

Sheet Change_Log
B1: What changed from v3 to v4
B4: # | C4: Area | D4: v3 | E4: v4
B5: 1 | C5: Output | D5: Customer-level ECL, aggregation and portfolio summary tabs. | E5: Removed entirely. The output is a sector by grade by scenario stressed PD grid, plus a PD-multiple summary at grade MR5.
B6: 2 | C6: Sector taxonomy | D6: 16 sectors, several built by splitting an SNA parent with a placeholder share, and two (real estate, water and waste) with no GVA at all, which meant they silently received no stress. | E6: 10 sectors. Every ISIC Rev.4 section sits in exactly one sector; every sector has a GVA figure taken from the source. No placeholder splits of GVA, no zero-GVA rows. ISIC L, E, N and R are not itemised in Oman's submission but the table still reconciles to published GDP, so they are absorbed into their parent sector rather than given empty rows.
B7: 3 | C7: ISIC B split | D7: 93% / 7% placeholder between oil and gas and other mining. | E7: Sourced. Oman's separately reported non-oil Mining GVA is 205.8 OMR m for 2023, so oil and gas extraction is 14,750.3 out of an ISIC B total of 14,956.1.
B8: 4 | C8: k anchor | D8: Two conflicting values, 2.0% to 2.05% and 2.0% to 4.0%, with the conflict flagged but unresolved. | E8: Both traced. 2.0% to 4.0% is COAL MINING under disorderly transition (OP 281 Section 5.4), not the median firm. 2.0% to 2.05% is the +2.5% relative disorderly-versus-orderly figure at 2050. The clean transition-only median-firm anchor is +0.5% relative, orderly versus hot house world in the policy implementation phase, and is now the default.
B9: 5 | C9: EU intensity | D9: 1,100 t/EURm revenue, described as a coal-mining figure. | E9: Identified as the LARGE-FIRM average on a Scope 1+2+3 basis, so neither median nor Scope 1. Replaced by a symmetric construction: EU national Scope 1 emissions divided by EU GVA, built exactly as the Oman intensity is, with a documented median-to-average adjustment.
B10: 6 | C10: Revenue versus GVA | D10: Flagged as a defect, handled by an unsourced turnover-to-GVA ratio applied to the EU anchor. | E10: Workaround implemented. Route 1 removes the conversion entirely by constructing both sides from national aggregates. Route 2 (the firm-level conversion) is retained for comparison, and a basis switch on Sector_Master lets the whole model run on turnover if the bank obtains it.
B11: 7 | C11: EU pass-through | D11: 50%. | E11: 0%. OP 281 Section 5.1 applies the carbon tax to operating costs with no cost relief; any demand response runs separately through Scope 3 revenues. There is no pass-through in the ECB cost channel.
B12: 8 | C12: Price base | D12: NGFS carbon prices in US$2010 applied directly to GVA in 2023 US dollars. | E12: US GDP deflator applied explicitly on Scenario_Mapping. Omitting it understated every cost ratio by roughly a quarter.
B13: 9 | C13: Carbon price value | D13: Net Zero 2035 at 290. | E13: Corrected to 294, per the NGFS Phase V statement that the price rises from $98/tCO2 in 2025 to $294/tCO2 by 2035.
B14: 10 | C14: Carbon price region | D14: Global, unremarked. | E14: Global, with the direction of bias documented: the NGFS footnote states prices tend to be LOWER in emerging economies, so applying the global path to Oman overstates the transition cost.
B15: 11 | C15: GVA vintage | D15: Undated. | E15: Identified as 2023 current prices, against 2024 EDGAR emissions. The one-year mismatch is disclosed and the 2024 replacement values are recorded in the Verification log.
... B24: 20 | C24: Ordering checks | D24: Transition ordering only. | E24: Both orderings now checked live. Transition must run NZ >= DT >= FW >= CP and physical must run CP >= FW >= DT >= NZ. Both pass.

Sheet Verification
B1: Verification log
B2: Every input number in the model, what it was checked against, and the result. VERIFIED means traced to the primary source named. CORRECTED means the source disagreed with the value in the workbook and the value has been changed. UNVERIFIABLE means no public source could confirm it and it remains a flagged input.
B4: # | C4: Value | D4: Value now in model | E4: Source checked against | F4: Finding | G4: Status
B5: 1 | C5: NGFS shadow carbon price, Net Zero 2050, 2035 | D5: US$2010 294 /tCO2 | E5: NGFS Phase V main report, Main results, Carbon prices | F5: The report states a price of about $300/tCO2 is needed by 2035 for net zero by 2050, rising from $98/tCO2 in 2025 to $294/tCO2. The workbook carried 290. Changed to 294. | G5: CORRECTED
B6: 2 | C6: Units of the NGFS carbon price | D6: US$2010 | E6: NGFS Phase V, Scenarios at a glance and Main results, chart axes | F6: Both carbon price charts are labelled US$2010 per tCO2. The workbook applied this directly to GVA measured in 2023 current US dollars. A price deflator is now applied explicitly on Scenario_Mapping. Omitting it understated every cost ratio by roughly a quarter. | G6: CORRECTED
B7: 3 | C7: Regional applicability of the carbon price | D7: Global weighted | E7: NGFS Phase V, Main results, Carbon prices, footnote | F7: The published prices are weighted global values. The footnote states that prices tend to be LOWER in emerging economies, because policy stringency is lower and more low-cost abatement remains available. Applying the global path to Oman therefore biases the transition cost UPWARDS. Country-downscaled prices exist in the IIASA portal for 220 countries. | G7: VERIFIED, conservative bias documented
B8: 4 | C8: End-of-century warming by scenario | D8: NZ 1.4, DT 1.7, FW 2.4, CP 3.0 | E8: NGFS Phase V, Scenarios at a glance | F8: All four match the source exactly. | G8: VERIFIED
B9: 5 | C9: Transition GDP deviation, Net Zero and Delayed Transition | D9: NZ -1.5 / -1.0 / -0.8; DT -0.3 / -2.0 / -1.7 | E9: NGFS Phase V GDP decomposition chart; ECB Occasional Paper 281 Section 3.2.1 | F9: The published Phase V chart gives the transition component graphically, not as a table, so exact values cannot be read off. The magnitudes and the shape (Net Zero loss peaks early then narrows, Delayed Transition loss appears around 2030 and peaks later) are consistent with the chart. ECB OP 281 independently states that the transition-risk impact is limited to no more than 2% of European GDP under a disorderly transition, which corroborates the -2.0% Delayed Transition figure. Values retained as plausible but not exact. | G9: PLAUSIBLE, not exact
B10: 6 | C10: Transition GDP deviation, Fragmented World | D10: 0.0 in every year | E10: NGFS Phase V GDP decomposition chart | F10: Fragmented World is NOT plotted in the published GDP decomposition chart, which shows only Net Zero 2050, Delayed Transition and Current Policies. No public figure exists. A zero deviation is not credible for a high-cost, badly co-ordinated transition. Requires the IIASA portal pull. | G10: UNVERIFIABLE - action required
B11: 7 | C11: Transition GDP deviation, Current Policies | D11: 0.0 in every year | E11: NGFS scenario design | F11: Correct by construction. Current Policies is the transition baseline and carries no additional transition cost. Its risk is physical, which this model does not cover. | G11: VERIFIED
B12: 8 | C12: EU anchor: median firm baseline PD | D12: 2.0% | E12: ECB Occasional Paper 281, Chart 31 panel b, right-hand axis | F12: The median-firm series on the right-hand axis runs from about 1.9% in 2020 to about 2.4% by 2050. A 2020 baseline of 2.0% is supported. | G12: VERIFIED
B13: 9 | C13: EU anchor: median firm PD response | D13: +0.5% RELATIVE (transition-only) | E13: ECB Occasional Paper 281, Section 5.3 | F13: Section 5.3 states the median firm would have a slightly higher PD, about 0.5%, under orderly transition during the policy implementation phase compared with the hot house world. Because hot house world carries no transition policy, this difference is a CLEAN transition-only effect. Chart 28 confirms these are percentage CHANGES relative to baseline, not percentage points. So 2.00% becomes 2.01%. | G13: VERIFIED and corrected
B14: 10 | C14: Origin of the 2.0% to 2.05% figure in the v2 sheet | D14: Not used as primary | E14: ECB Occasional Paper 281, Section 5.3 | F14: This is the +2.5% relative figure for DISORDERLY transition versus orderly at 2050. It is not the transition-only median-firm anchor and it mixes transition timing with residual physical effects. Retained as selectable Anchor B for sensitivity. | G14: IDENTIFIED
B15: 11 | C15: Origin of the 2.0% to 4.0% figure in the v2 register | D15: Not used | E15: ECB Occasional Paper 281, Section 5.4 and Chart 31 | F15: This is COAL MINING (NACE B05), not the median firm: the paper states the transition would drive coal-mining PDs to 5% and 4% under orderly and disorderly transition, a 150% and 100% increase on current values. The register entry was a coal-mining anchor mislabelled as a median-firm anchor. Discarded, because the user is calibrating on a median firm. | G15: RESOLVED
... B43: 39 | C43: Insurance recovery and P&L share | D43: 25% recovery, 60% of retained loss to P&L | E43: Analyst judgement | F43: Oman's non-life insurance penetration is low and catastrophe cover is not universal. The 60/40 split between P&L impact and capital replacement is what keeps the PD and LGD channels from double counting the same damage. | G43: JUDGEMENT

Sheet Quality_Checks
B1: Quality checks (live)
B2: Every check is a live formula. Items marked ACTION are decisions or data pulls that only the bank or a source download can resolve; they are deliberately left visible rather than defaulted away.
B4: # | C4: Check | D4: Result | E4: Status | F4: What it means
B5: 1 | C5: Sector GVA reconciles to SNA total value added | D5: =Sector_Master!E18 -> 41963.907 | E5: =Sector_Master!E20 -> PASS | F5: Sector GVA must equal 41,963.9 OMR m exactly. Every ISIC section is in exactly one sector.
B6: 2 | C6: Every EDGAR row's allocation shares sum to 1.00 | D6: =COUNTIF(Emissions_Allocation!R6:R12,"FAIL") -> 0 | E6: =IF(D6=0,"PASS","FAIL") -> PASS | F6: Fix the shaded share cells on Emissions_Allocation.
B7: 3 | C7: EDGAR categories reconcile to the national total | D7: =Emissions_Allocation!D15 -> PASS | E7: =Emissions_Allocation!D15 -> PASS | F7: The E7 residual is a plug, so this holds unless the national total is edited.
B8: 4 | C8: Allocated sector emissions reconcile to the national total | D8: =Emissions_Allocation!R17 -> OK | E8: =Emissions_Allocation!R17 -> OK | F8: Allocation has neither lost nor created emissions.
B9: 5 | C9: Sectors with zero computed intensity | D9: =COUNTIF(Oman_Intensity!F6:F15,0) -> 0 | E9: =IF(D9=0,"PASS","FAIL") -> PASS | F9: Must be zero. This was the v3 defect: rows were created for ISIC sections Oman does not itemise, so those sectors had no denominator and received no stress. The v4 taxonomy makes it structurally impossible.
B10: 6 | C10: No de-stress: stressed PD is never below baseline | D10: =StressedPD_Sector!G100 -> 0 | E10: =IF(D10=0,"PASS","FAIL") -> PASS | F10: Under the probit-shift form this can only fail if a push or macro shift is negative.
B11: 7 | C11: Probit identity: NORMSDIST(NORMSINV(2%)) = 2% | D11: =StressedPD_Sector!G101 -> 0.02 | E11: =IF(ABS(D11-0.02)<0.000000001,"PASS","FAIL") -> PASS | F11: Confirms the transform round-trips and the baseline is preserved at zero stress.
B12: 8 | C12: Sectors where physical cost exceeds transition cost under Current Policies | D12: =SUMPRODUCT((StressedPD_Sector!M16:M25>StressedPD_Sector!I16:I25)*1) -> 7 | E12: =IF(D12>0,"crossover present","no crossover") -> crossover present | F12: Diagnostic, not a pass or fail. Current Policies has almost no transition cost by construction, so physical damage should dominate there. If this reads zero at a long horizon, the physical module is switched off or mis-scaled. Ordering itself is tested separately by checks 22 and 23.
B13: 9 | C13: Denominator basis in use | D13: =Sector_Master!C4 -> GVA | E13: =IF(Sector_Master!C4="GVA","GVA","TURNOVER") -> GVA | F13: GVA by default, because Oman publishes value added by activity but not turnover. The EU anchor is converted onto the same basis on EU_k_Calibration rather than left as an implicit unit mismatch.
B14: 10 | C14: EU intensity route in use | D14: =EU_k_Calibration!C34 -> 1 | E14: =IF(D14=1,"Symmetric","Firm-level") -> Symmetric | F14: Route 1 (symmetric) builds the EU intensity the same way the Oman intensity is built, national Scope 1 emissions over national GVA, so the turnover conversion never enters.
B15: 11 | C15: US GDP deflator applied to the carbon price | D15: =Scenario_Mapping!C15 -> 1.35 | E15: =IF(D15>1.01,"PASS","FAIL") -> PASS | F15: NGFS prices are US$2010; the denominator is 2023 US dollars. v2 mixed the two, understating every cost ratio by roughly a quarter.
B16: 12 | C16: Corporate share of national emissions | D16: =Emissions_Allocation!D26 -> 0.8169275 | E16: =IF(AND(D16>0.4,D16<0.9),"PASS","REVIEW") -> PASS | F16: The remainder is households and own-account use. If this drifts above 90% the household exclusion has been switched off and private vehicle and residential emissions are being charged to borrowers.
B17: 13 | C17: Live regression reproduces the reported slope | D17: =ABS(Regression_Data!E19-Macro_Shift!C5) -> 0 | E17: =IF(D17<0.00001,"PASS","FAIL") -> PASS | F17: The estimation on Regression_Data must reproduce the selected specification on Regression_Tests.
B18: 14 | C18: EDGAR Buildings emissions per head (tCO2e) | D18: =Emissions_Allocation!D23 -> 4.1943396 | E18: =IF(D18<3,"PASS","FLAG") -> FLAG | F18: EXPECTED TO FLAG. This is direct building fuel combustion only, since air conditioning electricity is already under Power Industry. Above about 3 tCO2e per head the figure is not credible for a hot climate. Seventy per cent is allocated to households so it does not distort corporate intensities, but re-download the EDGAR sector file.
B19: 15 | C19: Fragmented World carries a non-zero GDP deviation | D19: =Scenario_Mapping!D25 -> ACTION - FW deviation is zero in every year | E19: =IF(LEFT(D19,4)="PASS","PASS","ACTION") -> ACTION | F19: EXPECTED TO SHOW ACTION. Fragmented World is not plotted in the published NGFS chart and no public figure exists, but a zero deviation for a high-cost, badly co-ordinated transition is not credible. Requires the IIASA portal pull.
B20: 16 | C20: k anchor decision recorded | D20: =EU_k_Calibration!C8 -> A | E20: =IF(D20="A","Anchor A (transition-only, +0.5% relative)","Anchor B (disorderly 2050, +2.5% relative)") -> Anchor A (transition-only, +0.5% relative) | F20: Both are now traced to ECB OP 281 Section 5.3. Anchor A is the default because it is the only clean transition-only identification.
B21: 17 | C21: Extrapolation multiple of k beyond its calibration point | D21: =EU_k_Calibration!C68 -> 129.70533 | E21: =IF(D21<10,"PASS","DISCLOSE") -> DISCLOSE | F21: k is calibrated at one cost ratio and applied far above it. Above 10x, disclose or cap.
B22: 18 | C22: Curvature parameter theta in use | D22: =k_MultiAnchor!C17 -> 0 | E22: =IF(D22=0,"log (v4 default)","non-default") -> log (v4 default) | F22: theta = 0 is the logarithmic form. The ECB anchors cannot identify this parameter (see k_MultiAnchor section C); it is exposed so the range can be reported rather than assumed away.
B23: 19 | C23: Coal anchor out-of-sample check | D23: =k_MultiAnchor!C40 -> 47.45908 | E23: =IF(D23<3,"consistent","REJECTED") -> REJECTED | F23: EXPECTED TO REJECT. The coal-mining PD response demands an intensity 20 to 50 times higher than coal plausibly has on a Scope 1 basis, confirming OP 281's own statement that the response is driven by Scope 3 abatement investment raising leverage. It therefore cannot calibrate a Scope 1 cost curve.
B24: 20 | C24: Cost ratio cap and cells bound | D24: =k_MultiAnchor!C61 -> 0 | E24: =IF(k_MultiAnchor!C60>100,"OFF","ON") -> OFF | F24: Wired but off. Given that curvature cannot be estimated above the calibration range, a cap is the only mechanism that bounds the utilities and manufacturing result. Set k_MultiAnchor C60 to switch it on.
B25: 21 | C25: Physical exposure weights normalise to 1.00 | D25: =Physical_Exposure!H18 -> PASS | E25: =IF(D25="PASS","PASS","FAIL") -> PASS | F25: Exposure weights redistribute the national annual average loss across sectors; they must not change its total. The value-added-weighted mean of the normalised weights must be exactly 1.000 for all three hazards.
B26: 22 | C26: Transition ordering: NZ >= DT >= FW >= CP | D26: =StressedPD_Sector!G102 -> 0 | E26: =IF(D26=0,"PASS","FAIL") -> PASS | F26: Transition severity must follow the carbon price ordering.
B27: 23 | C27: Physical ordering: CP >= FW >= DT >= NZ | D27: =StressedPD_Sector!G103 -> 0 | E27: =IF(D27=0,"PASS","FAIL") -> PASS | F27: Physical severity must follow the warming ordering, i.e. the exact reverse of transition. If both pass, the model has internally coherent opposing channels, which is the single most important structural test of a climate scenario model.
B28: 24 | C28: Warming path at horizon is interpolated, not sourced | D28: =Physical_Hazard!E34 -> 1.64 | E28: =IF(Physical_Hazard!D30>0,"FLAG","FLAG") -> FLAG | F28: EXPECTED TO FLAG. The warming figure at the horizon is a straight-line interpolation between today and 2100. Replace with the MAGICC temperature path published with NGFS Phase V. This is the weakest input in the physical module.
C30: Count of FAIL / ACTION / FLAG / REJECTED | E30: =COUNTIF(E5:E28,"FAIL")+COUNTIF(E5:E28,"ACTION")+COUNTIF(E5:E28,"FLAG")+COUNTIF(E5:E28,"REJECTED") -> 4
C32: Four items are expected to flag on delivery: 14 (EDGAR Buildings), 15 (Fragmented World transition deviation), 19 (the coal anchor, an intended diagnostic) and 24 (the warming interpolation).

Sheet StressedPD_Sector
B1: Stressed PD by sector and rating grade [MAIN OUTPUT]
B2: stressed_PD = NORMSDIST( NORMSINV(PD_0) + push + macro_shift ), where push = k x g(transition cost ratio + physical cost ratio). The two cost ratios are added INSIDE the transform, not as two separate pushes, because the transform is concave: adding two separate pushes would understate the joint effect of facing both shocks at once.
B4: Horizon year | C4: =Scenario_Mapping!C39 -> 2040
B5: k (fitted on ECB anchor 1) | C5: =k_MultiAnchor!C20 -> 0.26300976
B6: US GDP deflator, 2010 to denominator base | C6: =Scenario_Mapping!C15 -> 1.35
B7: Curvature parameter theta | C7: =k_MultiAnchor!C17 -> 0
C8: Net Zero 2050 | D8: Delayed Transition | E8: Current Policies | F8: Fragmented World
B9: Carbon price at horizon (US$2010/tCO2) | C9: =INDEX(NGFS_CarbonPrice!$C$6:$F$9,MATCH(C$8,NGFS_CarbonPrice!$B$6:$B$9,0),MATCH($C$4,NGFS_CarbonPrice!$C$5:$F$5,0)) -> 420 | D9: =INDEX(NGFS_CarbonPrice!$C$6:$F$9,MATCH(D$8,NGFS_CarbonPrice!$B$6:$B$9,0),MATCH($C$4,NGFS_CarbonPrice!$C$5:$F$5,0)) -> 165 | E9: =INDEX(NGFS_CarbonPrice!$C$6:$F$9,MATCH(E$8,NGFS_CarbonPrice!$B$6:$B$9,0),MATCH($C$4,NGFS_CarbonPrice!$C$5:$F$5,0)) -> 8 | F9: =INDEX(NGFS_CarbonPrice!$C$6:$F$9,MATCH(F$8,NGFS_CarbonPrice!$B$6:$B$9,0),MATCH($C$4,NGFS_CarbonPrice!$C$5:$F$5,0)) -> 35
B10: Carbon price deflated | C10: =C9*$C$6 -> 567 | D10: =D9*$C$6 -> 222.75 | E10: =E9*$C$6 -> 10.8 | F10: =F9*$C$6 -> 47.25
B11: Emissions intensity index | C11: =INDEX(Dynamic_Adjust!$C$6:$C$9,MATCH(C$8,Dynamic_Adjust!$B$6:$B$9,0)) -> 1 | D11: =INDEX(Dynamic_Adjust!$C$6:$C$9,MATCH(D$8,Dynamic_Adjust!$B$6:$B$9,0)) -> 1 | E11: =INDEX(Dynamic_Adjust!$C$6:$C$9,MATCH(E$8,Dynamic_Adjust!$B$6:$B$9,0)) -> 1 | F11: =INDEX(Dynamic_Adjust!$C$6:$C$9,MATCH(F$8,Dynamic_Adjust!$B$6:$B$9,0)) -> 1
B12: Denominator index | C12: =INDEX(Dynamic_Adjust!$D$6:$D$9,MATCH(C$8,Dynamic_Adjust!$B$6:$B$9,0)) -> 1 | D12: =INDEX(Dynamic_Adjust!$D$6:$D$9,MATCH(D$8,Dynamic_Adjust!$B$6:$B$9,0)) -> 1 | E12: =INDEX(Dynamic_Adjust!$D$6:$D$9,MATCH(E$8,Dynamic_Adjust!$B$6:$B$9,0)) -> 1 | F12: =INDEX(Dynamic_Adjust!$D$6:$D$9,MATCH(F$8,Dynamic_Adjust!$B$6:$B$9,0)) -> 1
B13: macro_shift before macro_beta | C13: =INDEX(Macro_Shift!$E$15:$E$18,MATCH(C$8,Macro_Shift!$B$15:$B$18,0)) -> 0.0095201194 | D13: =INDEX(Macro_Shift!$E$15:$E$18,MATCH(D$8,Macro_Shift!$B$15:$B$18,0)) -> 0.019040239 | E13: =INDEX(Macro_Shift!$E$15:$E$18,MATCH(E$8,Macro_Shift!$B$15:$B$18,0)) -> 0 | F13: =INDEX(Macro_Shift!$E$15:$E$18,MATCH(F$8,Macro_Shift!$B$15:$B$18,0)) -> 0
B15: ID | C15: Sector | D15: Intensity (t/US$m) | E15: Pass-through | F15: macro_beta | G15: transition NZ | H15: transition DT | I15: transition CP | J15: transition FW | K15: physical NZ | L15: physical DT | M15: physical CP | N15: physical FW | O15: TOTAL cost NZ | P15: TOTAL cost DT | Q15: TOTAL cost CP | R15: TOTAL cost FW | S15: push NZ | T15: push DT | U15: push CP | V15: push FW | W15: macro NZ | X15: macro DT | Y15: macro CP | Z15: macro FW
B16: S01 | C16: Agriculture, Forestry & Fishing | D16: =Oman_Intensity!F6 -> 717.44975 | E16: =Oman_Intensity!G6 -> 0.25 | F16: =Oman_Intensity!H6 -> 1 | G16: =IF($D16<=0,0,C$10*$D16*C$11*(1-$E16)/(1000000*C$12)) -> 0.30509551 | H16: =IF($D16<=0,0,D$10*$D16*D$11*(1-$E16)/(1000000*D$12)) -> 0.11985895 | I16: =IF($D16<=0,0,E$10*$D16*E$11*(1-$E16)/(1000000*E$12)) -> 0.005811343 | J16: =IF($D16<=0,0,F$10*$D16*F$11*(1-$E16)/(1000000*F$12)) -> 0.025424626 | K16: =Physical_Exposure!D25 -> 0.016476475 | L16: =Physical_Exposure!E25 -> 0.01828231 | M16: =Physical_Exposure!F25 -> 0.027614921 | N16: =Physical_Exposure!G25 -> 0.022991798 | O16: =MIN(G16+K16,k_MultiAnchor!$C$60) -> 0.32157198 | P16: =MIN(H16+L16,k_MultiAnchor!$C$60) -> 0.13814126 | Q16: =MIN(I16+M16,k_MultiAnchor!$C$60) -> 0.033426264 | R16: =MIN(J16+N16,k_MultiAnchor!$C$60) -> 0.048416423 | S16: =$C$5*IF(ABS($C$7)<0.000000000001,LN(1+O16),((1+O16)^$C$7-1)/$C$7) -> 0.073332888 | T16: =$C$5*IF(ABS($C$7)<0.000000000001,LN(1+P16),((1+P16)^$C$7-1)/$C$7) -> 0.034032531 | U16: =$C$5*IF(ABS($C$7)<0.000000000001,LN(1+Q16),((1+Q16)^$C$7-1)/$C$7) -> 0.0086476958 | V16: =$C$5*IF(ABS($C$7)<0.000000000001,LN(1+R16),((1+R16)^$C$7-1)/$C$7) -> 0.012435327 | W16: =C$13*$F16 -> 0.0095201194 | X16: =D$13*$F16 -> 0.019040239 | Y16: =E$13*$F16 -> 0 | Z16: =F$13*$F16 -> 0
B17: S02 | C17: Oil & Gas Extraction | D17: =Oman_Intensity!F7 -> 1185.1007 | E17: =Oman_Intensity!G7 -> 0.05 | F17: =Oman_Intensity!H7 -> 1 | G17: =IF($D17<=0,0,C$10*$D17*C$11*(1-$E17)/(1000000*C$12)) -> 0.63835448 | H17: =IF($D17<=0,0,D$10*$D17*D$11*(1-$E17)/(1000000*D$12)) -> 0.25078212 | I17: =IF($D17<=0,0,E$10*$D17*E$11*(1-$E17)/(1000000*E$12)) -> 0.012159133 | J17: =IF($D17<=0,0,F$10*$D17*F$11*(1-$E17)/(1000000*F$12)) -> 0.053196207 | K17: =Physical_Exposure!D26 -> 0.0064994814 | L17: =Physical_Exposure!E26 -> 0.0072663239 | M17: =Physical_Exposure!F26 -> 0.01129257 | N17: =Physical_Exposure!G26 -> 0.0092865145 | O17: =MIN(G17+K17,k_MultiAnchor!$C$60) -> 0.64485396 | P17: =MIN(H17+L17,k_MultiAnchor!$C$60) -> 0.25804844 | Q17: =MIN(I17+M17,k_MultiAnchor!$C$60) -> 0.023451703 | R17: =MIN(J17+N17,k_MultiAnchor!$C$60) -> 0.062482721 | S17: =$C$5*IF(ABS($C$7)<0.000000000001,LN(1+O17),((1+O17)^$C$7-1)/$C$7) -> 0.13088723 | T17: =$C$5*IF(ABS($C$7)<0.000000000001,LN(1+P17),((1+P17)^$C$7-1)/$C$7) -> 0.060376958 | U17: =$C$5*IF(ABS($C$7)<0.000000000001,LN(1+Q17),((1+Q17)^$C$7-1)/$C$7) -> 0.0060968127 | V17: =$C$5*IF(ABS($C$7)<0.000000000001,LN(1+R17),((1+R17)^$C$7-1)/$C$7) -> 0.01594059 | W17: =C$13*$F17 -> 0.0095201194 | X17: =D$13*$F17 -> 0.019040239 | Y17: =E$13*$F17 -> 0 | Z17: =F$13*$F17 -> 0
B18: S03 | C18: Mining & Quarrying (non-oil) | D18: =Oman_Intensity!F8 -> 1334.9036 | E18: =Oman_Intensity!G8 -> 0.3 | F18: =Oman_Intensity!H8 -> 1 | G18: =IF($D18<=0,0,C$10*$D18*C$11*(1-$E18)/(1000000*C$12)) -> 0.52982324 | H18: =IF($D18<=0,0,D$10*$D18*D$11*(1-$E18)/(1000000*D$12)) -> 0.20814484 | I18: =IF($D18<=0,0,E$10*$D18*E$11*(1-$E18)/(1000000*E$12)) -> 0.010091871 | J18: =IF($D18<=0,0,F$10*$D18*F$11*(1-$E18)/(1000000*F$12)) -> 0.044151937 | K18: =Physical_Exposure!D27 -> 0.010911436 | L18: =Physical_Exposure!E27 -> 0.012289413 | M18: =Physical_Exposure!F27 -> 0.019616425 | N18: =Physical_Exposure!G27 -> 0.015949272 | O18: =MIN(G18+K18,k_MultiAnchor!$C$60) -> 0.54073468 | P18: =MIN(H18+L18,k_MultiAnchor!$C$60) -> 0.22043426 | Q18: =MIN(I18+M18,k_MultiAnchor!$C$60) -> 0.029708296 | R18: =MIN(J18+N18,k_MultiAnchor!$C$60) -> 0.060101209 | S18: =$C$5*IF(ABS($C$7)<0.000000000001,LN(1+O18),((1+O18)^$C$7-1)/$C$7) -> 0.11368843 | T18: =$C$5*IF(ABS($C$7)<0.000000000001,LN(1+P18),((1+P18)^$C$7-1)/$C$7) -> 0.052393318 | U18: =$C$5*IF(ABS($C$7)<0.000000000001,LN(1+Q18),((1+Q18)^$C$7-1)/$C$7) -> 0.0076997566 | V18: =$C$5*IF(ABS($C$7)<0.000000000001,LN(1+R18),((1+R18)^$C$7-1)/$C$7) -> 0.015350403 | W18: =C$13*$F18 -> 0.0095201194 | X18: =D$13*$F18 -> 0.019040239 | Y18: =E$13*$F18 -> 0 | Z18: =F$13*$F18 -> 0
B19: S04 | C19: Manufacturing | D19: =Oman_Intensity!F9 -> 2087.9448 | E19: =Oman_Intensity!G9 -> 0.3 | F19: =Oman_Intensity!H9 -> 1 | G19: =IF($D19<=0,0,C$10*$D19*C$11*(1-$E19)/(1000000*C$12)) -> 0.82870529 | H19: =IF($D19<=0,0,D$10*$D19*D$11*(1-$E19)/(1000000*D$12)) -> 0.32556279 | I19: =IF($D19<=0,0,E$10*$D19*E$11*(1-$E19)/(1000000*E$12)) -> 0.015784863 | J19: =IF($D19<=0,0,F$10*$D19*F$11*(1-$E19)/(1000000*F$12)) -> 0.069058774 | K19: =Physical_Exposure!D28 -> 0.0064242651 | L19: =Physical_Exposure!E28 -> 0.0071248132 | M19: =Physical_Exposure!F28 -> 0.010722697 | N19: =Physical_Exposure!G28 -> 0.00894478 | O19: =MIN(G19+K19,k_MultiAnchor!$C$60) -> 0.83512955 | P19: =MIN(H19+L19,k_MultiAnchor!$C$60) -> 0.33268761 | Q19: =MIN(I19+M19,k_MultiAnchor!$C$60) -> 0.02650756 | R19: =MIN(J19+N19,k_MultiAnchor!$C$60) -> 0.078003554 | S19: =$C$5*IF(ABS($C$7)<0.000000000001,LN(1+O19),((1+O19)^$C$7-1)/$C$7) -> 0.15967719 | T19: =$C$5*IF(ABS($C$7)<0.000000000001,LN(1+P19),((1+P19)^$C$7-1)/$C$7) -> 0.075535788 | U19: =$C$5*IF(ABS($C$7)<0.000000000001,LN(1+Q19),((1+Q19)^$C$7-1)/$C$7) -> 0.006880946 | V19: =$C$5*IF(ABS($C$7)<0.000000000001,LN(1+R19),((1+R19)^$C$7-1)/$C$7) -> 0.019754866 | W19: =C$13*$F19 -> 0.0095201194 | X19: =D$13*$F19 -> 0.019040239 | Y19: =E$13*$F19 -> 0 | Z19: =F$13*$F19 -> 0
B20: S05 | C20: Electricity, Gas, Water & Waste | D20: =Oman_Intensity!F10 -> 8926.9692 | E20: =Oman_Intensity!G10 -> 0.8 | F20: =Oman_Intensity!H10 -> 1 | G20: =IF($D20<=0,0,C$10*$D20*C$11*(1-$E20)/(1000000*C$12)) -> 1.0123183 | H20: =IF($D20<=0,0,D$10*$D20*D$11*(1-$E20)/(1000000*D$12)) -> 0.39769648 | I20: =IF($D20<=0,0,E$10*$D20*E$11*(1-$E20)/(1000000*E$12)) -> 0.019282253 | J20: =IF($D20<=0,0,F$10*$D20*F$11*(1-$E20)/(1000000*F$12)) -> 0.084359859 | K20: =Physical_Exposure!D29 -> 0.0080605421 | L20: =Physical_Exposure!E29 -> 0.0089195449 | M20: =Physical_Exposure!F29 -> 0.013315013 | N20: =Physical_Exposure!G29 -> 0.011145856 | O20: =MIN(G20+K20,k_MultiAnchor!$C$60) -> 1.0203788 | P20: =MIN(H20+L20,k_MultiAnchor!$C$60) -> 0.40661602 | Q20: =MIN(I20+M20,k_MultiAnchor!$C$60) -> 0.032597266 | R20: =MIN(J20+N20,k_MultiAnchor!$C$60) -> 0.095505715 | S20: =$C$5*IF(ABS($C$7)<0.000000000001,LN(1+O20),((1+O20)^$C$7-1)/$C$7) -> 0.18497083 | T20: =$C$5*IF(ABS($C$7)<0.000000000001,LN(1+P20),((1+P20)^$C$7-1)/$C$7) -> 0.089735468 | U20: =$C$5*IF(ABS($C$7)<0.000000000001,LN(1+Q20),((1+Q20)^$C$7-1)/$C$7) -> 0.0084366288 | V20: =$C$5*IF(ABS($C$7)<0.000000000001,LN(1+R20),((1+R20)^$C$7-1)/$C$7) -> 0.023990724 | W20: =C$13*$F20 -> 0.0095201194 | X20: =D$13*$F20 -> 0.019040239 | Y20: =E$13*$F20 -> 0 | Z20: =F$13*$F20 -> 0
B21: S06 | C21: Construction | D21: =Oman_Intensity!F11 -> 198.61822 | E21: =Oman_Intensity!G11 -> 0.5 | F21: =Oman_Intensity!H11 -> 1 | G21: =IF($D21<=0,0,C$10*$D21*C$11*(1-$E21)/(1000000*C$12)) -> 0.056308264 | H21: =IF($D21<=0,0,D$10*$D21*D$11*(1-$E21)/(1000000*D$12)) -> 0.022121104 | I21: =IF($D21<=0,0,E$10*$D21*E$11*(1-$E21)/(1000000*E$12)) -> 0.0010725384 | J21: =IF($D21<=0,0,F$10*$D21*F$11*(1-$E21)/(1000000*F$12)) -> 0.0046923554 | K21: =Physical_Exposure!D30 -> 0.012126552 | L21: =Physical_Exposure!E30 -> 0.013702392 | M21: =Physical_Exposure!F30 -> 0.022114953 | N21: =Physical_Exposure!G30 -> 0.017898683 | O21: =MIN(G21+K21,k_MultiAnchor!$C$60) -> 0.068434816 | P21: =MIN(H21+L21,k_MultiAnchor!$C$60) -> 0.035823496 | Q21: =MIN(I21+M21,k_MultiAnchor!$C$60) -> 0.023187491 | R21: =MIN(J21+N21,k_MultiAnchor!$C$60) -> 0.022591038 | S21: =$C$5*IF(ABS($C$7)<0.000000000001,LN(1+O21),((1+O21)^$C$7-1)/$C$7) -> 0.017409876 | T21: =$C$5*IF(ABS($C$7)<0.000000000001,LN(1+P21),((1+P21)^$C$7-1)/$C$7) -> 0.0092570911 | U21: =$C$5*IF(ABS($C$7)<0.000000000001,LN(1+Q21),((1+Q21)^$C$7-1)/$C$7) -> 0.006028906 | V21: =$C$5*IF(ABS($C$7)<0.000000000001,LN(1+R21),((1+R21)^$C$7-1)/$C$7) -> 0.0058755434 | W21: =C$13*$F21 -> 0.0095201194 | X21: =D$13*$F21 -> 0.019040239 | Y21: =E$13*$F21 -> 0 | Z21: =F$13*$F21 -> 0
B22: S07 | C22: Wholesale & Retail Trade | D22: =Oman_Intensity!F12 -> 428.01663 | E22: =Oman_Intensity!G12 -> 0.7 | F22: =Oman_Intensity!H12 -> 1 | G22: =IF($D22<=0,0,C$10*$D22*C$11*(1-$E22)/(1000000*C$12)) -> 0.072805628 | H22: =IF($D22<=0,0,D$10*$D22*D$11*(1-$E22)/(1000000*D$12)) -> 0.028602211 | I22: =IF($D22<=0,0,E$10*$D22*E$11*(1-$E22)/(1000000*E$12)) -> 0.0013867739 | J22: =IF($D22<=0,0,F$10*$D22*F$11*(1-$E22)/(1000000*F$12)) -> 0.0060671357 | K22: =Physical_Exposure!D31 -> 0.0037660892 | L22: =Physical_Exposure!E31 -> 0.0041781021 | M22: =Physical_Exposure!F31 -> 0.0062840799 | N22: =Physical_Exposure!G31 -> 0.005245403 | O22: =MIN(G22+K22,k_MultiAnchor!$C$60) -> 0.076571717 | P22: =MIN(H22+L22,k_MultiAnchor!$C$60) -> 0.032780313 | Q22: =MIN(I22+M22,k_MultiAnchor!$C$60) -> 0.0076708537 | R22: =MIN(J22+N22,k_MultiAnchor!$C$60) -> 0.011312539 | S22: =$C$5*IF(ABS($C$7)<0.000000000001,LN(1+O22),((1+O22)^$C$7-1)/$C$7) -> 0.019405296 | T22: =$C$5*IF(ABS($C$7)<0.000000000001,LN(1+P22),((1+P22)^$C$7-1)/$C$7) -> 0.008483248 | U22: =$C$5*IF(ABS($C$7)<0.000000000001,LN(1+Q22),((1+Q22)^$C$7-1)/$C$7) -> 0.0020098107 | V22: =$C$5*IF(ABS($C$7)<0.000000000001,LN(1+R22),((1+R22)^$C$7-1)/$C$7) -> 0.0029586048 | W22: =C$13*$F22 -> 0.0095201194 | X22: =D$13*$F22 -> 0.019040239 | Y22: =E$13*$F22 -> 0 | Z22: =F$13*$F22 -> 0
B23: S08 | C23: Transport & Storage | D23: =Oman_Intensity!F13 -> 1190.4402 | E23: =Oman_Intensity!G13 -> 0.6 | F23: =Oman_Intensity!H13 -> 1 | G23: =IF($D23<=0,0,C$10*$D23*C$11*(1-$E23)/(1000000*C$12)) -> 0.26999184 | H23: =IF($D23<=0,0,D$10*$D23*D$11*(1-$E23)/(1000000*D$12)) -> 0.10606822 | I23: =IF($D23<=0,0,E$10*$D23*E$11*(1-$E23)/(1000000*E$12)) -> 0.0051427016 | J23: =IF($D23<=0,0,F$10*$D23*F$11*(1-$E23)/(1000000*F$12)) -> 0.02249932 | K23: =Physical_Exposure!D32 -> 0.0067073924 | L23: =Physical_Exposure!E32 -> 0.0075268282 | M23: =Physical_Exposure!F32 -> 0.011833316 | N23: =Physical_Exposure!G32 -> 0.0096872415 | O23: =MIN(G23+K23,k_MultiAnchor!$C$60) -> 0.27669923 | P23: =MIN(H23+L23,k_MultiAnchor!$C$60) -> 0.11359505 | Q23: =MIN(I23+M23,k_MultiAnchor!$C$60) -> 0.016976018 | R23: =MIN(J23+N23,k_MultiAnchor!$C$60) -> 0.032186561 | S23: =$C$5*IF(ABS($C$7)<0.000000000001,LN(1+O23),((1+O23)^$C$7-1)/$C$7) -> 0.064247503 | T23: =$C$5*IF(ABS($C$7)<0.000000000001,LN(1+P23),((1+P23)^$C$7-1)/$C$7) -> 0.028298158 | U23: =$C$5*IF(ABS($C$7)<0.000000000001,LN(1+Q23),((1+Q23)^$C$7-1)/$C$7) -> 0.0044273842 | V23: =$C$5*IF(ABS($C$7)<0.000000000001,LN(1+R23),((1+R23)^$C$7-1)/$C$7) -> 0.0083319985 | W23: =C$13*$F23 -> 0.0095201194 | X23: =D$13*$F23 -> 0.019040239 | Y23: =E$13*$F23 -> 0 | Z23: =F$13*$F23 -> 0
B24: S09 | C24: Accommodation & Food Services | D24: =Oman_Intensity!F14 -> 730.03078 | E24: =Oman_Intensity!G14 -> 0.35 | F24: =Oman_Intensity!H14 -> 1 | G24: =IF($D24<=0,0,C$10*$D24*C$11*(1-$E24)/(1000000*C$12)) -> 0.26905285 | H24: =IF($D24<=0,0,D$10*$D24*D$11*(1-$E24)/(1000000*D$12)) -> 0.10569933 | I24: =IF($D24<=0,0,E$10*$D24*E$11*(1-$E24)/(1000000*E$12)) -> 0.0051248161 | J24: =IF($D24<=0,0,F$10*$D24*F$11*(1-$E24)/(1000000*F$12)) -> 0.02242107 | K24: =Physical_Exposure!D33 -> 0.0056719972 | L24: =Physical_Exposure!E33 -> 0.0062809294 | M24: =Physical_Exposure!F33 -> 0.009393502 | N24: =Physical_Exposure!G33 -> 0.0078581776 | O24: =MIN(G24+K24,k_MultiAnchor!$C$60) -> 0.27472484 | P24: =MIN(H24+L24,k_MultiAnchor!$C$60) -> 0.11198026 | Q24: =MIN(I24+M24,k_MultiAnchor!$C$60) -> 0.014518318 | R24: =MIN(J24+N24,k_MultiAnchor!$C$60) -> 0.030279248 | S24: =$C$5*IF(ABS($C$7)<0.000000000001,LN(1+O24),((1+O24)^$C$7-1)/$C$7) -> 0.06384045 | T24: =$C$5*IF(ABS($C$7)<0.000000000001,LN(1+P24),((1+P24)^$C$7-1)/$C$7) -> 0.027916499 | U24: =$C$5*IF(ABS($C$7)<0.000000000001,LN(1+Q24),((1+Q24)^$C$7-1)/$C$7) -> 0.003791006 | V24: =$C$5*IF(ABS($C$7)<0.000000000001,LN(1+R24),((1+R24)^$C$7-1)/$C$7) -> 0.0078455496 | W24: =C$13*$F24 -> 0.0095201194 | X24: =D$13*$F24 -> 0.019040239 | Y24: =E$13*$F24 -> 0 | Z24: =F$13*$F24 -> 0
B25: S10 | C25: Financial, Professional, Public & Other Services | D25: =Oman_Intensity!F15 -> 161.89863 | E25: =Oman_Intensity!G15 -> 0.6 | F25: =Oman_Intensity!H15 -> 1 | G25: =IF($D25<=0,0,C$10*$D25*C$11*(1-$E25)/(1000000*C$12)) -> 0.036718609 | H25: =IF($D25<=0,0,D$10*$D25*D$11*(1-$E25)/(1000000*D$12)) -> 0.014425168 | I25: =IF($D25<=0,0,E$10*$D25*E$11*(1-$E25)/(1000000*E$12)) -> 0.00069940208 | J25: =IF($D25<=0,0,F$10*$D25*F$11*(1-$E25)/(1000000*F$12)) -> 0.0030598841 | K25: =Physical_Exposure!D34 -> 0.001634379 | L25: =Physical_Exposure!E34 -> 0.0018214048 | M25: =Physical_Exposure!F34 -> 0.0027917362 | N25: =Physical_Exposure!G34 -> 0.0023104411 | O25: =MIN(G25+K25,k_MultiAnchor!$C$60) -> 0.038352988 | P25: =MIN(H25+L25,k_MultiAnchor!$C$60) -> 0.016246573 | Q25: =MIN(I25+M25,k_MultiAnchor!$C$60) -> 0.0034911382 | R25: =MIN(J25+N25,k_MultiAnchor!$C$60) -> 0.0053703252 | S25: =$C$5*IF(ABS($C$7)<0.000000000001,LN(1+O25),((1+O25)^$C$7-1)/$C$7) -> 0.0098985808 | T25: =$C$5*IF(ABS($C$7)<0.000000000001,LN(1+P25),((1+P25)^$C$7-1)/$C$7) -> 0.0042386678 | U25: =$C$5*IF(ABS($C$7)<0.000000000001,LN(1+Q25),((1+Q25)^$C$7-1)/$C$7) -> 0.00091660436 | V25: =$C$5*IF(ABS($C$7)<0.000000000001,LN(1+R25),((1+R25)^$C$7-1)/$C$7) -> 0.0014086688 | W25: =C$13*$F25 -> 0.0095201194 | X25: =D$13*$F25 -> 0.019040239 | Y25: =E$13*$F25 -> 0 | Z25: =F$13*$F25 -> 0
B28: Sector ID | C28: Sector | D28: Grade | E28: Key | F28: Baseline PD | G28: Stressed PD NZ | H28: Stressed PD DT | I28: Stressed PD CP | J28: Stressed PD FW | K28: PD multiple NZ | L28: PD multiple DT | M28: PD multiple CP | N28: PD multiple FW
B29: =$B$16 -> S01 | C29: =$C$16 -> Agriculture, Forestry & Fishing | D29: MR1 | E29: =B29&"|"&D29 -> S01|MR1 | F29: =INDEX(RatingGrades!$C$6:$C$12,MATCH(D29,RatingGrades!$B$6:$B$12,0)) -> 0.001 | G29: =NORMSDIST(NORMSINV($F29)+S$16+W$16) -> 0.0013175537 | H29: =NORMSDIST(NORMSINV($F29)+T$16+X$16) -> 0.0011940951 | I29: =NORMSDIST(NORMSINV($F29)+U$16+Y$16) -> 0.0010295097 | J29: =NORMSDIST(NORMSINV($F29)+V$16+Z$16) -> 0.0010426847 | K29: =G29/$F29 -> 1.3175537 | L29: =H29/$F29 -> 1.1940951 | M29: =I29/$F29 -> 1.0295097 | N29: =J29/$F29 -> 1.0426847
B30: =$B$16 -> S01 | C30: =$C$16 -> Agriculture, Forestry & Fishing | D30: MR2 | E30: =B30&"|"&D30 -> S01|MR2 | F30: =INDEX(RatingGrades!$C$6:$C$12,MATCH(D30,RatingGrades!$B$6:$B$12,0)) -> 0.0025 | G30: =NORMSDIST(NORMSINV($F30)+S$16+W$16) -> 0.0032230608 | H30: =NORMSDIST(NORMSINV($F30)+T$16+X$16) -> 0.0029439392 | I30: =NORMSDIST(NORMSINV($F30)+U$16+Y$16) -> 0.0025679342 | J30: =NORMSDIST(NORMSINV($F30)+V$16+Z$16) -> 0.0025982109 | K30: =G30/$F30 -> 1.2892243 | L30: =H30/$F30 -> 1.1775757 | M30: =I30/$F30 -> 1.0271737 | N30: =J30/$F30 -> 1.0392843
B31: =$B$16 -> S01 | C31: =$C$16 -> Agriculture, Forestry & Fishing | D31: MR3 | E31: =B31&"|"&D31 -> S01|MR3 | F31: =INDEX(RatingGrades!$C$6:$C$12,MATCH(D31,RatingGrades!$B$6:$B$12,0)) -> 0.005 | G31: =NORMSDIST(NORMSINV($F31)+S$16+W$16) -> 0.0063338651 | H31: =NORMSDIST(NORMSINV($F31)+T$16+X$16) -> 0.0058219493 | I31: =NORMSDIST(NORMSINV($F31)+U$16+Y$16) -> 0.0051264449 | J31: =NORMSDIST(NORMSINV($F31)+V$16+Z$16) -> 0.0051827177 | K31: =G31/$F31 -> 1.266773 | L31: =H31/$F31 -> 1.1643899 | M31: =I31/$F31 -> 1.025289 | N31: =J31/$F31 -> 1.0365435
B32: =$B$16 -> S01 | C32: =$C$16 -> Agriculture, Forestry & Fishing | D32: MR4 | E32: =B32&"|"&D32 -> S01|MR4 | F32: =INDEX(RatingGrades!$C$6:$C$12,MATCH(D32,RatingGrades!$B$6:$B$12,0)) -> 0.01 | G32: =NORMSDIST(NORMSINV($F32)+S$16+W$16) -> 0.01243246 | H32: =NORMSDIST(NORMSINV($F32)+T$16+X$16) -> 0.011504803 | I32: =NORMSDIST(NORMSINV($F32)+U$16+Y$16) -> 0.010232811 | J32: =NORMSDIST(NORMSINV($F32)+V$16+Z$16) -> 0.01033626 | K32: =G32/$F32 -> 1.243246 | L32: =H32/$F32 -> 1.1504803 | M32: =I32/$F32 -> 1.0232811 | N32: =J32/$F32 -> 1.033626
B33: =$B$16 -> S01 | C33: =$C$16 -> Agriculture, Forestry & Fishing | D33: MR5 | E33: =B33&"|"&D33 -> S01|MR5 | F33: =INDEX(RatingGrades!$C$6:$C$12,MATCH(D33,RatingGrades!$B$6:$B$12,0)) -> 0.02 | G33: =NORMSDIST(NORMSINV($F33)+S$16+W$16) -> 0.024367892 | H33: =NORMSDIST(NORMSINV($F33)+T$16+X$16) -> 0.022713651 | I33: =NORMSDIST(NORMSINV($F33)+U$16+Y$16) -> 0.02042244 | J33: =NORMSDIST(NORMSINV($F33)+V$16+Z$16) -> 0.020609834 | K33: =G33/$F33 -> 1.2183946 | L33: =H33/$F33 -> 1.1356826 | M33: =I33/$F33 -> 1.021122 | N33: =J33/$F33 -> 1.0304917
B34: =$B$16 -> S01 | C34: =$C$16 -> Agriculture, Forestry & Fishing | D34: MR6 | E34: =B34&"|"&D34 -> S01|MR6 | F34: =INDEX(RatingGrades!$C$6:$C$12,MATCH(D34,RatingGrades!$B$6:$B$12,0)) -> 0.045 | G34: =NORMSDIST(NORMSINV($F34)+S$16+W$16) -> 0.05342173 | H34: =NORMSDIST(NORMSINV($F34)+T$16+X$16) -> 0.050261341 | I34: =NORMSDIST(NORMSINV($F34)+U$16+Y$16) -> 0.045825715 | J34: =NORMSDIST(NORMSINV($F34)+V$16+Z$16) -> 0.046191187 | K34: =G34/$F34 -> 1.1871496 | L34: =H34/$F34 -> 1.1169187 | M34: =I34/$F34 -> 1.0183492 | N34: =J34/$F34 -> 1.0264708
B35: =$B$16 -> S01 | C35: =$C$16 -> Agriculture, Forestry & Fishing | D35: MR7 | E35: =B35&"|"&D35 -> S01|MR7 | F35: =INDEX(RatingGrades!$C$6:$C$12,MATCH(D35,RatingGrades!$B$6:$B$12,0)) -> 0.1 | G35: =NORMSDIST(NORMSINV($F35)+S$16+W$16) -> 0.11532259 | H35: =NORMSDIST(NORMSINV($F35)+T$16+X$16) -> 0.10963364 | I35: =NORMSDIST(NORMSINV($F35)+U$16+Y$16) -> 0.10152608 | J35: =NORMSDIST(NORMSINV($F35)+V$16+Z$16) -> 0.1021998 | K35: =G35/$F35 -> 1.1532259 | L35: =H35/$F35 -> 1.0963364 | M35: =I35/$F35 -> 1.0152608 | N35: =J35/$F35 -> 1.021998
B36: =$B$17 -> S02 | C36: =$C$17 -> Oil & Gas Extraction | D36: MR1 | E36: =B36&"|"&D36 -> S02|MR1 | F36: =INDEX(RatingGrades!$C$6:$C$12,MATCH(D36,RatingGrades!$B$6:$B$12,0)) -> 0.001 | G36: =NORMSDIST(NORMSINV($F36)+S$17+W$17) -> 0.0015897701 | H36: =NORMSDIST(NORMSINV($F36)+T$17+X$17) -> 0.0013027372 | I36: =NORMSDIST(NORMSINV($F36)+U$17+Y$17) -> 0.001020723 | J36: =NORMSDIST(NORMSINV($F36)+V$17+Z$17) -> 0.001055015 | K36: =G36/$F36 -> 1.5897701 | L36: =H36/$F36 -> 1.3027372 | M36: =I36/$F36 -> 1.020723 | N36: =J36/$F36 -> 1.055015
B37: =$B$17 -> S02 | C37: =$C$17 -> Oil & Gas Extraction | D37: MR2 | E37: =B37&"|"&D37 -> S02|MR2 | F37: =INDEX(RatingGrades!$C$6:$C$12,MATCH(D37,RatingGrades!$B$6:$B$12,0)) -> 0.0025 | G37: =NORMSDIST(NORMSINV($F37)+S$17+W$17) -> 0.0038308392 | H37: =NORMSDIST(NORMSINV($F37)+T$17+X$17) -> 0.0031896856 | I37: =NORMSDIST(NORMSINV($F37)+U$17+Y$17) -> 0.0025477236 | J37: =NORMSDIST(NORMSINV($F37)+V$17+Z$17) -> 0.0026265174 | K37: =G37/$F37 -> 1.5323357 | L37: =H37/$F37 -> 1.2758743 | M37: =I37/$F37 -> 1.0190894 | N37: =J37/$F37 -> 1.0506069
B38: =$B$17 -> S02 | C38: =$C$17 -> Oil & Gas Extraction | D38: MR3 | E38: =B38&"|"&D38 -> S02|MR3 | F38: =INDEX(RatingGrades!$C$6:$C$12,MATCH(D38,RatingGrades!$B$6:$B$12,0)) -> 0.005 | G38: =NORMSDIST(NORMSINV($F38)+S$17+W$17) -> 0.0074372165 | H38: =NORMSDIST(NORMSINV($F38)+T$17+X$17) -> 0.0062728378 | I38: =NORMSDIST(NORMSINV($F38)+U$17+Y$17) -> 0.0050888537 | J38: =NORMSDIST(NORMSINV($F38)+V$17+Z$17) -> 0.0052352843 | K38: =G38/$F38 -> 1.4874433 | L38: =H38/$F38 -> 1.2545676 | M38: =I38/$F38 -> 1.0177707 | N38: =J38/$F38 -> 1.0470569
B39: =$B$17 -> S02 | C39: =$C$17 -> Oil & Gas Extraction | D39: MR4 | E39: =B39&"|"&D39 -> S02|MR4 | F39: =INDEX(RatingGrades!$C$6:$C$12,MATCH(D39,RatingGrades!$B$6:$B$12,0)) -> 0.01 | G39: =NORMSDIST(NORMSINV($F39)+S$17+W$17) -> 0.014409978 | H39: =NORMSDIST(NORMSINV($F39)+T$17+X$17) -> 0.012322229 | I39: =NORMSDIST(NORMSINV($F39)+U$17+Y$17) -> 0.01016365 | J39: =NORMSDIST(NORMSINV($F39)+V$17+Z$17) -> 0.010432808 | K39: =G39/$F39 -> 1.4409978 | L39: =H39/$F39 -> 1.2322229 | M39: =I39/$F39 -> 1.016365 | N39: =J39/$F39 -> 1.0432808
B40: =$B$17 -> S02 | C40: =$C$17 -> Oil & Gas Extraction | D40: MR5 | E40: =B40&"|"&D40 -> S02|MR5 | F40: =INDEX(RatingGrades!$C$6:$C$12,MATCH(D40,RatingGrades!$B$6:$B$12,0)) -> 0.02 | G40: =NORMSDIST(NORMSINV($F40)+S$17+W$17) -> 0.02785217 | H40: =NORMSDIST(NORMSINV($F40)+T$17+X$17) -> 0.024172019 | I40: =NORMSDIST(NORMSINV($F40)+U$17+Y$17) -> 0.02029705 | J40: =NORMSDIST(NORMSINV($F40)+V$17+Z$17) -> 0.020784553 | K40: =G40/$F40 -> 1.3926085 | L40: =H40/$F40 -> 1.2086009 | M40: =I40/$F40 -> 1.0148525 | N40: =J40/$F40 -> 1.0392276
B41: =$B$17 -> S02 | C41: =$C$17 -> Oil & Gas Extraction | D41: MR6 | E41: =B41&"|"&D41 -> S02|MR6 | F41: =INDEX(RatingGrades!$C$6:$C$12,MATCH(D41,RatingGrades!$B$6:$B$12,0)) -> 0.045 | G41: =NORMSDIST(NORMSINV($F41)+S$17+W$17) -> 0.059974182 | H41: =NORMSDIST(NORMSINV($F41)+T$17+X$17) -> 0.053049263 | I41: =NORMSDIST(NORMSINV($F41)+U$17+Y$17) -> 0.045580891 | J41: =NORMSDIST(NORMSINV($F41)+V$17+Z$17) -> 0.046531495 | K41: =G41/$F41 -> 1.3327596 | L41: =H41/$F41 -> 1.1788725 | M41: =I41/$F41 -> 1.0129087 | N41: =J41/$F41 -> 1.0340332
B42: =$B$17 -> S02 | C42: =$C$17 -> Oil & Gas Extraction | D42: MR7 | E42: =B42&"|"&D42 -> S02|MR7 | F42: =INDEX(RatingGrades!$C$6:$C$12,MATCH(D42,RatingGrades!$B$6:$B$12,0)) -> 0.1 | G42: =NORMSDIST(NORMSINV($F42)+S$17+W$17) -> 0.12690496 | H42: =NORMSDIST(NORMSINV($F42)+T$17+X$17) -> 0.11465574 | I42: =NORMSDIST(NORMSINV($F42)+U$17+Y$17) -> 0.10107416 | J42: =NORMSDIST(NORMSINV($F42)+V$17+Z$17) -> 0.1028262 | K42: =G42/$F42 -> 1.2690496 | L42: =H42/$F42 -> 1.1465574 | M42: =I42/$F42 -> 1.0107416 | N42: =J42/$F42 -> 1.028262
B43: =$B$18 -> S03 | C43: =$C$18 -> Mining & Quarrying (non-oil) | D43: MR1 | E43: =B43&"|"&D43 -> S03|MR1 | F43: =INDEX(RatingGrades!$C$6:$C$12,MATCH(D43,RatingGrades!$B$6:$B$12,0)) -> 0.001 | G43: =NORMSDIST(NORMSINV($F43)+S$18+W$18) -> 0.0015034886 | H43: =NORMSDIST(NORMSINV($F43)+T$18+X$18) -> 0.0012688953 | I43: =NORMSDIST(NORMSINV($F43)+U$18+Y$18) -> 0.0010262364 | J43: =NORMSDIST(NORMSINV($F43)+V$18+Z$18) -> 0.0010529296 | K43: =G43/$F43 -> 1.5034886 | L43: =H43/$F43 -> 1.2688953 | M43: =I43/$F43 -> 1.0262364 | N43: =J43/$F43 -> 1.0529296
B44: =$B$18 -> S03 | C44: =$C$18 -> Mining & Quarrying (non-oil) | D44: MR2 | E44: =B44&"|"&D44 -> S03|MR2 | F44: =INDEX(RatingGrades!$C$6:$C$12,MATCH(D44,RatingGrades!$B$6:$B$12,0)) -> 0.0025 | G44: =NORMSDIST(NORMSINV($F44)+S$18+W$18) -> 0.0036392573 | H44: =NORMSDIST(NORMSINV($F44)+T$18+X$18) -> 0.0031133312 | I44: =NORMSDIST(NORMSINV($F44)+U$18+Y$18) -> 0.0025604068 | J44: =NORMSDIST(NORMSINV($F44)+V$18+Z$18) -> 0.0026217319 | K44: =G44/$F44 -> 1.4557029 | L44: =H44/$F44 -> 1.2453325 | M44: =I44/$F44 -> 1.0241627 | N44: =J44/$F44 -> 1.0486928
B45: =$B$18 -> S03 | C45: =$C$18 -> Mining & Quarrying (non-oil) | D45: MR3 | E45: =B45&"|"&D45 -> S03|MR3 | F45: =INDEX(RatingGrades!$C$6:$C$12,MATCH(D45,RatingGrades!$B$6:$B$12,0)) -> 0.005 | G45: =NORMSDIST(NORMSINV($F45)+S$18+W$18) -> 0.0070909886 | H45: =NORMSDIST(NORMSINV($F45)+T$18+X$18) -> 0.0061330374 | I45: =NORMSDIST(NORMSINV($F45)+U$18+Y$18) -> 0.0051124468 | J45: =NORMSDIST(NORMSINV($F45)+V$18+Z$18) -> 0.0052264005 | K45: =G45/$F45 -> 1.4181977 | L45: =H45/$F45 -> 1.2266075 | M45: =I45/$F45 -> 1.0224894 | N45: =J45/$F45 -> 1.0452801
B46: =$B$18 -> S03 | C46: =$C$18 -> Mining & Quarrying (non-oil) | D46: MR4 | E46: =B46&"|"&D46 -> S03|MR4 | F46: =INDEX(RatingGrades!$C$6:$C$12,MATCH(D46,RatingGrades!$B$6:$B$12,0)) -> 0.01 | G46: =NORMSDIST(NORMSINV($F46)+S$18+W$18) -> 0.013792465 | H46: =NORMSDIST(NORMSINV($F46)+T$18+X$18) -> 0.012069354 | I46: =NORMSDIST(NORMSINV($F46)+U$18+Y$18) -> 0.010207062 | J46: =NORMSDIST(NORMSINV($F46)+V$18+Z$18) -> 0.010416497 | K46: =G46/$F46 -> 1.3792465 | L46: =H46/$F46 -> 1.2069354 | M46: =I46/$F46 -> 1.0207062 | N46: =J46/$F46 -> 1.0416497
B47: =$B$18 -> S03 | C47: =$C$18 -> Mining & Quarrying (non-oil) | D47: MR5 | E47: =B47&"|"&D47 -> S03|MR5 | F47: =INDEX(RatingGrades!$C$6:$C$12,MATCH(D47,RatingGrades!$B$6:$B$12,0)) -> 0.02 | G47: =NORMSDIST(NORMSINV($F47)+S$18+W$18) -> 0.02676996 | H47: =NORMSDIST(NORMSINV($F47)+T$18+X$18) -> 0.023721978 | I47: =NORMSDIST(NORMSINV($F47)+U$18+Y$18) -> 0.020375767 | J47: =NORMSDIST(NORMSINV($F47)+V$18+Z$18) -> 0.020755048 | K47: =G47/$F47 -> 1.338498 | L47: =H47/$F47 -> 1.1860989 | M47: =I47/$F47 -> 1.0187884 | N47: =J47/$F47 -> 1.0377524
B48: =$B$18 -> S03 | C48: =$C$18 -> Mining & Quarrying (non-oil) | D48: MR6 | E48: =B48&"|"&D48 -> S03|MR6 | F48: =INDEX(RatingGrades!$C$6:$C$12,MATCH(D48,RatingGrades!$B$6:$B$12,0)) -> 0.045 | G48: =NORMSDIST(NORMSINV($F48)+S$18+W$18) -> 0.057953345 | H48: =NORMSDIST(NORMSINV($F48)+T$18+X$18) -> 0.05219173 | I48: =NORMSDIST(NORMSINV($F48)+U$18+Y$18) -> 0.045734612 | J48: =NORMSDIST(NORMSINV($F48)+V$18+Z$18) -> 0.046474056 | K48: =G48/$F48 -> 1.2878521 | L48: =H48/$F48 -> 1.1598162 | M48: =I48/$F48 -> 1.0163247 | N48: =J48/$F48 -> 1.0327568
B49: =$B$18 -> S03 | C49: =$C$18 -> Mining & Quarrying (non-oil) | D49: MR7 | E49: =B49&"|"&D49 -> S03|MR7 | F49: =INDEX(RatingGrades!$C$6:$C$12,MATCH(D49,RatingGrades!$B$6:$B$12,0)) -> 0.1 | G49: =NORMSDIST(NORMSINV($F49)+S$18+W$18) -> 0.12336204 | H49: =NORMSDIST(NORMSINV($F49)+T$18+X$18) -> 0.11311681 | I49: =NORMSDIST(NORMSINV($F49)+U$18+Y$18) -> 0.10135797 | J49: =NORMSDIST(NORMSINV($F49)+V$18+Z$18) -> 0.10272054 | K49: =G49/$F49 -> 1.2336204 | L49: =H49/$F49 -> 1.1311681 | M49: =I49/$F49 -> 1.0135797 | N49: =J49/$F49 -> 1.0272054
B50: =$B$19 -> S04 | C50: =$C$19 -> Manufacturing | D50: MR1 | E50: =B50&"|"&D50 -> S04|MR1 | F50: =INDEX(RatingGrades!$C$6:$C$12,MATCH(D50,RatingGrades!$B$6:$B$12,0)) -> 0.001 | G50: =NORMSDIST(NORMSINV($F50)+S$19+W$19) -> 0.0017443532 | H50: =NORMSDIST(NORMSINV($F50)+T$19+X$19) -> 0.0013692747 | I50: =NORMSDIST(NORMSINV($F50)+U$19+Y$19) -> 0.0010234167 | J50: =NORMSDIST(NORMSINV($F50)+V$19+Z$19) -> 0.0010685842 | K50: =G50/$F50 -> 1.7443532 | L50: =H50/$F50 -> 1.3692747 | M50: =I50/$F50 -> 1.0234167 | N50: =J50/$F50 -> 1.0685842
B51: =$B$19 -> S04 | C51: =$C$19 -> Manufacturing | D51: MR2 | E51: =B51&"|"&D51 -> S04|MR2 | F51: =INDEX(RatingGrades!$C$6:$C$12,MATCH(D51,RatingGrades!$B$6:$B$12,0)) -> 0.0025 | G51: =NORMSDIST(NORMSINV($F51)+S$19+W$19) -> 0.0041718405 | H51: =NORMSDIST(NORMSINV($F51)+T$19+X$19) -> 0.0033393148 | I51: =NORMSDIST(NORMSINV($F51)+U$19+Y$19) -> 0.0025539209 | J51: =NORMSDIST(NORMSINV($F51)+V$19+Z$19) -> 0.0026576356 | K51: =G51/$F51 -> 1.6687362 | L51: =H51/$F51 -> 1.3357259 | M51: =I51/$F51 -> 1.0215684 | N51: =J51/$F51 -> 1.0630542
B52: =$B$19 -> S04 | C52: =$C$19 -> Manufacturing | D52: MR3 | E52: =B52&"|"&D52 -> S04|MR3 | F52: =INDEX(RatingGrades!$C$6:$C$12,MATCH(D52,RatingGrades!$B$6:$B$12,0)) -> 0.005 | G52: =NORMSDIST(NORMSINV($F52)+S$19+W$19) -> 0.0080501924 | H52: =NORMSDIST(NORMSINV($F52)+T$19+X$19) -> 0.0065460655 | I52: =NORMSDIST(NORMSINV($F52)+U$19+Y$19) -> 0.0051003829 | J52: =NORMSDIST(NORMSINV($F52)+V$19+Z$19) -> 0.0052930235 | K52: =G52/$F52 -> 1.6100385 | L52: =H52/$F52 -> 1.3092131 | M52: =I52/$F52 -> 1.0200766 | N52: =J52/$F52 -> 1.0586047
B53: =$B$19 -> S04 | C53: =$C$19 -> Manufacturing | D53: MR4 | E53: =B53&"|"&D53 -> S04|MR4 | F53: =INDEX(RatingGrades!$C$6:$C$12,MATCH(D53,RatingGrades!$B$6:$B$12,0)) -> 0.01 | G53: =NORMSDIST(NORMSINV($F53)+S$19+W$19) -> 0.015496968 | H53: =NORMSDIST(NORMSINV($F53)+T$19+X$19) -> 0.012815023 | I53: =NORMSDIST(NORMSINV($F53)+U$19+Y$19) -> 0.010184866 | J53: =NORMSDIST(NORMSINV($F53)+V$19+Z$19) -> 0.01053876 | K53: =G53/$F53 -> 1.5496968 | L53: =H53/$F53 -> 1.2815023 | M53: =I53/$F53 -> 1.0184866 | N53: =J53/$F53 -> 1.053876
B54: =$B$19 -> S04 | C54: =$C$19 -> Manufacturing | D54: MR5 | E54: =B54&"|"&D54 -> S04|MR5 | F54: =INDEX(RatingGrades!$C$6:$C$12,MATCH(D54,RatingGrades!$B$6:$B$12,0)) -> 0.02 | G54: =NORMSDIST(NORMSINV($F54)+S$19+W$19) -> 0.029745201 | H54: =NORMSDIST(NORMSINV($F54)+T$19+X$19) -> 0.025046272 | I54: =NORMSDIST(NORMSINV($F54)+U$19+Y$19) -> 0.020335525 | J54: =NORMSDIST(NORMSINV($F54)+V$19+Z$19) -> 0.020976098 | K54: =G54/$F54 -> 1.4872601 | L54: =H54/$F54 -> 1.2523136 | M54: =I54/$F54 -> 1.0167763 | N54: =J54/$F54 -> 1.0488049
B55: =$B$19 -> S04 | C55: =$C$19 -> Manufacturing | D55: MR6 | E55: =B55&"|"&D55 -> S04|MR6 | F55: =INDEX(RatingGrades!$C$6:$C$12,MATCH(D55,RatingGrades!$B$6:$B$12,0)) -> 0.045 | G55: =NORMSDIST(NORMSINV($F55)+S$19+W$19) -> 0.063479982 | H55: =NORMSDIST(NORMSINV($F55)+T$19+X$19) -> 0.05470821 | I55: =NORMSDIST(NORMSINV($F55)+U$19+Y$19) -> 0.045656037 | J55: =NORMSDIST(NORMSINV($F55)+V$19+Z$19) -> 0.046904086 | K55: =G55/$F55 -> 1.4106663 | L55: =H55/$F55 -> 1.215738 | M55: =I55/$F55 -> 1.0145786 | N55: =J55/$F55 -> 1.042313
B56: =$B$19 -> S04 | C56: =$C$19 -> Manufacturing | D56: MR7 | E56: =B56&"|"&D56 -> S04|MR7 | F56: =INDEX(RatingGrades!$C$6:$C$12,MATCH(D56,RatingGrades!$B$6:$B$12,0)) -> 0.1 | G56: =NORMSDIST(NORMSINV($F56)+S$19+W$19) -> 0.13299293 | H56: =NORMSDIST(NORMSINV($F56)+T$19+X$19) -> 0.11761863 | I56: =NORMSDIST(NORMSINV($F56)+U$19+Y$19) -> 0.10121293 | J56: =NORMSDIST(NORMSINV($F56)+V$19+Z$19) -> 0.10351097 | K56: =G56/$F56 -> 1.3299293 | L56: =H56/$F56 -> 1.1761863 | M56: =I56/$F56 -> 1.0121293 | N56: =J56/$F56 -> 1.0351097
B57: =$B$20 -> S05 | C57: =$C$20 -> Electricity, Gas, Water & Waste | D57: MR1 | E57: =B57&"|"&D57 -> S05|MR1 | F57: =INDEX(RatingGrades!$C$6:$C$12,MATCH(D57,RatingGrades!$B$6:$B$12,0)) -> 0.001 | G57: =NORMSDIST(NORMSINV($F57)+S$20+W$20) -> 0.0018913201 | H57: =NORMSDIST(NORMSINV($F57)+T$20+X$20) -> 0.0014344035 | I57: =NORMSDIST(NORMSINV($F57)+U$20+Y$20) -> 0.0010287801 | J57: =NORMSDIST(NORMSINV($F57)+V$20+Z$20) -> 0.0010838405 | K57: =G57/$F57 -> 1.8913201 | L57: =H57/$F57 -> 1.4344035 | M57: =I57/$F57 -> 1.0287801 | N57: =J57/$F57 -> 1.0838405
B58: =$B$20 -> S05 | C58: =$C$20 -> Electricity, Gas, Water & Waste | D58: MR2 | E58: =B58&"|"&D58 -> S05|MR2 | F58: =INDEX(RatingGrades!$C$6:$C$12,MATCH(D58,RatingGrades!$B$6:$B$12,0)) -> 0.0025 | G58: =NORMSDIST(NORMSINV($F58)+S$20+W$20) -> 0.0044935717 | H58: =NORMSDIST(NORMSINV($F58)+T$20+X$20) -> 0.0034851692 | I58: =NORMSDIST(NORMSINV($F58)+U$20+Y$20) -> 0.0025662564 | J58: =NORMSDIST(NORMSINV($F58)+V$20+Z$20) -> 0.0026925831 | K58: =G58/$F58 -> 1.7974287 | L58: =H58/$F58 -> 1.3940677 | M58: =I58/$F58 -> 1.0265026 | N58: =J58/$F58 -> 1.0770332
B59: =$B$20 -> S05 | C59: =$C$20 -> Electricity, Gas, Water & Waste | D59: MR3 | E59: =B59&"|"&D59 -> S05|MR3 | F59: =INDEX(RatingGrades!$C$6:$C$12,MATCH(D59,RatingGrades!$B$6:$B$12,0)) -> 0.005 | G59: =NORMSDIST(NORMSINV($F59)+S$20+W$20) -> 0.0086249298 | H59: =NORMSDIST(NORMSINV($F59)+T$20+X$20) -> 0.0068114983 | I59: =NORMSDIST(NORMSINV($F59)+U$20+Y$20) -> 0.0051233252 | J59: =NORMSDIST(NORMSINV($F59)+V$20+Z$20) -> 0.0053578076 | K59: =G59/$F59 -> 1.724986 | L59: =H59/$F59 -> 1.3622997 | M59: =I59/$F59 -> 1.024665 | N59: =J59/$F59 -> 1.0715615
B60: =$B$20 -> S05 | C60: =$C$20 -> Electricity, Gas, Water & Waste | D60: MR4 | E60: =B60&"|"&D60 -> S05|MR4 | F60: =INDEX(RatingGrades!$C$6:$C$12,MATCH(D60,RatingGrades!$B$6:$B$12,0)) -> 0.01 | G60: =NORMSDIST(NORMSINV($F60)+S$20+W$20) -> 0.016509305 | H60: =NORMSDIST(NORMSINV($F60)+T$20+X$20) -> 0.013292009 | I60: =NORMSDIST(NORMSINV($F60)+U$20+Y$20) -> 0.010227073 | J60: =NORMSDIST(NORMSINV($F60)+V$20+Z$20) -> 0.01065752 | K60: =G60/$F60 -> 1.6509305 | L60: =H60/$F60 -> 1.3292009 | M60: =I60/$F60 -> 1.0227073 | N60: =J60/$F60 -> 1.065752
B61: =$B$20 -> S05 | C61: =$C$20 -> Electricity, Gas, Water & Waste | D61: MR5 | E61: =B61&"|"&D61 -> S05|MR5 | F61: =INDEX(RatingGrades!$C$6:$C$12,MATCH(D61,RatingGrades!$B$6:$B$12,0)) -> 0.02 | G61: =NORMSDIST(NORMSINV($F61)+S$20+W$20) -> 0.031495291 | H61: =NORMSDIST(NORMSINV($F61)+T$20+X$20) -> 0.025889102 | I61: =NORMSDIST(NORMSINV($F61)+U$20+Y$20) -> 0.02041204 | J61: =NORMSDIST(NORMSINV($F61)+V$20+Z$20) -> 0.021190563 | K61: =G61/$F61 -> 1.5747646 | L61: =H61/$F61 -> 1.2944551 | M61: =I61/$F61 -> 1.020602 | N61: =J61/$F61 -> 1.0595281
B62: =$B$20 -> S05 | C62: =$C$20 -> Electricity, Gas, Water & Waste | D62: MR6 | E62: =B62&"|"&D62 -> S05|MR6 | F62: =INDEX(RatingGrades!$C$6:$C$12,MATCH(D62,RatingGrades!$B$6:$B$12,0)) -> 0.045 | G62: =NORMSDIST(NORMSINV($F62)+S$20+W$20) -> 0.06668984 | H62: =NORMSDIST(NORMSINV($F62)+T$20+X$20) -> 0.05629914 | I62: =NORMSDIST(NORMSINV($F62)+U$20+Y$20) -> 0.045805418 | J62: =NORMSDIST(NORMSINV($F62)+V$20+Z$20) -> 0.047320658 | K62: =G62/$F62 -> 1.4819964 | L62: =H62/$F62 -> 1.251092 | M62: =I62/$F62 -> 1.0178982 | N62: =J62/$F62 -> 1.0515702
B63: =$B$20 -> S05 | C63: =$C$20 -> Electricity, Gas, Water & Waste | D63: MR7 | E63: =B63&"|"&D63 -> S05|MR7 | F63: =INDEX(RatingGrades!$C$6:$C$12,MATCH(D63,RatingGrades!$B$6:$B$12,0)) -> 0.1 | G63: =NORMSDIST(NORMSINV($F63)+S$20+W$20) -> 0.13850501 | H63: =NORMSDIST(NORMSINV($F63)+T$20+X$20) -> 0.12044285 | I63: =NORMSDIST(NORMSINV($F63)+U$20+Y$20) -> 0.10148863 | J63: =NORMSDIST(NORMSINV($F63)+V$20+Z$20) -> 0.10427531 | K63: =G63/$F63 -> 1.3850501 | L63: =H63/$F63 -> 1.2044285 | M63: =I63/$F63 -> 1.0148863 | N63: =J63/$F63 -> 1.0427531
B64: =$B$21 -> S06 | C64: =$C$21 -> Construction | D64: MR1 | E64: =B64&"|"&D64 -> S06|MR1 | F64: =INDEX(RatingGrades!$C$6:$C$12,MATCH(D64,RatingGrades!$B$6:$B$12,0)) -> 0.001 | G64: =NORMSDIST(NORMSINV($F64)+S$21+W$21) -> 0.0010945439 | H64: =NORMSDIST(NORMSINV($F64)+T$21+X$21) -> 0.0010995561 | I64: =NORMSDIST(NORMSINV($F64)+U$21+Y$21) -> 0.00102049 | J64: =NORMSDIST(NORMSINV($F64)+V$21+Z$21) -> 0.0010199641 | K64: =G64/$F64 -> 1.0945439 | L64: =H64/$F64 -> 1.0995561 | M64: =I64/$F64 -> 1.02049 | N64: =J64/$F64 -> 1.0199641
B65: =$B$21 -> S06 | C65: =$C$21 -> Construction | D65: MR2 | E65: =B65&"|"&D65 -> S06|MR2 | F65: =INDEX(RatingGrades!$C$6:$C$12,MATCH(D65,RatingGrades!$B$6:$B$12,0)) -> 0.0025 | G65: =NORMSDIST(NORMSINV($F65)+S$21+W$21) -> 0.0027170765 | H65: =NORMSDIST(NORMSINV($F65)+T$21+X$21) -> 0.0027285391 | I65: =NORMSDIST(NORMSINV($F65)+U$21+Y$21) -> 0.0025471876 | J65: =NORMSDIST(NORMSINV($F65)+V$21+Z$21) -> 0.0025459773 | K65: =G65/$F65 -> 1.0868306 | L65: =H65/$F65 -> 1.0914157 | M65: =I65/$F65 -> 1.018875 | N65: =J65/$F65 -> 1.0183909
B66: =$B$21 -> S06 | C66: =$C$21 -> Construction | D66: MR3 | E66: =B66&"|"&D66 -> S06|MR3 | F66: =INDEX(RatingGrades!$C$6:$C$12,MATCH(D66,RatingGrades!$B$6:$B$12,0)) -> 0.005 | G66: =NORMSDIST(NORMSINV($F66)+S$21+W$21) -> 0.0054031748 | H66: =NORMSDIST(NORMSINV($F66)+T$21+X$21) -> 0.0054243955 | I66: =NORMSDIST(NORMSINV($F66)+U$21+Y$21) -> 0.0050878563 | J66: =NORMSDIST(NORMSINV($F66)+V$21+Z$21) -> 0.0050856045 | K66: =G66/$F66 -> 1.080635 | L66: =H66/$F66 -> 1.0848791 | M66: =I66/$F66 -> 1.0175713 | N66: =J66/$F66 -> 1.0171209
B67: =$B$21 -> S06 | C67: =$C$21 -> Construction | D67: MR4 | E67: =B67&"|"&D67 -> S06|MR4 | F67: =INDEX(RatingGrades!$C$6:$C$12,MATCH(D67,RatingGrades!$B$6:$B$12,0)) -> 0.01 | G67: =NORMSDIST(NORMSINV($F67)+S$21+W$21) -> 0.010740611 | H67: =NORMSDIST(NORMSINV($F67)+T$21+X$21) -> 0.010779456 | I67: =NORMSDIST(NORMSINV($F67)+U$21+Y$21) -> 0.010161814 | J67: =NORMSDIST(NORMSINV($F67)+V$21+Z$21) -> 0.01015767 | K67: =G67/$F67 -> 1.0740611 | L67: =H67/$F67 -> 1.0779456 | M67: =I67/$F67 -> 1.0161814 | N67: =J67/$F67 -> 1.015767
B68: =$B$21 -> S06 | C68: =$C$21 -> Construction | D68: MR5 | E68: =B68&"|"&D68 -> S06|MR5 | F68: =INDEX(RatingGrades!$C$6:$C$12,MATCH(D68,RatingGrades!$B$6:$B$12,0)) -> 0.02 | G68: =NORMSDIST(NORMSINV($F68)+S$21+W$21) -> 0.021340468 | H68: =NORMSDIST(NORMSINV($F68)+T$21+X$21) -> 0.021410508 | I68: =NORMSDIST(NORMSINV($F68)+U$21+Y$21) -> 0.020293721 | J68: =NORMSDIST(NORMSINV($F68)+V$21+Z$21) -> 0.020286205 | K68: =G68/$F68 -> 1.0670234 | L68: =H68/$F68 -> 1.0705254 | M68: =I68/$F68 -> 1.0146861 | N68: =J68/$F68 -> 1.0143102
B69: =$B$21 -> S06 | C69: =$C$21 -> Construction | D69: MR6 | E69: =B69&"|"&D69 -> S06|MR6 | F69: =INDEX(RatingGrades!$C$6:$C$12,MATCH(D69,RatingGrades!$B$6:$B$12,0)) -> 0.045 | G69: =NORMSDIST(NORMSINV($F69)+S$21+W$21) -> 0.047611458 | H69: =NORMSDIST(NORMSINV($F69)+T$21+X$21) -> 0.047747223 | I69: =NORMSDIST(NORMSINV($F69)+U$21+Y$21) -> 0.045574388 | J69: =NORMSDIST(NORMSINV($F69)+V$21+Z$21) -> 0.045559704 | K69: =G69/$F69 -> 1.0580324 | L69: =H69/$F69 -> 1.0610494 | M69: =I69/$F69 -> 1.0127642 | N69: =J69/$F69 -> 1.0124379
B70: =$B$21 -> S06 | C70: =$C$21 -> Construction | D70: MR7 | E70: =B70&"|"&D70 -> S06|MR7 | F70: =INDEX(RatingGrades!$C$6:$C$12,MATCH(D70,RatingGrades!$B$6:$B$12,0)) -> 0.1 | G70: =NORMSDIST(NORMSINV($F70)+S$21+W$21) -> 0.10480808 | H70: =NORMSDIST(NORMSINV($F70)+T$21+X$21) -> 0.1050566 | I70: =NORMSDIST(NORMSINV($F70)+U$21+Y$21) -> 0.10106215 | J70: =NORMSDIST(NORMSINV($F70)+V$21+Z$21) -> 0.10103503 | K70: =G70/$F70 -> 1.0480808 | L70: =H70/$F70 -> 1.050566 | M70: =I70/$F70 -> 1.0106215 | N70: =J70/$F70 -> 1.0103503
B71: =$B$22 -> S07 | C71: =$C$22 -> Wholesale & Retail Trade | D71: MR1 | E71: =B71&"|"&D71 -> S07|MR1 | F71: =INDEX(RatingGrades!$C$6:$C$12,MATCH(D71,RatingGrades!$B$6:$B$12,0)) -> 0.001 | G71: =NORMSDIST(NORMSINV($F71)+S$22+W$22) -> 0.0011018655 | H71: =NORMSDIST(NORMSINV($F71)+T$22+X$22) -> 0.0010967169 | I71: =NORMSDIST(NORMSINV($F71)+U$22+Y$22) -> 0.0010067883 | J71: =NORMSDIST(NORMSINV($F71)+V$22+Z$22) -> 0.0010100076 | K71: =G71/$F71 -> 1.1018655 | L71: =H71/$F71 -> 1.0967169 | M71: =I71/$F71 -> 1.0067883 | N71: =J71/$F71 -> 1.0100076
B72: =$B$22 -> S07 | C72: =$C$22 -> Wholesale & Retail Trade | D72: MR2 | E72: =B72&"|"&D72 -> S07|MR2 | F72: =INDEX(RatingGrades!$C$6:$C$12,MATCH(D72,RatingGrades!$B$6:$B$12,0)) -> 0.0025 | G72: =NORMSDIST(NORMSINV($F72)+S$22+W$22) -> 0.0027338191 | H72: =NORMSDIST(NORMSINV($F72)+T$22+X$22) -> 0.0027220465 | I72: =NORMSDIST(NORMSINV($F72)+U$22+Y$22) -> 0.002515642 | J72: =NORMSDIST(NORMSINV($F72)+V$22+Z$22) -> 0.002523057 | K72: =G72/$F72 -> 1.0935276 | L72: =H72/$F72 -> 1.0888186 | M72: =I72/$F72 -> 1.0062568 | N72: =J72/$F72 -> 1.0092228
B73: =$B$22 -> S07 | C73: =$C$22 -> Wholesale & Retail Trade | D73: MR3 | E73: =B73&"|"&D73 -> S07|MR3 | F73: =INDEX(RatingGrades!$C$6:$C$12,MATCH(D73,RatingGrades!$B$6:$B$12,0)) -> 0.005 | G73: =NORMSDIST(NORMSINV($F73)+S$22+W$22) -> 0.0054341681 | H73: =NORMSDIST(NORMSINV($F73)+T$22+X$22) -> 0.0054123766 | I73: =NORMSDIST(NORMSINV($F73)+U$22+Y$22) -> 0.0050291367 | J73: =NORMSDIST(NORMSINV($F73)+V$22+Z$22) -> 0.005042944 | K73: =G73/$F73 -> 1.0868336 | L73: =H73/$F73 -> 1.0824753 | M73: =I73/$F73 -> 1.0058273 | N73: =J73/$F73 -> 1.0085888
B74: =$B$22 -> S07 | C74: =$C$22 -> Wholesale & Retail Trade | D74: MR4 | E74: =B74&"|"&D74 -> S07|MR4 | F74: =INDEX(RatingGrades!$C$6:$C$12,MATCH(D74,RatingGrades!$B$6:$B$12,0)) -> 0.01 | G74: =NORMSDIST(NORMSINV($F74)+S$22+W$22) -> 0.010797341 | H74: =NORMSDIST(NORMSINV($F74)+T$22+X$22) -> 0.010757457 | I74: =NORMSDIST(NORMSINV($F74)+U$22+Y$22) -> 0.010053691 | J74: =NORMSDIST(NORMSINV($F74)+V$22+Z$22) -> 0.010079125 | K74: =G74/$F74 -> 1.0797341 | L74: =H74/$F74 -> 1.0757457 | M74: =I74/$F74 -> 1.0053691 | N74: =J74/$F74 -> 1.0079125
B75: =$B$22 -> S07 | C75: =$C$22 -> Wholesale & Retail Trade | D75: MR5 | E75: =B75&"|"&D75 -> S07|MR5 | F75: =INDEX(RatingGrades!$C$6:$C$12,MATCH(D75,RatingGrades!$B$6:$B$12,0)) -> 0.02 | G75: =NORMSDIST(NORMSINV($F75)+S$22+W$22) -> 0.021442746 | H75: =NORMSDIST(NORMSINV($F75)+T$22+X$22) -> 0.021370845 | I75: =NORMSDIST(NORMSINV($F75)+U$22+Y$22) -> 0.020097512 | J75: =NORMSDIST(NORMSINV($F75)+V$22+Z$22) -> 0.020143686 | K75: =G75/$F75 -> 1.0721373 | L75: =H75/$F75 -> 1.0685422 | M75: =I75/$F75 -> 1.0048756 | N75: =J75/$F75 -> 1.0071843
B76: =$B$22 -> S07 | C76: =$C$22 -> Wholesale & Retail Trade | D76: MR6 | E76: =B76&"|"&D76 -> S07|MR6 | F76: =INDEX(RatingGrades!$C$6:$C$12,MATCH(D76,RatingGrades!$B$6:$B$12,0)) -> 0.045 | G76: =NORMSDIST(NORMSINV($F76)+S$22+W$22) -> 0.047809691 | H76: =NORMSDIST(NORMSINV($F76)+T$22+X$22) -> 0.047670349 | I76: =NORMSDIST(NORMSINV($F76)+U$22+Y$22) -> 0.045190828 | J76: =NORMSDIST(NORMSINV($F76)+V$22+Z$22) -> 0.045281141 | K76: =G76/$F76 -> 1.0624376 | L76: =H76/$F76 -> 1.0593411 | M76: =I76/$F76 -> 1.0042406 | N76: =J76/$F76 -> 1.0062476
B77: =$B$22 -> S07 | C77: =$C$22 -> Wholesale & Retail Trade | D77: MR7 | E77: =B77&"|"&D77 -> S07|MR7 | F77: =INDEX(RatingGrades!$C$6:$C$12,MATCH(D77,RatingGrades!$B$6:$B$12,0)) -> 0.1 | G77: =NORMSDIST(NORMSINV($F77)+S$22+W$22) -> 0.1051709 | H77: =NORMSDIST(NORMSINV($F77)+T$22+X$22) -> 0.1049159 | I77: =NORMSDIST(NORMSINV($F77)+U$22+Y$22) -> 0.10035317 | J77: =NORMSDIST(NORMSINV($F77)+V$22+Z$22) -> 0.10052022 | K77: =G77/$F77 -> 1.051709 | L77: =H77/$F77 -> 1.049159 | M77: =I77/$F77 -> 1.0035317 | N77: =J77/$F77 -> 1.0052022
B78: =$B$23 -> S08 | C78: =$C$23 -> Transport & Storage | D78: MR1 | E78: =B78&"|"&D78 -> S08|MR1 | F78: =INDEX(RatingGrades!$C$6:$C$12,MATCH(D78,RatingGrades!$B$6:$B$12,0)) -> 0.001 | G78: =NORMSDIST(NORMSINV($F78)+S$23+W$23) -> 0.001278705 | H78: =NORMSDIST(NORMSINV($F78)+T$23+X$23) -> 0.0011715746 | I78: =NORMSDIST(NORMSINV($F78)+U$23+Y$23) -> 0.0010150098 | J78: =NORMSDIST(NORMSINV($F78)+V$23+Z$23) -> 0.0010284186 | K78: =G78/$F78 -> 1.278705 | L78: =H78/$F78 -> 1.1715746 | M78: =I78/$F78 -> 1.0150098 | N78: =J78/$F78 -> 1.0284186
B79: =$B$23 -> S08 | C79: =$C$23 -> Transport & Storage | D79: MR2 | E79: =B79&"|"&D79 -> S08|MR2 | F79: =INDEX(RatingGrades!$C$6:$C$12,MATCH(D79,RatingGrades!$B$6:$B$12,0)) -> 0.0025 | G79: =NORMSDIST(NORMSINV($F79)+S$23+W$23) -> 0.0031354819 | H79: =NORMSDIST(NORMSINV($F79)+T$23+X$23) -> 0.0028927641 | I79: =NORMSDIST(NORMSINV($F79)+U$23+Y$23) -> 0.0025345747 | J79: =NORMSDIST(NORMSINV($F79)+V$23+Z$23) -> 0.0025654251 | K79: =G79/$F79 -> 1.2541927 | L79: =H79/$F79 -> 1.1571056 | M79: =I79/$F79 -> 1.0138299 | N79: =J79/$F79 -> 1.02617
B80: =$B$23 -> S08 | C80: =$C$23 -> Transport & Storage | D80: MR3 | E80: =B80&"|"&D80 -> S08|MR3 | F80: =INDEX(RatingGrades!$C$6:$C$12,MATCH(D80,RatingGrades!$B$6:$B$12,0)) -> 0.005 | G80: =NORMSDIST(NORMSINV($F80)+S$23+W$23) -> 0.0061736206 | H80: =NORMSDIST(NORMSINV($F80)+T$23+X$23) -> 0.0057277027 | I80: =NORMSDIST(NORMSINV($F80)+U$23+Y$23) -> 0.0050643851 | J80: =NORMSDIST(NORMSINV($F80)+V$23+Z$23) -> 0.0051217793 | K80: =G80/$F80 -> 1.2347241 | L80: =H80/$F80 -> 1.1455405 | M80: =I80/$F80 -> 1.012877 | N80: =J80/$F80 -> 1.0243559
B81: =$B$23 -> S08 | C81: =$C$23 -> Transport & Storage | D81: MR4 | E81: =B81&"|"&D81 -> S08|MR4 | F81: =INDEX(RatingGrades!$C$6:$C$12,MATCH(D81,RatingGrades!$B$6:$B$12,0)) -> 0.01 | G81: =NORMSDIST(NORMSINV($F81)+S$23+W$23) -> 0.012142814 | H81: =NORMSDIST(NORMSINV($F81)+T$23+X$23) -> 0.011333251 | I81: =NORMSDIST(NORMSINV($F81)+U$23+Y$23) -> 0.010118609 | J81: =NORMSDIST(NORMSINV($F81)+V$23+Z$23) -> 0.010224229 | K81: =G81/$F81 -> 1.2142814 | L81: =H81/$F81 -> 1.1333251 | M81: =I81/$F81 -> 1.0118609 | N81: =J81/$F81 -> 1.0224229
B82: =$B$23 -> S08 | C82: =$C$23 -> Transport & Storage | D82: MR5 | E82: =B82&"|"&D82 -> S08|MR5 | F82: =INDEX(RatingGrades!$C$6:$C$12,MATCH(D82,RatingGrades!$B$6:$B$12,0)) -> 0.02 | G82: =NORMSDIST(NORMSINV($F82)+S$23+W$23) -> 0.023852816 | H82: =NORMSDIST(NORMSINV($F82)+T$23+X$23) -> 0.022406234 | I82: =NORMSDIST(NORMSINV($F82)+U$23+Y$23) -> 0.020215343 | J82: =NORMSDIST(NORMSINV($F82)+V$23+Z$23) -> 0.020406887 | K82: =G82/$F82 -> 1.1926408 | L82: =H82/$F82 -> 1.1203117 | M82: =I82/$F82 -> 1.0107671 | N82: =J82/$F82 -> 1.0203443
B83: =$B$23 -> S08 | C83: =$C$23 -> Transport & Storage | D83: MR6 | E83: =B83&"|"&D83 -> S08|MR6 | F83: =INDEX(RatingGrades!$C$6:$C$12,MATCH(D83,RatingGrades!$B$6:$B$12,0)) -> 0.045 | G83: =NORMSDIST(NORMSINV($F83)+S$23+W$23) -> 0.052441288 | H83: =NORMSDIST(NORMSINV($F83)+T$23+X$23) -> 0.04967025 | I83: =NORMSDIST(NORMSINV($F83)+U$23+Y$23) -> 0.045421235 | J83: =NORMSDIST(NORMSINV($F83)+V$23+Z$23) -> 0.045795359 | K83: =G83/$F83 -> 1.165362 | L83: =H83/$F83 -> 1.1037833 | M83: =I83/$F83 -> 1.0093608 | N83: =J83/$F83 -> 1.0176746
B84: =$B$23 -> S08 | C84: =$C$23 -> Transport & Storage | D84: MR7 | E84: =B84&"|"&D84 -> S08|MR7 | F84: =INDEX(RatingGrades!$C$6:$C$12,MATCH(D84,RatingGrades!$B$6:$B$12,0)) -> 0.1 | G84: =NORMSDIST(NORMSINV($F84)+S$23+W$23) -> 0.11356519 | H84: =NORMSDIST(NORMSINV($F84)+T$23+X$23) -> 0.10856174 | I84: =NORMSDIST(NORMSINV($F84)+U$23+Y$23) -> 0.1007792 | J84: =NORMSDIST(NORMSINV($F84)+V$23+Z$23) -> 0.10147007 | K84: =G84/$F84 -> 1.1356519 | L84: =H84/$F84 -> 1.0856174 | M84: =I84/$F84 -> 1.007792 | N84: =J84/$F84 -> 1.0147007
B85: =$B$24 -> S09 | C85: =$C$24 -> Accommodation & Food Services | D85: MR1 | E85: =B85&"|"&D85 -> S09|MR1 | F85: =INDEX(RatingGrades!$C$6:$C$12,MATCH(D85,RatingGrades!$B$6:$B$12,0)) -> 0.001 | G85: =NORMSDIST(NORMSINV($F85)+S$24+W$24) -> 0.0012769893 | H85: =NORMSDIST(NORMSINV($F85)+T$24+X$24) -> 0.0011700896 | I85: =NORMSDIST(NORMSINV($F85)+U$24+Y$24) -> 0.0010128397 | J85: =NORMSDIST(NORMSINV($F85)+V$24+Z$24) -> 0.0010267392 | K85: =G85/$F85 -> 1.2769893 | L85: =H85/$F85 -> 1.1700896 | M85: =I85/$F85 -> 1.0128397 | N85: =J85/$F85 -> 1.0267392
B86: =$B$24 -> S09 | C86: =$C$24 -> Accommodation & Food Services | D86: MR2 | E86: =B86&"|"&D86 -> S09|MR2 | F86: =INDEX(RatingGrades!$C$6:$C$12,MATCH(D86,RatingGrades!$B$6:$B$12,0)) -> 0.0025 | G86: =NORMSDIST(NORMSINV($F86)+S$24+W$24) -> 0.0031316087 | H86: =NORMSDIST(NORMSINV($F86)+T$24+X$24) -> 0.0028893867 | I86: =NORMSDIST(NORMSINV($F86)+U$24+Y$24) -> 0.0025295786 | J86: =NORMSDIST(NORMSINV($F86)+V$24+Z$24) -> 0.0025615633 | K86: =G86/$F86 -> 1.2526435 | L86: =H86/$F86 -> 1.1557547 | M86: =I86/$F86 -> 1.0118314 | N86: =J86/$F86 -> 1.0246253
B87: =$B$24 -> S09 | C87: =$C$24 -> Accommodation & Food Services | D87: MR3 | E87: =B87&"|"&D87 -> S09|MR3 | F87: =INDEX(RatingGrades!$C$6:$C$12,MATCH(D87,RatingGrades!$B$6:$B$12,0)) -> 0.005 | G87: =NORMSDIST(NORMSINV($F87)+S$24+W$24) -> 0.0061665259 | H87: =NORMSDIST(NORMSINV($F87)+T$24+X$24) -> 0.0057214783 | I87: =NORMSDIST(NORMSINV($F87)+U$24+Y$24) -> 0.0050550854 | J87: =NORMSDIST(NORMSINV($F87)+V$24+Z$24) -> 0.0051145975 | K87: =G87/$F87 -> 1.2333052 | L87: =H87/$F87 -> 1.1442957 | M87: =I87/$F87 -> 1.0110171 | N87: =J87/$F87 -> 1.0229195
B88: =$B$24 -> S09 | C88: =$C$24 -> Accommodation & Food Services | D88: MR4 | E88: =B88&"|"&D88 -> S09|MR4 | F88: =INDEX(RatingGrades!$C$6:$C$12,MATCH(D88,RatingGrades!$B$6:$B$12,0)) -> 0.01 | G88: =NORMSDIST(NORMSINV($F88)+S$24+W$24) -> 0.012129975 | H88: =NORMSDIST(NORMSINV($F88)+T$24+X$24) -> 0.011321912 | I88: =NORMSDIST(NORMSINV($F88)+U$24+Y$24) -> 0.010101485 | J88: =NORMSDIST(NORMSINV($F88)+V$24+Z$24) -> 0.010211018 | K88: =G88/$F88 -> 1.2129975 | L88: =H88/$F88 -> 1.1321912 | M88: =I88/$F88 -> 1.0101485 | N88: =J88/$F88 -> 1.0211018
B89: =$B$24 -> S09 | C89: =$C$24 -> Accommodation & Food Services | D89: MR5 | E89: =B89&"|"&D89 -> S09|MR5 | F89: =INDEX(RatingGrades!$C$6:$C$12,MATCH(D89,RatingGrades!$B$6:$B$12,0)) -> 0.02 | G89: =NORMSDIST(NORMSINV($F89)+S$24+W$24) -> 0.023829955 | H89: =NORMSDIST(NORMSINV($F89)+T$24+X$24) -> 0.022385898 | I89: =NORMSDIST(NORMSINV($F89)+U$24+Y$24) -> 0.020184269 | J89: =NORMSDIST(NORMSINV($F89)+V$24+Z$24) -> 0.02038294 | K89: =G89/$F89 -> 1.1914977 | L89: =H89/$F89 -> 1.1192949 | M89: =I89/$F89 -> 1.0092135 | N89: =J89/$F89 -> 1.019147
B90: =$B$24 -> S09 | C90: =$C$24 -> Accommodation & Food Services | D90: MR6 | E90: =B90&"|"&D90 -> S09|MR6 | F90: =INDEX(RatingGrades!$C$6:$C$12,MATCH(D90,RatingGrades!$B$6:$B$12,0)) -> 0.045 | G90: =NORMSDIST(NORMSINV($F90)+S$24+W$24) -> 0.052397698 | H90: =NORMSDIST(NORMSINV($F90)+T$24+X$24) -> 0.049631107 | I90: =NORMSDIST(NORMSINV($F90)+U$24+Y$24) -> 0.045360494 | J90: =NORMSDIST(NORMSINV($F90)+V$24+Z$24) -> 0.045748615 | K90: =G90/$F90 -> 1.1643933 | L90: =H90/$F90 -> 1.1029135 | M90: =I90/$F90 -> 1.008011 | N90: =J90/$F90 -> 1.0166359
B91: =$B$24 -> S09 | C91: =$C$24 -> Accommodation & Food Services | D91: MR7 | E91: =B91&"|"&D91 -> S09|MR7 | F91: =INDEX(RatingGrades!$C$6:$C$12,MATCH(D91,RatingGrades!$B$6:$B$12,0)) -> 0.1 | G91: =NORMSDIST(NORMSINV($F91)+S$24+W$24) -> 0.1134869 | H91: =NORMSDIST(NORMSINV($F91)+T$24+X$24) -> 0.10849067 | I91: =NORMSDIST(NORMSINV($F91)+U$24+Y$24) -> 0.10066693 | J91: =NORMSDIST(NORMSINV($F91)+V$24+Z$24) -> 0.10138381 | K91: =G91/$F91 -> 1.134869 | L91: =H91/$F91 -> 1.0849067 | M91: =I91/$F91 -> 1.0066693 | N91: =J91/$F91 -> 1.0138381
B92: =$B$25 -> S10 | C92: =$C$25 -> Financial, Professional, Public & Other Services | D92: MR1 | E92: =B92&"|"&D92 -> S10|MR1 | F92: =INDEX(RatingGrades!$C$6:$C$12,MATCH(D92,RatingGrades!$B$6:$B$12,0)) -> 0.001 | G92: =NORMSDIST(NORMSINV($F92)+S$25+W$25) -> 0.0010673819 | H92: =NORMSDIST(NORMSINV($F92)+T$25+X$25) -> 0.0010812628 | I92: =NORMSDIST(NORMSINV($F92)+U$25+Y$25) -> 0.0010030907 | J92: =NORMSDIST(NORMSINV($F92)+V$25+Z$25) -> 0.0010047535 | K92: =G92/$F92 -> 1.0673819 | L92: =H92/$F92 -> 1.0812628 | M92: =I92/$F92 -> 1.0030907 | N92: =J92/$F92 -> 1.0047535
B93: =$B$25 -> S10 | C93: =$C$25 -> Financial, Professional, Public & Other Services | D93: MR2 | E93: =B93&"|"&D93 -> S10|MR2 | F93: =INDEX(RatingGrades!$C$6:$C$12,MATCH(D93,RatingGrades!$B$6:$B$12,0)) -> 0.0025 | G93: =NORMSDIST(NORMSINV($F93)+S$25+W$25) -> 0.0026548797 | H93: =NORMSDIST(NORMSINV($F93)+T$25+X$25) -> 0.0026866814 | I93: =NORMSDIST(NORMSINV($F93)+U$25+Y$25) -> 0.0025071228 | J93: =NORMSDIST(NORMSINV($F93)+V$25+Z$25) -> 0.0025109542 | K93: =G93/$F93 -> 1.0619519 | L93: =H93/$F93 -> 1.0746726 | M93: =I93/$F93 -> 1.0028491 | N93: =J93/$F93 -> 1.0043817
B94: =$B$25 -> S10 | C94: =$C$25 -> Financial, Professional, Public & Other Services | D94: MR3 | E94: =B94&"|"&D94 -> S10|MR3 | F94: =INDEX(RatingGrades!$C$6:$C$12,MATCH(D94,RatingGrades!$B$6:$B$12,0)) -> 0.005 | G94: =NORMSDIST(NORMSINV($F94)+S$25+W$25) -> 0.0052879121 | H94: =NORMSDIST(NORMSINV($F94)+T$25+X$25) -> 0.0053468719 | I94: =NORMSDIST(NORMSINV($F94)+U$25+Y$25) -> 0.0050132695 | J94: =NORMSDIST(NORMSINV($F94)+V$25+Z$25) -> 0.005020406 | K94: =G94/$F94 -> 1.0575824 | L94: =H94/$F94 -> 1.0693744 | M94: =I94/$F94 -> 1.0026539 | N94: =J94/$F94 -> 1.0040812
B95: =$B$25 -> S10 | C95: =$C$25 -> Financial, Professional, Public & Other Services | D95: MR4 | E95: =B95&"|"&D95 -> S10|MR4 | F95: =INDEX(RatingGrades!$C$6:$C$12,MATCH(D95,RatingGrades!$B$6:$B$12,0)) -> 0.01 | G95: =NORMSDIST(NORMSINV($F95)+S$25+W$25) -> 0.010529384 | H95: =NORMSDIST(NORMSINV($F95)+T$25+X$25) -> 0.010637482 | I95: =NORMSDIST(NORMSINV($F95)+U$25+Y$25) -> 0.010024456 | J95: =NORMSDIST(NORMSINV($F95)+V$25+Z$25) -> 0.010037606 | K95: =G95/$F95 -> 1.0529384 | L95: =H95/$F95 -> 1.0637482 | M95: =I95/$F95 -> 1.0024456 | N95: =J95/$F95 -> 1.0037606
B96: =$B$25 -> S10 | C96: =$C$25 -> Financial, Professional, Public & Other Services | D96: MR5 | E96: =B96&"|"&D96 -> S10|MR5 | F96: =INDEX(RatingGrades!$C$6:$C$12,MATCH(D96,RatingGrades!$B$6:$B$12,0)) -> 0.02 | G96: =NORMSDIST(NORMSINV($F96)+S$25+W$25) -> 0.020959157 | H96: =NORMSDIST(NORMSINV($F96)+T$25+X$25) -> 0.021154394 | I96: =NORMSDIST(NORMSINV($F96)+U$25+Y$25) -> 0.020044422 | J96: =NORMSDIST(NORMSINV($F96)+V$25+Z$25) -> 0.020068304 | K96: =G96/$F96 -> 1.0479578 | L96: =H96/$F96 -> 1.0577197 | M96: =I96/$F96 -> 1.0022211 | N96: =J96/$F96 -> 1.0034152
B97: =$B$25 -> S10 | C97: =$C$25 -> Financial, Professional, Public & Other Services | D97: MR6 | E97: =B97&"|"&D97 -> S10|MR6 | F97: =INDEX(RatingGrades!$C$6:$C$12,MATCH(D97,RatingGrades!$B$6:$B$12,0)) -> 0.045 | G97: =NORMSDIST(NORMSINV($F97)+S$25+W$25) -> 0.046871152 | H97: =NORMSDIST(NORMSINV($F97)+T$25+X$25) -> 0.047250449 | I97: =NORMSDIST(NORMSINV($F97)+U$25+Y$25) -> 0.04508695 | J97: =NORMSDIST(NORMSINV($F97)+V$25+Z$25) -> 0.045133683 | K97: =G97/$F97 -> 1.0415812 | L97: =H97/$F97 -> 1.05001 | M97: =I97/$F97 -> 1.0019322 | N97: =J97/$F97 -> 1.0029707
B98: =$B$25 -> S10 | C98: =$C$25 -> Financial, Professional, Public & Other Services | D98: MR7 | E98: =B98&"|"&D98 -> S10|MR7 | F98: =INDEX(RatingGrades!$C$6:$C$12,MATCH(D98,RatingGrades!$B$6:$B$12,0)) -> 0.1 | G98: =NORMSDIST(NORMSINV($F98)+S$25+W$25) -> 0.10345049 | H98: =NORMSDIST(NORMSINV($F98)+T$25+X$25) -> 0.10414658 | I98: =NORMSDIST(NORMSINV($F98)+U$25+Y$25) -> 0.10016096 | J98: =NORMSDIST(NORMSINV($F98)+V$25+Z$25) -> 0.10024744 | K98: =G98/$F98 -> 1.0345049 | L98: =H98/$F98 -> 1.0414658 | M98: =I98/$F98 -> 1.0016096 | N98: =J98/$F98 -> 1.0024744
C100: No de-stress check (count of stressed PD below baseline) | G100: =SUMPRODUCT((G29:G98<$F29:$F98-0.000000001)*1)+SUMPRODUCT((H29:H98<$F29:$F98-0.000000001)*1)+SUMPRODUCT((I29:I98<$F29:$F98-0.000000001)*1)+SUMPRODUCT((J29:J98<$F29:$F98-0.000000001)*1) -> 0
C101: Identity check: NORMSDIST(NORMSINV(2%)) must equal 2% | G101: =NORMSDIST(NORMSINV(0.02)) -> 0.02
C102: Transition ordering violations (NZ>=DT>=FW>=CP) | G102: =SUMPRODUCT((G16:G25<H16:H25-0.000000000001)*1)+SUMPRODUCT((H16:H25<J16:J25-0.000000000001)*1)+SUMPRODUCT((J16:J25<I16:I25-0.000000000001)*1) -> 0
C103: Physical ordering violations (CP>=FW>=DT>=NZ) | G103: =SUMPRODUCT((M16:M25<N16:N25-0.000000000001)*1)+SUMPRODUCT((N16:N25<L16:L25-0.000000000001)*1)+SUMPRODUCT((L16:L25<K16:K25-0.000000000001)*1) -> 0
C106: Summary at grade MR5 (2.00% baseline): PD multiple, and the transition / physical split of the push
B107: ID | C107: Sector | D107: PD mult NZ | E107: PD mult DT | F107: PD mult CP | G107: PD mult FW | H107: push from transition (NZ) | I107: push from physical (NZ) | J107: physical share of push (NZ)
...

Sheet Sector_Master
B1: Sector master: 10-sector taxonomy, complete ISIC coverage
B2: Every ISIC Rev.4 section sits in exactly one sector. Every sector's GVA comes from the source, not from a judgemental split of a parent. There are no zero-GVA rows, which is what caused the real-estate problem in v3: ISIC L, E, N and R are not itemised in Oman's SNA submission but are absorbed inside the lines that are, so they are folded into their parent sector rather than given empty rows of their own.
B4: Denominator basis (GVA or TURNOVER) | C4: GVA | E4: See ReadMe and the note below the table for why GVA is the default.
B5: OMR / US$ peg | C5: 2.6008
B7: ID | C7: Sector | D7: ISIC Rev.4 sections | E7: GVA 2023 (OMR m) | F7: GVA 2023 (US$ m) | G7: Turnover / GVA | H7: Denominator (US$ m) | I7: Pass-through | J7: macro_beta | K7: Pass-through rationale (trade-exposure basis)
B8: S01 | C8: Agriculture, Forestry & Fishing | D8: A | E8: 996.81484 | F8: =E8*$C$5 -> 2592.516 | G8: 1 | H8: =IF($C$4="TURNOVER",F8*G8,F8) -> 2592.516 | I8: 0.25 | J8: 1 | K8: Commodity price-takers, partly supported by domestic subsidy. Low pass-through.
B9: S02 | C9: Oil & Gas Extraction | D9: B (petroleum part) | E9: 14750.294 | F9: =E9*$C$5 -> 38362.564 | G9: 1 | H9: =IF($C$4="TURNOVER",F9*G9,F9) -> 38362.564 | I9: 0.05 | J9: 1 | K9: World-priced crude and LNG. A domestic carbon cost cannot be passed to an international buyer. Near-zero pass-through.
B10: S03 | C10: Mining & Quarrying (non-oil) | D10: B (remainder) | E10: 205.8 | F10: =E10*$C$5 -> 535.24464 | G10: 1 | H10: =IF($C$4="TURNOVER",F10*G10,F10) -> 535.24464 | I10: 0.3 | J10: 1 | K10: Limestone, gypsum, chromite, copper. Part exported at world prices, part sold into the domestic construction chain.
B11: S04 | C11: Manufacturing | D11: C | E11: 3819.7517 | F11: =E11*$C$5 -> 9934.4102 | G11: 1 | H11: =IF($C$4="TURNOVER",F11*G11,F11) -> 9934.4102 | I11: 0.3 | J11: 1 | K11: Dominated in Oman by refining, petrochemicals and metals, all internationally traded against unabated Gulf and Asian competitors. Weighted below the 45% base rate for that reason.
B12: S05 | C12: Electricity, Gas, Water & Waste | D12: D, E | E12: 970.07565 | F12: =E12*$C$5 -> 2522.9728 | G12: 1 | H12: =IF($C$4="TURNOVER",F12*G12,F12) -> 2522.9728 | I12: 0.8 | J12: 1 | K12: Regulated tariffs with cost recovery through the regulator and state subsidy. Cost migrates to the sovereign rather than the utility. Corollary: residual credit risk becomes sovereign-linked, which this model does not capture.
B13: S06 | C13: Construction | D13: F | E13: 2766.3441 | F13: =E13*$C$5 -> 7194.7077 | G13: 1 | H13: =IF($C$4="TURNOVER",F13*G13,F13) -> 7194.7077 | I13: 0.5 | J13: 1 | K13: Domestic, contract-based. Cost-escalation clauses on long contracts, fixed price on many others.
B14: S07 | C14: Wholesale & Retail Trade | D14: G | E14: 3165.6894 | F14: =E14*$C$5 -> 8233.325 | G14: 1 | H14: =IF($C$4="TURNOVER",F14*G14,F14) -> 8233.325 | I14: 0.7 | J14: 1 | K14: Passes input cost to the final consumer over the medium term. Thin margins but high pass-through.
B15: S08 | C15: Transport & Storage | D15: H | E15: 1680.826 | F15: =E15*$C$5 -> 4371.4922 | G15: 1 | H15: =IF($C$4="TURNOVER",F15*G15,F15) -> 4371.4922 | I15: 0.6 | J15: 1 | K15: Fuel surcharges are standard contractual practice in freight and warehousing; partly offset by international competition in shipping and aviation.
B16: S09 | C16: Accommodation & Food Services | D16: I | E16: 585.41162 | F16: =E16*$C$5 -> 1522.5385 | G16: 1 | H16: =IF($C$4="TURNOVER",F16*G16,F16) -> 1522.5385 | I16: 0.35 | J16: 1 | K16: Price-elastic international demand competing with regional destinations. Below-average pass-through.
B17: S10 | C17: Financial, Professional, Public & Other Services | D17: J, K, L, M, N, O, P, Q, R, S, T | E17: 13022.9 | F17: =E17*$C$5 -> 33869.959 | G17: 1 | H17: =IF($C$4="TURNOVER",F17*G17,F17) -> 33869.959 | I17: 0.6 | J17: 1 | K17: Domestic and largely non-traded. Includes real estate (ISIC L), which Oman's SNA submission does not itemise separately.
C18: Total | E18: =SUM(E8:E17) -> 41963.907
C19: UN SNA Table 2.4, total value added at basic prices, 2023 | E19: 41963.907
C20: Reconciliation | E20: =IF(ABS(E18-E19)<0.01,"PASS","FAIL") -> PASS
B22: WHY GVA AND NOT TURNOVER. Turnover is the better denominator on comparability grounds, because the EU literature (ECB OP 281, EU ETS carbon-leakage work) reports emission intensity per unit of revenue. It is not used here for one reason: Oman does not publish output or turnover by ISIC activity. NCSI publishes value added by activity; output at basic prices would require the supply-use table, which is not public. GVA is therefore the only denominator that exists for every sector in this list. Two consequences follow. First, the EU anchor must be converted onto a GVA basis, which is done explicitly on EU_k_Calibration rather than left as an implicit unit mismatch. Second, if the bank can obtain turnover by sector, switch cell C4 to TURNOVER, populate column G, and the model runs on a revenue basis end to end.
B26: There is also an argument that GVA is the more meaningful denominator for default risk, since GVA is approximately EBITDA plus labour compensation, i.e. the funds actually available to absorb a cost shock, whereas revenue is not. The decisive point, though, is data availability, and the two bases must never be mixed as they were in v2.
B29: TIMING: GVA is 2023 current prices. Emissions are 2024 EDGAR. See Verification item 18 for the 2024 replacement values.

Sheet Emissions_Allocation
B1: Emissions allocation: EDGAR IPCC categories onto the lending taxonomy
B2: EDGAR reports emissions by IPCC SOURCE category; a bank lends to ISIC ACTIVITIES. Each EDGAR row is split across lending sectors plus a Households and own-account column that is excluded from every corporate intensity.
B5: Code | C5: EDGAR category | D5: MtCO2e | E5: Definition | F5: S01 | G5: S02 | H5: S03 | I5: S04 | J5: S05 | K5: S06 | L5: S07 | M5: S08 | N5: S09 | O5: S10 | P5: HH | Q5: Row sum | R5: Check
B6: E1 | C6: Fuel Exploitation | D6: 42.24 | E6: Upstream oil and gas: fugitive methane, venting, flaring, own energy use. IPCC 1B. | F6: 0 | G6: 1 | H6: 0 | I6: 0 | J6: 0 | K6: 0 | L6: 0 | M6: 0 | N6: 0 | O6: 0 | P6: 0 | Q6: =SUM(F6:P6) -> 1 | R6: =IF(ABS(Q6-1)<0.000001,"OK","FAIL") -> OK
B7: E2 | C7: Power Industry | D7: 17.15 | E7: Public electricity and heat generation. IPCC 1A1a. | F7: 0 | G7: 0 | H7: 0 | I7: 0 | J7: 1 | K7: 0 | L7: 0 | M7: 0 | N7: 0 | O7: 0 | P7: 0 | Q7: =SUM(F7:P7) -> 1 | R7: =IF(ABS(Q7-1)<0.000001,"OK","FAIL") -> OK
B8: E3 | C8: Industrial Combustion | D8: 14.29 | E8: Fuel combustion in manufacturing industries AND construction. IPCC 1A2. | F8: 0 | G8: 0 | H8: 0.05 | I8: 0.85 | J8: 0 | K8: 0.1 | L8: 0 | M8: 0 | N8: 0 | O8: 0 | P8: 0 | Q8: =SUM(F8:P8) -> 1 | R8: =IF(ABS(Q8-1)<0.000001,"OK","FAIL") -> OK
B9: E4 | C9: Transport | D9: 13.01 | E9: Road, domestic aviation, domestic navigation, rail. INCLUDES private household vehicles. IPCC 1A3. | F9: 0 | G9: 0 | H9: 0 | I9: 0 | J9: 0 | K9: 0 | L9: 0.1 | M9: 0.4 | N9: 0 | O9: 0 | P9: 0.5 | Q9: =SUM(F9:P9) -> 1 | R9: =IF(ABS(Q9-1)<0.000001,"OK","FAIL") -> OK
B10: E5 | C10: Agriculture | D10: 1.86 | E10: Enteric fermentation, manure, soils, agricultural fuel use. IPCC 3. | F10: 1 | G10: 0 | H10: 0 | I10: 0 | J10: 0 | K10: 0 | L10: 0 | M10: 0 | N10: 0 | O10: 0 | P10: 0 | Q10: =SUM(F10:P10) -> 1 | R10: =IF(ABS(Q10-1)<0.000001,"OK","FAIL") -> OK
B11: E6 | C11: Buildings | D11: 22.23 | E11: Residential, commercial and institutional fuel combustion, i.e. building OCCUPANCY energy. IPCC 1A4. NOT the construction industry. | F11: 0 | G11: 0 | H11: 0 | I11: 0 | J11: 0 | K11: 0 | L11: 0.1 | M11: 0 | N11: 0.05 | O11: 0.15 | P11: 0.7 | Q11: =SUM(F11:P11) -> 1 | R11: =IF(ABS(Q11-1)<0.000001,"OK","FAIL") -> OK
B12: E7 | C12: Residual (industrial processes, waste, other) | D12: =$D$14-SUM(D6:D11) -> 21.49 | E12: PLUG: national total less the six categories above. | F12: 0 | G12: 0.15 | H12: 0 | I12: 0.4 | J12: 0.25 | K12: 0 | L12: 0 | M12: 0 | N12: 0 | O12: 0.1 | P12: 0.1 | Q12: =SUM(F12:P12) -> 1 | R12: =IF(ABS(Q12-1)<0.000001,"OK","FAIL") -> OK
C13: Sum of categories | D13: =SUM(D6:D12) -> 132.27
C14: National total GHG (MtCO2e) | D14: 132.27
C15: Reconciliation | D15: =IF(ABS(D13-D14)<0.001,"PASS","FAIL") -> PASS
C16: Allocated emissions by lending sector (MtCO2e)
C17: Allocated MtCO2e | F17: =SUMPRODUCT($D$6:$D$12,F6:F12) -> 1.86 | G17: =SUMPRODUCT($D$6:$D$12,G6:G12) -> 45.4635 | H17: =SUMPRODUCT($D$6:$D$12,H6:H12) -> 0.7145 | I17: =SUMPRODUCT($D$6:$D$12,I6:I12) -> 20.7425 | J17: =SUMPRODUCT($D$6:$D$12,J6:J12) -> 22.5225 | K17: =SUMPRODUCT($D$6:$D$12,K6:K12) -> 1.429 | L17: =SUMPRODUCT($D$6:$D$12,L6:L12) -> 3.524 | M17: =SUMPRODUCT($D$6:$D$12,M6:M12) -> 5.204 | ... P17: =SUMPRODUCT($D$6:$D$12,P6:P12) -> 24.215 | Q17: =SUM(F17:P17) -> 132.27 | R17: =IF(ABS(Q17-D14)<0.001,"OK","FAIL") -> OK
C18: Sector ID | F18: S01 | G18: S02 | H18: S03 | I18: S04 | J18: S05 | K18: S06 | L18: S07 | M18: S08 | N18: S09 | O18: S10 | P18: HH
C20: Plausibility checks
C21: Population (millions) | D21: 5.3
C22: National emissions per head (tCO2e) | D22: =D14/D21 -> 24.956604 | E22: High, but consistent with Oman being among the highest per-capita emitters globally. Not a fail.
C23: EDGAR Buildings per head (tCO2e) | D23: =D11/D21 -> 4.1943396 | E23: =IF(D23>3,"FLAG - implausibly high, re-download EDGAR","OK") -> FLAG - implausibly high, re-download EDGAR
E24: This is DIRECT fuel combustion in buildings only; air conditioning electricity is already counted under Power Industry. Above roughly 3 tCO2e per head the figure is not credible for a hot climate. Seventy per cent is allocated to households so it does not distort corporate intensities, but the underlying figure should be re-checked.
C26: Corporate share of national emissions | D26: =(Q17-P17)/Q17 -> 0.8169275
C27: The remainder is households and own-account use: private vehicles and residential building energy. In v2 these were charged to Transport & Logistics and to Construction respectively.
C29: The three shaded allocation rows that carry judgement are E3 (industrial combustion across manufacturing, mining and construction), E4 (transport between freight operators and households) and E6 (buildings between households and commercial occupiers), plus the E7 residual. Replace with an EDGAR sub-sector download or an ISIC-basis emissions account from Eora, EXIOBASE or GTAP, reconciled to the EDGAR national total.

Sheet Oman_Intensity
B1: Emissions intensity by sector
B2: Basis: tCO2e all-gas Scope 1 per US$ million of the denominator selected on Sector_Master (GVA by default). The same basis is used in EU_k_Calibration.
B5: ID | C5: Sector | D5: Emissions (MtCO2e) | E5: Denominator (US$ m) | F5: Intensity (tCO2e / US$m) | G5: Pass-through | H5: macro_beta | I5: Note
B6: S01 | C6: Agriculture, Forestry & Fishing | D6: =INDEX(Emissions_Allocation!$F$17:$O$17,MATCH($B6,Emissions_Allocation!$F$18:$O$18,0)) -> 1.86 | E6: =Sector_Master!H8 -> 2592.516 | F6: =IF(E6<=0,0,D6*1000000/E6) -> 717.44975 | G6: =Sector_Master!I8 -> 0.25 | H6: =Sector_Master!J8 -> 1
B7: S02 | C7: Oil & Gas Extraction | D7: =INDEX(Emissions_Allocation!$F$17:$O$17,MATCH($B7,Emissions_Allocation!$F$18:$O$18,0)) -> 45.4635 | E7: =Sector_Master!H9 -> 38362.564 | F7: =IF(E7<=0,0,D7*1000000/E7) -> 1185.1007 | G7: =Sector_Master!I9 -> 0.05 | H7: =Sector_Master!J9 -> 1
B8: S03 | C8: Mining & Quarrying (non-oil) | D8: =INDEX(Emissions_Allocation!$F$17:$O$17,MATCH($B8,Emissions_Allocation!$F$18:$O$18,0)) -> 0.7145 | E8: =Sector_Master!H10 -> 535.24464 | F8: =IF(E8<=0,0,D8*1000000/E8) -> 1334.9036 | G8: =Sector_Master!I10 -> 0.3 | H8: =Sector_Master!J10 -> 1
B9: S04 | C9: Manufacturing | D9: =INDEX(Emissions_Allocation!$F$17:$O$17,MATCH($B9,Emissions_Allocation!$F$18:$O$18,0)) -> 20.7425 | E9: =Sector_Master!H11 -> 9934.4102 | F9: =IF(E9<=0,0,D9*1000000/E9) -> 2087.9448 | G9: =Sector_Master!I11 -> 0.3 | H9: =Sector_Master!J11 -> 1
B10: S05 | C10: Electricity, Gas, Water & Waste | D10: =INDEX(Emissions_Allocation!$F$17:$O$17,MATCH($B10,Emissions_Allocation!$F$18:$O$18,0)) -> 22.5225 | E10: =Sector_Master!H12 -> 2522.9728 | F10: =IF(E10<=0,0,D10*1000000/E10) -> 8926.9692 | G10: =Sector_Master!I12 -> 0.8 | H10: =Sector_Master!J12 -> 1
B11: S06 | C11: Construction | D11: =INDEX(Emissions_Allocation!$F$17:$O$17,MATCH($B11,Emissions_Allocation!$F$18:$O$18,0)) -> 1.429 | E11: =Sector_Master!H13 -> 7194.7077 | F11: =IF(E11<=0,0,D11*1000000/E11) -> 198.61822 | G11: =Sector_Master!I13 -> 0.5 | H11: =Sector_Master!J13 -> 1
B12: S07 | C12: Wholesale & Retail Trade | D12: =INDEX(Emissions_Allocation!$F$17:$O$17,MATCH($B12,Emissions_Allocation!$F$18:$O$18,0)) -> 3.524 | E12: =Sector_Master!H14 -> 8233.325 | F12: =IF(E12<=0,0,D12*1000000/E12) -> 428.01663 | G12: =Sector_Master!I14 -> 0.7 | H12: =Sector_Master!J14 -> 1
B13: S08 | C13: Transport & Storage | D13: =INDEX(Emissions_Allocation!$F$17:$O$17,MATCH($B13,Emissions_Allocation!$F$18:$O$18,0)) -> 5.204 | E13: =Sector_Master!H15 -> 4371.4922 | F13: =IF(E13<=0,0,D13*1000000/E13) -> 1190.4402 | G13: =Sector_Master!I15 -> 0.6 | H13: =Sector_Master!J15 -> 1
B14: S09 | C14: Accommodation & Food Services | D14: =INDEX(Emissions_Allocation!$F$17:$O$17,MATCH($B14,Emissions_Allocation!$F$18:$O$18,0)) -> 1.1115 | E14: =Sector_Master!H16 -> 1522.5385 | F14: =IF(E14<=0,0,D14*1000000/E14) -> 730.03078 | G14: =Sector_Master!I16 -> 0.35 | H14: =Sector_Master!J16 -> 1
B15: S10 | C15: Financial, Professional, Public & Other Services | D15: =INDEX(Emissions_Allocation!$F$17:$O$17,MATCH($B15,Emissions_Allocation!$F$18:$O$18,0)) -> 5.4835 | E15: =Sector_Master!H17 -> 33869.959 | F15: =IF(E15<=0,0,D15*1000000/E15) -> 161.89863 | G15: =Sector_Master!I17 -> 0.6 | H15: =Sector_Master!J17 -> 1
C16: Total | D16: =SUM(D6:D15) -> 108.055 | E16: =SUM(E6:E15) -> 109139.73
C17: Implied economy-wide intensity (corporate only) | F17: =D16*1000000/E16 -> 990.06109
B19: Sectors with zero intensity are impossible in this taxonomy because every sector has a positive denominator and a positive emissions allocation. That was the v3 defect, caused by creating rows for ISIC sections that Oman does not itemise.

Sheet NGFS_CarbonPrice
B1: NGFS Phase V shadow carbon price
B5: Scenario | C5: 2030 | D5: 2035 | E5: 2040 | F5: 2050
B6: Net Zero 2050 | C6: 200 | D6: 294 | E6: 420 | F6: 630
B7: Delayed Transition | C7: 5 | D7: 100 | E7: 165 | F7: 315
B8: Current Policies | C8: 5 | D8: 6 | E8: 8 | F8: 10
B9: Fragmented World | C9: 5 | D9: 20 | E9: 35 | F9: 55
B11: Unit: US$2010 per tCO2. VERIFIED against NGFS Phase V, Main results, Carbon prices: both published charts are labelled US$2010/tCO2.
B12: VERIFIED: the report states that a shadow price of around $300/tCO2 is needed by 2035 to incentivise net zero by 2050, an increase from $98/tCO2 in 2025 to $294/tCO2 within ten years. The Net Zero 2035 cell has been corrected from 290 to 294. The remaining cells are chart-read and are flagged.
B14: VERIFIED, AND A CONSERVATIVE BIAS: these are weighted GLOBAL prices. The source footnote states that prices tend to be LOWER in emerging economies, because policy stringency is lower and more low-cost abatement remains available. Applying the global path to Oman therefore OVERSTATES the transition cost. Phase V downscales carbon prices to 220 countries; pull the Oman (OMN) series to remove the bias.
B17: Fragmented World exists specifically to generate divergent REGIONAL prices, so a single global path removes the feature that distinguishes it from Delayed Transition.
B19: Interpretation: an NGFS shadow price is a marginal abatement cost, not a tax bill. Charging price times full current emissions with no abatement response is conservative.

Sheet Scenario_Mapping
B1: Scenario mapping, price deflator and macro deviations
B4: Quadrant mapping and warming
B5: Quadrant | C5: NGFS Phase V scenario | D5: Warming by 2100 (degC)
B6: Orderly | C6: Net Zero 2050 | D6: 1.4
B7: Disorderly | C7: Delayed Transition | D7: 1.7
B8: Hot House World | C8: Current Policies | D8: 3
B9: Too Little Too Late | C9: Fragmented World | D9: 2.4
B10: VERIFIED against NGFS Phase V, Scenarios at a glance. All four warming figures match.
B12: Price base alignment
B13: Carbon price base year | C13: 2010
B14: Denominator (GVA) base year | C14: 2023
B15: US GDP deflator, ratio target year / 2010 | C15: 1.35 | I15: TO VERIFY: US Bureau of Economic Analysis implicit price deflator for GDP, 2023 index divided by 2010 index. The NGFS price is in US$2010 and the denominator is in 2023 US dollars. v2 mixed the two without adjustment, which understated every cost ratio by roughly a quarter.
B18: Transition-only GDP LEVEL deviation from baseline (%)
B19: Scenario | D19: 2030 | E19: 2035 | F19: 2040 | G19: 2050
B20: Net Zero 2050 | D20: -1.5 | E20: =(D20+F20)/2 -> -1.25 | F20: -1 | G20: -0.8
B21: Delayed Transition | D21: -0.3 | E21: =(D21+F21)/2 -> -1.15 | F21: -2 | G21: -1.7
B22: Current Policies | D22: 0 | E22: =(D22+F22)/2 -> 0 | F22: 0 | G22: 0
B23: Fragmented World | D23: 0 | E23: =(D23+F23)/2 -> 0 | F23: 0 | G23: 0
B25: Fragmented World check | D25: =IF(COUNTIF(D23:G23,0)=4,"ACTION - FW deviation is zero in every year","PASS") -> ACTION - FW deviation is zero in every year
B27: PARTLY VERIFIED. The Phase V GDP decomposition chart shows the transition component graphically, not as a table, so exact values cannot be read. The Net Zero and Delayed Transition magnitudes and shapes are consistent with that chart, and ECB Occasional Paper 281 independently states that the transition-risk impact is limited to no more than 2% of European GDP under a disorderly transition, which corroborates the -2.0% figure.
B30: NOT VERIFIABLE: Fragmented World is not plotted in the published chart at all, which shows only Net Zero 2050, Delayed Transition and Current Policies. No public figure exists. A zero deviation for a high-cost, badly co-ordinated transition is not credible.
B32: CORRECT BY CONSTRUCTION: Current Policies at zero. It is the transition baseline and carries no additional transition cost. Its risk is physical, which this model does not cover.
B34: REQUIRED PULL: IIASA NGFS Phase V Scenario Explorer, model NiGEM NGFS v1.23.2, variable NiGEM|Gross Domestic Product (GDP), damage decomposition = Transition, region = Middle East. Oman has no country-level NiGEM macro output; Middle East is the closest aggregate and includes Oman. For a hydrocarbon exporter the Net Zero transition loss should be a MULTIPLE of the global figure, not below it.
B38: Horizon control
B39: Horizon year (2030 / 2035 / 2040 / 2050) | C39: 2040

Sheet Dynamic_Adjust
B1: Dynamic adjustment: emissions intensity and denominator paths
B2: Both indices default to 1.00, which reproduces a static treatment exactly. Switching them on requires no change to any formula downstream.
B5: Scenario | C5: Emissions intensity index at horizon | D5: Denominator index at horizon
B6: Net Zero 2050 | C6: 1 | D6: 1
B7: Delayed Transition | C7: 1 | D7: 1
B8: Current Policies | C8: 1 | D8: 1
B9: Fragmented World | C9: 1 | D9: 1
B11: Emissions intensity index: scenario sector intensity at the horizon divided by the same intensity in the base year. Under Net Zero 2050 this is well below 1.00 for power and industry, so leaving it at 1.00 OVERSTATES the carbon cost. Source: NGFS Phase V IAM output, Emissions|CO2 by sector and Final Energy by sector, downscaled to Oman.
B14: Denominator index: scenario nominal GVA at the horizon divided by base-year GVA. Leaving it at 1.00 UNDERSTATES the denominator and so overstates the cost ratio. Source: NiGEM GDP path, Middle East.
B17: The two omissions bias the cost ratio in opposite directions and do not reliably cancel.

Sheet Physical_Hazard
B1: Physical risk: hazard baselines, warming path and severity
B2: Layer 2 design. Physical damage is expressed as an annual cost as a share of value added, exactly like the carbon cost, and the two are added together INSIDE the push transform. That reuses the calibrated k rather than inventing a second sensitivity, on the reasoning that a dollar of flood damage hits the profit and loss account the same way a dollar of carbon cost does.
B4: A. Baseline annual average loss: tropical cyclone and flood [SOURCED from Oman's event record]
B5: Event | C5: Year | D5: Direct damage (US$ m) | E5: Source
B6: Cyclone Gonu | C6: 2007 | D6: 4200 | E6: Fritz et al. (2010); IWA Water Practice & Technology 17(12). Widely reported at US$4.0 to 4.2bn (2007 dollars). Still the worst natural disaster in Oman's history.
B7: Cyclone Phet | C7: 2010 | D7: 700 | E7: Haggag & Badry (2012). Damage exceeded US$700m in Oman.
B8: Cyclone Shaheen | C8: 2021 | D8: 500 | E8: Government of Oman estimate of direct economic losses, cited in Al-Manji (2022).
B9: Total observed direct damage | D9: =SUM(D6:D8) -> 5400
B10: Observation window (years) | D10: 18 | H10: 2007 to 2024 inclusive. The literature describes intense cyclones striking Oman roughly every three to four years, so an 18-year window covering three major events is consistent with that frequency.
B11: Annual average loss (US$ m per year) | D11: =D9/D10 -> 300
B12: National gross value added (US$ m) | D12: =Sector_Master!E18*Sector_Master!C5 -> 109139.73
B13: Baseline AAL as a share of GVA | D13: =D11/D12 -> 0.0027487699
B14: This is a floor, not a full estimate. It captures only the three largest recorded events and omits smaller wadi flash floods, the April 2024 rainfall episode, and all indirect losses. It also uses nominal damage figures from different years without deflating. Every one of those omissions pushes the true figure up.
B17: B. Baseline annual average loss by hazard (share of national GVA)
B18: Hazard | C18: Baseline AAL (% of GVA) | D18: Economic mechanism | E18: Status
B19: H1 | C19: Tropical cyclone and flood | D19: =D13 -> 0.0027487699 | E19: Destruction of physical capital, followed by business interruption while operations are restored. | F19: SOURCED from event record
B20: H2 | C20: Extreme heat | D20: 0.003 | E20: Loss of outdoor labour productivity, midday working restrictions, higher cooling load and equipment derating. | F20: INPUT - replace with NGFS acute heatwave damage
B21: H3 | C21: Water stress and drought | D21: 0.001 | E21: Constrained output, higher input costs, higher desalination energy cost. | F21: INPUT - replace with NGFS acute drought damage
B23: REQUIRED PULL to replace H2 and H3: IIASA NGFS Phase V Scenario Explorer, model NiGEM NGFS v1.23.2, variable NiGEM|Gross Domestic Product (GDP) with damage decomposition = Acute, hazard = heatwaves and drought, region = Middle East. NGFS models exactly four acute hazards: heatwaves acting on the labour force, cyclones and floods acting on the capital stock, and drought acting on productivity, commodity prices and exports. Cyclone and flood are combined into H1 here because Oman's loss record cannot separate them: the damage from an Arabian Sea cyclone is overwhelmingly flood damage.
B27: C. Warming path
B28: Warming above pre-industrial today (degC) | D28: 1.3
B29: Base year | D29: 2025
B30: Horizon year | D30: =Scenario_Mapping!C39 -> 2040
B31: Scenario | D31: Warming by 2100 (degC) | E31: Warming at horizon (degC) | F31: Ratio to today
B32: Net Zero 2050 | D32: =Scenario_Mapping!D6 -> 1.4 | E32: =$D$28+(D32-$D$28)*($D$30-$D$29)/(2100-$D$29) -> 1.32 | F32: =E32/$D$28 -> 1.0153846
B33: Delayed Transition | D33: =Scenario_Mapping!D7 -> 1.7 | E33: =$D$28+(D33-$D$28)*($D$30-$D$29)/(2100-$D$29) -> 1.38 | F33: =E33/$D$28 -> 1.0615385
B34: Current Policies | D34: =Scenario_Mapping!D8 -> 3 | E34: =$D$28+(D34-$D$28)*($D$30-$D$29)/(2100-$D$29) -> 1.64 | F34: =E34/$D$28 -> 1.2615385
B35: Fragmented World | D35: =Scenario_Mapping!D9 -> 2.4 | E35: =$D$28+(D35-$D$28)*($D$30-$D$29)/(2100-$D$29) -> 1.52 | F35: =E35/$D$28 -> 1.1692308
B36: The horizon column is a straight-line interpolation between today's warming and the end-of-century figure. It is a PLACEHOLDER and it is the weakest link in the physical module. Replace it with the MAGICC temperature path published with NGFS Phase V, which is available by scenario and year.
B39: Why this matters more than it looks. Warming paths diverge slowly. At 2100 the four scenarios span 1.4 to 3.0 degrees, but at 2040 they span only about 1.32 to 1.64. Physical risk therefore barely discriminates between scenarios at a 2040 horizon and discriminates strongly at 2050 and beyond. If the point of the exercise is to show the transition-versus-physical trade-off, run it at 2050.
B43: D. Severity multipliers
B44: Hazard | C44: Warming elasticity | D44: Net Zero 2050 | E44: Delayed Transition | F44: Current Policies | G44: Fragmented World
B45: H1 | C45: 2 | D45: =Physical_Hazard!$F$32^$C45 -> 1.0310059 | E45: =Physical_Hazard!$F$33^$C45 -> 1.1268639 | F45: =Physical_Hazard!$F$34^$C45 -> 1.5914793 | G45: =Physical_Hazard!$F$35^$C45 -> 1.3671006 | I45: Damage rises faster than temperature because it scales with storm intensity, and intensity enters damage functions at a high power. IPCC AR6 finds the proportion of the most intense tropical cyclones increases with warming.
B46: H2 | C46: 3 | D46: =Physical_Hazard!$F$32^$C46 -> 1.0468675 | E46: =Physical_Hazard!$F$33^$C46 -> 1.1962094 | F46: =Physical_Hazard!$F$34^$C46 -> 2.0077123 | G46: =Physical_Hazard!$F$35^$C46 -> 1.5984561 | I46: Labour productivity loss is strongly convex in temperature: hours lost rise sharply once wet-bulb thresholds are crossed, which the Gulf is already close to.
B47: H3 | C47: 1.5 | D47: =Physical_Hazard!$F$32^$C47 -> 1.0231655 | E47: =Physical_Hazard!$F$33^$C47 -> 1.0937136 | F47: =Physical_Hazard!$F$34^$C47 -> 1.4169377 | G47: =Physical_Hazard!$F$35^$C47 -> 1.2643006 | I47: Water stress responds to warming through evaporation and precipitation variability, but Oman is already at the extreme of the scale, so the marginal elasticity is lower.
B49: Multiplier = (warming at horizon / warming today) ^ elasticity. All three elasticities are ANALYST JUDGEMENT and are exposed for sensitivity. They control how sharply physical risk separates the scenarios, so they should be tested before any result is presented.
B53: E. Loss transfer and conversion to a profit-and-loss impact
B54: Hazard | C54: Insurance recovery | D54: Share of loss hitting the P&L | E54: Reasoning
B55: H1 | C55: 0.25 | D55: 0.6 | E55: Oman's non-life insurance penetration is low and catastrophe cover is far from universal, so most damage is retained. Of the retained loss, the split below sends 60% to the profit and loss account as business interruption and repair expense, and leaves 40% as capital replacement.
B56: H2 | C56: 0 | D56: 1 | E56: Not an insurable event. Lost labour hours hit the P&L in full.
B57: H3 | C57: 0 | D57: 1 | E57: Not an insurable event. Higher input and water costs hit the P&L in full.
B59: THIS IS THE CHANNEL SEPARATION RULE, and it is the reason physical risk can sit in PD and in LGD without double counting. The PD channel takes only the flow that reaches the income statement: business interruption and repair expense, which is what determines whether the borrower can service the loan. The remaining 40% is capital replacement, which is where the collateral and LGD channel operates. The two shares sum to one, so the same damage is never charged twice. If the LGD module is reattached, it must use the 40% remainder and not the full loss.

Sheet Physical_Exposure
B1: Physical risk: sector exposure and physical cost ratio
B2: Exposure weights are RELATIVE, not absolute. They redistribute the national annual average loss across sectors; they do not change its total. Column H to J normalise the raw weights so that the value-added-weighted average is exactly 1.00, which guarantees the national loss is preserved whatever weights are entered.
B5: ID | C5: Sector | D5: GVA share | E5: H1 raw | F5: H2 raw | G5: H3 raw | H5: H1 used | I5: H2 used | J5: H3 used | K5: Reasoning
B6: S01 | C6: Agriculture, Forestry & Fishing | D6: =Sector_Master!E8/Sector_Master!$E$18 -> 0.0237541 | E6: 2.5 | F6: 3 | G6: 5 | H6: =E6/E$16 -> 2.4013189 | I6: =F6/F$16 -> 2.5755992 | J6: =G6/G$16 -> 5.2045755 | K6: Batinah farms were the worst-hit sector in Shaheen. Outdoor labour throughout. Overwhelmingly the most water-dependent activity in the economy.
B7: S02 | C7: Oil & Gas Extraction | D7: =Sector_Master!E9/Sector_Master!$E$18 -> 0.35149953 | E7: 0.7 | F7: 1.5 | G7: 1.5 | H7: =E7/E$16 -> 0.67236929 | I7: =F7/F$16 -> 1.2877996 | J7: =G7/G$16 -> 1.5613727 | K7: Producing fields are largely inland and away from cyclone tracks, though export terminals and coastal infrastructure are exposed. Outdoor operations in extreme heat. Water is used for enhanced oil recovery.
B8: S03 | C8: Mining & Quarrying (non-oil) | D8: =Sector_Master!E10/Sector_Master!$E$18 -> 0.0049042144 | E8: 1 | F8: 3 | G8: 1.5 | H8: =E8/E$16 -> 0.96052756 | I8: =F8/F$16 -> 2.5755992 | J8: =G8/G$16 -> 1.5613727 | K8: Quarries are dispersed. Entirely outdoor work, so heat exposure is at the top of the range.
B9: S04 | C9: Manufacturing | D9: =Sector_Master!E11/Sector_Master!$E$18 -> 0.091024691 | E9: 2 | F9: 1 | G9: 1.2 | H9: =E9/E$16 -> 1.9210551 | I9: =F9/F$16 -> 0.85853307 | J9: =G9/G$16 -> 1.2490981 | K9: Oman's industrial base is concentrated in coastal zones at Sohar, Duqm and Salalah, which is exactly where cyclones make landfall. Production is mostly indoors.
B10: S05 | C10: Electricity, Gas, Water & Waste | D10: =Sector_Master!E12/Sector_Master!$E$18 -> 0.023116905 | E10: 2.2 | F10: 1.2 | G10: 2 | H10: =E10/E$16 -> 2.1131606 | I10: =F10/F$16 -> 1.0302397 | J10: =G10/G$16 -> 2.0818302 | K10: Generation and desalination plants sit on the coast, and distribution networks failed widely in both Gonu and Shaheen. Desalination energy demand rises with water stress.
B11: S06 | C11: Construction | D11: =Sector_Master!E13/Sector_Master!$E$18 -> 0.065921985 | E11: 1.5 | F11: 3.5 | G11: 0.8 | H11: =E11/E$16 -> 1.4407913 | I11: =F11/F$16 -> 3.0048658 | J11: =G11/G$16 -> 0.83273208 | K11: Sites, plant and stored materials are exposed. Highest heat exposure of any sector: outdoor labour subject to statutory midday working bans in summer.
B12: S07 | C12: Wholesale & Retail Trade | D12: =Sector_Master!E14/Sector_Master!$E$18 -> 0.075438385 | E12: 1.8 | F12: 0.5 | G12: 0.2 | H12: =E12/E$16 -> 1.7289496 | I12: =F12/F$16 -> 0.42926654 | J12: =G12/G$16 -> 0.20818302 | K12: Retail premises and warehousing are concentrated along the populated Batinah coast.
B13: S08 | C13: Transport & Storage | D13: =Sector_Master!E15/Sector_Master!$E$18 -> 0.040054086 | E13: 2 | F13: 1.5 | G13: 0.2 | H13: =E13/E$16 -> 1.9210551 | I13: =F13/F$16 -> 1.2877996 | J13: =G13/G$16 -> 0.20818302 | K13: Ports, roads and logistics assets are coastal and were among the most visibly damaged in Shaheen.
B14: S09 | C14: Accommodation & Food Services | D14: =Sector_Master!E16/Sector_Master!$E$18 -> 0.01395036 | E14: 2 | F14: 0.8 | G14: 1 | H14: =E14/E$16 -> 1.9210551 | I14: =F14/F$16 -> 0.68682646 | J14: =G14/G$16 -> 1.0409151 | K14: Hotel stock is overwhelmingly coastal, and tourism is water-intensive per guest.
B15: S10 | C15: Financial, Professional, Public & Other Services | D15: =Sector_Master!E17/Sector_Master!$E$18 -> 0.31033575 | E15: 0.5 | F15: 0.3 | G15: 0.2 | H15: =E15/E$16 -> 0.48026378 | I15: =F15/F$16 -> 0.25755992 | J15: =G15/G$16 -> 0.20818302 | K15: Offices, dispersed and mostly inland. Lowest physical exposure of any sector on all three hazards.
C16: GVA-weighted mean of raw weights | E16: =SUMPRODUCT($D6:$D15,E6:E15) -> 1.0410945 | F16: =SUMPRODUCT($D6:$D15,F6:F15) -> 1.1647775 | G16: =SUMPRODUCT($D6:$D15,G6:G15) -> 0.96069314
C17: GVA-weighted mean after normalisation (must be 1.000) | H17: =SUMPRODUCT($D6:$D15,H6:H15) -> 1 | I17: =SUMPRODUCT($D6:$D15,I6:I15) -> 1 | J17: =SUMPRODUCT($D6:$D15,J6:J15) -> 1
C18: Check | H18: =IF(AND(ABS(H17-1)<0.0001,ABS(I17-1)<0.0001,ABS(J17-1)<0.0001),"PASS","FAIL") -> PASS
C20: All thirty raw weights are ANALYST JUDGEMENT, grounded in the damage pattern of Gonu and Shaheen, the coastal concentration of Oman's industrial and tourism assets, and which sectors employ outdoor labour. They are the single largest block of judgement in the physical module and should be replaced with geolocated collateral and site data if the bank holds it.
C23: Physical cost ratio by sector and scenario (annual P&L impact as a share of value added)
B24: ID | C24: Sector | D24: Net Zero 2050 | E24: Delayed Transition | F24: Current Policies | G24: Fragmented World
B25: S01 | C25: Agriculture, Forestry & Fishing | D25: =Physical_Hazard!$D$19*Physical_Hazard!D$45*$H6*(1-Physical_Hazard!$C$55)*Physical_Hazard!$D$55+Physical_Hazard!$D$20*Physical_Hazard!D$46*$I6*(1-Physical_Hazard!$C$56)*Physical_Hazard!$D$56+Physical_Hazard!$D$21*Physical_Hazard!D$47*$J6*(1-Physical_Hazard!$C$57)*Physical_Hazard!$D$57 -> 0.016476475 | E25: =Physical_Hazard!$D$19*Physical_Hazard!E$45*$H6*(1-Physical_Hazard!$C$55)*Physical_Hazard!$D$55+Physical_Hazard!$D$20*Physical_Hazard!E$46*$I6*(1-Physical_Hazard!$C$56)*Physical_Hazard!$D$56+Physical_Hazard!$D$21*Physical_Hazard!E$47*$J6*(1-Physical_Hazard!$C$57)*Physical_Hazard!$D$57 -> 0.01828231 | F25: =Physical_Hazard!$D$19*Physical_Hazard!F$45*$H6*(1-Physical_Hazard!$C$55)*Physical_Hazard!$D$55+Physical_Hazard!$D$20*Physical_Hazard!F$46*$I6*(1-Physical_Hazard!$C$56)*Physical_Hazard!$D$56+Physical_Hazard!$D$21*Physical_Hazard!F$47*$J6*(1-Physical_Hazard!$C$57)*Physical_Hazard!$D$57 -> 0.027614921 | G25: =Physical_Hazard!$D$19*Physical_Hazard!G$45*$H6*(1-Physical_Hazard!$C$55)*Physical_Hazard!$D$55+Physical_Hazard!$D$20*Physical_Hazard!G$46*$I6*(1-Physical_Hazard!$C$56)*Physical_Hazard!$D$56+Physical_Hazard!$D$21*Physical_Hazard!G$47*$J6*(1-Physical_Hazard!$C$57)*Physical_Hazard!$D$57 -> 0.022991798
B26: S02 | C26: Oil & Gas Extraction | D26: =Physical_Hazard!$D$19*Physical_Hazard!D$45*$H7*(1-Physical_Hazard!$C$55)*Physical_Hazard!$D$55+Physical_Hazard!$D$20*Physical_Hazard!D$46*$I7*(1-Physical_Hazard!$C$56)*Physical_Hazard!$D$56+Physical_Hazard!$D$21*Physical_Hazard!D$47*$J7*(1-Physical_Hazard!$C$57)*Physical_Hazard!$D$57 -> 0.0064994814 | E26: =Physical_Hazard!$D$19*Physical_Hazard!E$45*$H7*(1-Physical_Hazard!$C$55)*Physical_Hazard!$D$55+Physical_Hazard!$D$20*Physical_Hazard!E$46*$I7*(1-Physical_Hazard!$C$56)*Physical_Hazard!$D$56+Physical_Hazard!$D$21*Physical_Hazard!E$47*$J7*(1-Physical_Hazard!$C$57)*Physical_Hazard!$D$57 -> 0.0072663239 | F26: =Physical_Hazard!$D$19*Physical_Hazard!F$45*$H7*(1-Physical_Hazard!$C$55)*Physical_Hazard!$D$55+Physical_Hazard!$D$20*Physical_Hazard!F$46*$I7*(1-Physical_Hazard!$C$56)*Physical_Hazard!$D$56+Physical_Hazard!$D$21*Physical_Hazard!F$47*$J7*(1-Physical_Hazard!$C$57)*Physical_Hazard!$D$57 -> 0.01129257 | G26: =Physical_Hazard!$D$19*Physical_Hazard!G$45*$H7*(1-Physical_Hazard!$C$55)*Physical_Hazard!$D$55+Physical_Hazard!$D$20*Physical_Hazard!G$46*$I7*(1-Physical_Hazard!$C$56)*Physical_Hazard!$D$56+Physical_Hazard!$D$21*Physical_Hazard!G$47*$J7*(1-Physical_Hazard!$C$57)*Physical_Hazard!$D$57 -> 0.0092865145
B27: S03 | C27: Mining & Quarrying (non-oil) | D27: =Physical_Hazard!$D$19*Physical_Hazard!D$45*$H8*(1-Physical_Hazard!$C$55)*Physical_Hazard!$D$55+Physical_Hazard!$D$20*Physical_Hazard!D$46*$I8*(1-Physical_Hazard!$C$56)*Physical_Hazard!$D$56+Physical_Hazard!$D$21*Physical_Hazard!D$47*$J8*(1-Physical_Hazard!$C$57)*Physical_Hazard!$D$57 -> 0.010911436 | E27: =Physical_Hazard!$D$19*Physical_Hazard!E$45*$H8*(1-Physical_Hazard!$C$55)*Physical_Hazard!$D$55+Physical_Hazard!$D$20*Physical_Hazard!E$46*$I8*(1-Physical_Hazard!$C$56)*Physical_Hazard!$D$56+Physical_Hazard!$D$21*Physical_Hazard!E$47*$J8*(1-Physical_Hazard!$C$57)*Physical_Hazard!$D$57 -> 0.012289413 | F27: =Physical_Hazard!$D$19*Physical_Hazard!F$45*$H8*(1-Physical_Hazard!$C$55)*Physical_Hazard!$D$55+Physical_Hazard!$D$20*Physical_Hazard!F$46*$I8*(1-Physical_Hazard!$C$56)*Physical_Hazard!$D$56+Physical_Hazard!$D$21*Physical_Hazard!F$47*$J8*(1-Physical_Hazard!$C$57)*Physical_Hazard!$D$57 -> 0.019616425 | G27: =Physical_Hazard!$D$19*Physical_Hazard!G$45*$H8*(1-Physical_Hazard!$C$55)*Physical_Hazard!$D$55+Physical_Hazard!$D$20*Physical_Hazard!G$46*$I8*(1-Physical_Hazard!$C$56)*Physical_Hazard!$D$56+Physical_Hazard!$D$21*Physical_Hazard!G$47*$J8*(1-Physical_Hazard!$C$57)*Physical_Hazard!$D$57 -> 0.015949272
B28: S04 | C28: Manufacturing | D28: =Physical_Hazard!$D$19*Physical_Hazard!D$45*$H9*(1-Physical_Hazard!$C$55)*Physical_Hazard!$D$55+Physical_Hazard!$D$20*Physical_Hazard!D$46*$I9*(1-Physical_Hazard!$C$56)*Physical_Hazard!$D$56+Physical_Hazard!$D$21*Physical_Hazard!D$47*$J9*(1-Physical_Hazard!$C$57)*Physical_Hazard!$D$57 -> 0.0064242651 | E28: =Physical_Hazard!$D$19*Physical_Hazard!E$45*$H9*(1-Physical_Hazard!$C$55)*Physical_Hazard!$D$55+Physical_Hazard!$D$20*Physical_Hazard!E$46*$I9*(1-Physical_Hazard!$C$56)*Physical_Hazard!$D$56+Physical_Hazard!$D$21*Physical_Hazard!E$47*$J9*(1-Physical_Hazard!$C$57)*Physical_Hazard!$D$57 -> 0.0071248132 | F28: =Physical_Hazard!$D$19*Physical_Hazard!F$45*$H9*(1-Physical_Hazard!$C$55)*Physical_Hazard!$D$55+Physical_Hazard!$D$20*Physical_Hazard!F$46*$I9*(1-Physical_Hazard!$C$56)*Physical_Hazard!$D$56+Physical_Hazard!$D$21*Physical_Hazard!F$47*$J9*(1-Physical_Hazard!$C$57)*Physical_Hazard!$D$57 -> 0.010722697 | G28: =Physical_Hazard!$D$19*Physical_Hazard!G$45*$H9*(1-Physical_Hazard!$C$55)*Physical_Hazard!$D$55+Physical_Hazard!$D$20*Physical_Hazard!G$46*$I9*(1-Physical_Hazard!$C$56)*Physical_Hazard!$D$56+Physical_Hazard!$D$21*Physical_Hazard!G$47*$J9*(1-Physical_Hazard!$C$57)*Physical_Hazard!$D$57 -> 0.00894478
B29: S05 | C29: Electricity, Gas, Water & Waste | D29: =Physical_Hazard!$D$19*Physical_Hazard!D$45*$H10*(1-Physical_Hazard!$C$55)*Physical_Hazard!$D$55+Physical_Hazard!$D$20*Physical_Hazard!D$46*$I10*(1-Physical_Hazard!$C$56)*Physical_Hazard!$D$56+Physical_Hazard!$D$21*Physical_Hazard!D$47*$J10*(1-Physical_Hazard!$C$57)*Physical_Hazard!$D$57 -> 0.0080605421 | E29: =Physical_Hazard!$D$19*Physical_Hazard!E$45*$H10*(1-Physical_Hazard!$C$55)*Physical_Hazard!$D$55+Physical_Hazard!$D$20*Physical_Hazard!E$46*$I10*(1-Physical_Hazard!$C$56)*Physical_Hazard!$D$56+Physical_Hazard!$D$21*Physical_Hazard!E$47*$J10*(1-Physical_Hazard!$C$57)*Physical_Hazard!$D$57 -> 0.0089195449 | F29: =Physical_Hazard!$D$19*Physical_Hazard!F$45*$H10*(1-Physical_Hazard!$C$55)*Physical_Hazard!$D$55+Physical_Hazard!$D$20*Physical_Hazard!F$46*$I10*(1-Physical_Hazard!$C$56)*Physical_Hazard!$D$56+Physical_Hazard!$D$21*Physical_Hazard!F$47*$J10*(1-Physical_Hazard!$C$57)*Physical_Hazard!$D$57 -> 0.013315013 | G29: =Physical_Hazard!$D$19*Physical_Hazard!G$45*$H10*(1-Physical_Hazard!$C$55)*Physical_Hazard!$D$55+Physical_Hazard!$D$20*Physical_Hazard!G$46*$I10*(1-Physical_Hazard!$C$56)*Physical_Hazard!$D$56+Physical_Hazard!$D$21*Physical_Hazard!G$47*$J10*(1-Physical_Hazard!$C$57)*Physical_Hazard!$D$57 -> 0.011145856
B30: S06 | C30: Construction | D30: =Physical_Hazard!$D$19*Physical_Hazard!D$45*$H11*(1-Physical_Hazard!$C$55)*Physical_Hazard!$D$55+Physical_Hazard!$D$20*Physical_Hazard!D$46*$I11*(1-Physical_Hazard!$C$56)*Physical_Hazard!$D$56+Physical_Hazard!$D$21*Physical_Hazard!D$47*$J11*(1-Physical_Hazard!$C$57)*Physical_Hazard!$D$57 -> 0.012126552 | E30: =Physical_Hazard!$D$19*Physical_Hazard!E$45*$H11*(1-Physical_Hazard!$C$55)*Physical_Hazard!$D$55+Physical_Hazard!$D$20*Physical_Hazard!E$46*$I11*(1-Physical_Hazard!$C$56)*Physical_Hazard!$D$56+Physical_Hazard!$D$21*Physical_Hazard!E$47*$J11*(1-Physical_Hazard!$C$57)*Physical_Hazard!$D$57 -> 0.013702392 | F30: =Physical_Hazard!$D$19*Physical_Hazard!F$45*$H11*(1-Physical_Hazard!$C$55)*Physical_Hazard!$D$55+Physical_Hazard!$D$20*Physical_Hazard!F$46*$I11*(1-Physical_Hazard!$C$56)*Physical_Hazard!$D$56+Physical_Hazard!$D$21*Physical_Hazard!F$47*$J11*(1-Physical_Hazard!$C$57)*Physical_Hazard!$D$57 -> 0.022114953 | G30: =Physical_Hazard!$D$19*Physical_Hazard!G$45*$H11*(1-Physical_Hazard!$C$55)*Physical_Hazard!$D$55+Physical_Hazard!$D$20*Physical_Hazard!G$46*$I11*(1-Physical_Hazard!$C$56)*Physical_Hazard!$D$56+Physical_Hazard!$D$21*Physical_Hazard!G$47*$J11*(1-Physical_Hazard!$C$57)*Physical_Hazard!$D$57 -> 0.017898683
B31: S07 | C31: Wholesale & Retail Trade | D31: =Physical_Hazard!$D$19*Physical_Hazard!D$45*$H12*(1-Physical_Hazard!$C$55)*Physical_Hazard!$D$55+Physical_Hazard!$D$20*Physical_Hazard!D$46*$I12*(1-Physical_Hazard!$C$56)*Physical_Hazard!$D$56+Physical_Hazard!$D$21*Physical_Hazard!D$47*$J12*(1-Physical_Hazard!$C$57)*Physical_Hazard!$D$57 -> 0.0037660892 | E31: =Physical_Hazard!$D$19*Physical_Hazard!E$45*$H12*(1-Physical_Hazard!$C$55)*Physical_Hazard!$D$55+Physical_Hazard!$D$20*Physical_Hazard!E$46*$I12*(1-Physical_Hazard!$C$56)*Physical_Hazard!$D$56+Physical_Hazard!$D$21*Physical_Hazard!E$47*$J12*(1-Physical_Hazard!$C$57)*Physical_Hazard!$D$57 -> 0.0041781021 | F31: =Physical_Hazard!$D$19*Physical_Hazard!F$45*$H12*(1-Physical_Hazard!$C$55)*Physical_Hazard!$D$55+Physical_Hazard!$D$20*Physical_Hazard!F$46*$I12*(1-Physical_Hazard!$C$56)*Physical_Hazard!$D$56+Physical_Hazard!$D$21*Physical_Hazard!F$47*$J12*(1-Physical_Hazard!$C$57)*Physical_Hazard!$D$57 -> 0.0062840799 | G31: =Physical_Hazard!$D$19*Physical_Hazard!G$45*$H12*(1-Physical_Hazard!$C$55)*Physical_Hazard!$D$55+Physical_Hazard!$D$20*Physical_Hazard!G$46*$I12*(1-Physical_Hazard!$C$56)*Physical_Hazard!$D$56+Physical_Hazard!$D$21*Physical_Hazard!G$47*$J12*(1-Physical_Hazard!$C$57)*Physical_Hazard!$D$57 -> 0.005245403
B32: S08 | C32: Transport & Storage | D32: =Physical_Hazard!$D$19*Physical_Hazard!D$45*$H13*(1-Physical_Hazard!$C$55)*Physical_Hazard!$D$55+Physical_Hazard!$D$20*Physical_Hazard!D$46*$I13*(1-Physical_Hazard!$C$56)*Physical_Hazard!$D$56+Physical_Hazard!$D$21*Physical_Hazard!D$47*$J13*(1-Physical_Hazard!$C$57)*Physical_Hazard!$D$57 -> 0.0067073924 | E32: =Physical_Hazard!$D$19*Physical_Hazard!E$45*$H13*(1-Physical_Hazard!$C$55)*Physical_Hazard!$D$55+Physical_Hazard!$D$20*Physical_Hazard!E$46*$I13*(1-Physical_Hazard!$C$56)*Physical_Hazard!$D$56+Physical_Hazard!$D$21*Physical_Hazard!E$47*$J13*(1-Physical_Hazard!$C$57)*Physical_Hazard!$D$57 -> 0.0075268282 | F32: =Physical_Hazard!$D$19*Physical_Hazard!F$45*$H13*(1-Physical_Hazard!$C$55)*Physical_Hazard!$D$55+Physical_Hazard!$D$20*Physical_Hazard!F$46*$I13*(1-Physical_Hazard!$C$56)*Physical_Hazard!$D$56+Physical_Hazard!$D$21*Physical_Hazard!F$47*$J13*(1-Physical_Hazard!$C$57)*Physical_Hazard!$D$57 -> 0.011833316 | G32: =Physical_Hazard!$D$19*Physical_Hazard!G$45*$H13*(1-Physical_Hazard!$C$55)*Physical_Hazard!$D$55+Physical_Hazard!$D$20*Physical_Hazard!G$46*$I13*(1-Physical_Hazard!$C$56)*Physical_Hazard!$D$56+Physical_Hazard!$D$21*Physical_Hazard!G$47*$J13*(1-Physical_Hazard!$C$57)*Physical_Hazard!$D$57 -> 0.0096872415
B33: S09 | C33: Accommodation & Food Services | D33: =Physical_Hazard!$D$19*Physical_Hazard!D$45*$H14*(1-Physical_Hazard!$C$55)*Physical_Hazard!$D$55+Physical_Hazard!$D$20*Physical_Hazard!D$46*$I14*(1-Physical_Hazard!$C$56)*Physical_Hazard!$D$56+Physical_Hazard!$D$21*Physical_Hazard!D$47*$J14*(1-Physical_Hazard!$C$57)*Physical_Hazard!$D$57 -> 0.0056719972 | E33: =Physical_Hazard!$D$19*Physical_Hazard!E$45*$H14*(1-Physical_Hazard!$C$55)*Physical_Hazard!$D$55+Physical_Hazard!$D$20*Physical_Hazard!E$46*$I14*(1-Physical_Hazard!$C$56)*Physical_Hazard!$D$56+Physical_Hazard!$D$21*Physical_Hazard!E$47*$J14*(1-Physical_Hazard!$C$57)*Physical_Hazard!$D$57 -> 0.0062809294 | F33: =Physical_Hazard!$D$19*Physical_Hazard!F$45*$H14*(1-Physical_Hazard!$C$55)*Physical_Hazard!$D$55+Physical_Hazard!$D$20*Physical_Hazard!F$46*$I14*(1-Physical_Hazard!$C$56)*Physical_Hazard!$D$56+Physical_Hazard!$D$21*Physical_Hazard!F$47*$J14*(1-Physical_Hazard!$C$57)*Physical_Hazard!$D$57 -> 0.009393502 | G33: =Physical_Hazard!$D$19*Physical_Hazard!G$45*$H14*(1-Physical_Hazard!$C$55)*Physical_Hazard!$D$55+Physical_Hazard!$D$20*Physical_Hazard!G$46*$I14*(1-Physical_Hazard!$C$56)*Physical_Hazard!$D$56+Physical_Hazard!$D$21*Physical_Hazard!G$47*$J14*(1-Physical_Hazard!$C$57)*Physical_Hazard!$D$57 -> 0.0078581776
B34: S10 | C34: Financial, Professional, Public & Other Services | D34: =Physical_Hazard!$D$19*Physical_Hazard!D$45*$H15*(1-Physical_Hazard!$C$55)*Physical_Hazard!$D$55+Physical_Hazard!$D$20*Physical_Hazard!D$46*$I15*(1-Physical_Hazard!$C$56)*Physical_Hazard!$D$56+Physical_Hazard!$D$21*Physical_Hazard!D$47*$J15*(1-Physical_Hazard!$C$57)*Physical_Hazard!$D$57 -> 0.001634379 | E34: =Physical_Hazard!$D$19*Physical_Hazard!E$45*$H15*(1-Physical_Hazard!$C$55)*Physical_Hazard!$D$55+Physical_Hazard!$D$20*Physical_Hazard!E$46*$I15*(1-Physical_Hazard!$C$56)*Physical_Hazard!$D$56+Physical_Hazard!$D$21*Physical_Hazard!E$47*$J15*(1-Physical_Hazard!$C$57)*Physical_Hazard!$D$57 -> 0.0018214048 | F34: =Physical_Hazard!$D$19*Physical_Hazard!F$45*$H15*(1-Physical_Hazard!$C$55)*Physical_Hazard!$D$55+Physical_Hazard!$D$20*Physical_Hazard!F$46*$I15*(1-Physical_Hazard!$C$56)*Physical_Hazard!$D$56+Physical_Hazard!$D$21*Physical_Hazard!F$47*$J15*(1-Physical_Hazard!$C$57)*Physical_Hazard!$D$57 -> 0.0027917362 | G34: =Physical_Hazard!$D$19*Physical_Hazard!G$45*$H15*(1-Physical_Hazard!$C$55)*Physical_Hazard!$D$55+Physical_Hazard!$D$20*Physical_Hazard!G$46*$I15*(1-Physical_Hazard!$C$56)*Physical_Hazard!$D$56+Physical_Hazard!$D$21*Physical_Hazard!G$47*$J15*(1-Physical_Hazard!$C$57)*Physical_Hazard!$D$57 -> 0.0023104411
C35: GVA-weighted average (must equal the national AAL after severity and P&L conversion) | D35: =SUMPRODUCT($D$6:$D$15,D25:D34) -> 0.0054390672 | E35: =SUMPRODUCT($D$6:$D$15,E25:E34) -> 0.006076212 | F35: =SUMPRODUCT($D$6:$D$15,F25:F34) -> 0.0094086493 | G35: =SUMPRODUCT($D$6:$D$15,G25:G34) -> 0.0077506991
C37: Formula, per sector j and scenario s: physical cost ratio = SUM over hazards of [ baseline AAL x severity multiplier x normalised exposure x (1 - insurance recovery) x share hitting the P&L ]. Every term is on this tab or on Physical_Hazard, and each is sourced or flagged individually.

Sheet EU_k_Calibration
B1: Calibration of k on the MEDIAN European firm
B2: k = push_EU / LN(1 + cost_ratio_EU). Every input is either traced to ECB Occasional Paper 281 (Alogoskoufis et al., September 2021) or flagged as an assumption with its reasoning stated beside it.
B4: A. PD anchor, median European firm [VERIFIED]
B5: Median firm baseline PD | C5: 0.02 | F5: VERIFIED: OP 281 Chart 31 panel b, right-hand axis. The median-firm series runs from about 1.9% in 2020 to about 2.4% by 2050.
B6: ANCHOR A: relative PD increase, TRANSITION ONLY | C6: 0.005 | F6: VERIFIED: OP 281 Section 5.3. The median firm carries a PD about 0.5% HIGHER under orderly transition than under hot house world during the policy implementation phase (the first ten years). Hot house world has NO transition policy, so this difference isolates the transition effect cleanly. Chart 28 confirms these are relative percentage CHANGES, not percentage points.
B7: ANCHOR B: relative PD increase, DISORDERLY vs ORDERLY at 2050 | C7: 0.025 | F7: VERIFIED: OP 281 Section 5.3. Median-firm PDs are about 2.5% higher by 2050 under disorderly than under orderly transition. This is the figure the v2 live sheet used. It is not transition-only, so it is offered as a sensitivity rather than the primary anchor.
B8: Anchor in use (A or B) | C8: A
B9: Stressed PD implied | C9: =C5*(1+IF(C8="A",C6,C7)) -> 0.0201
B10: push_EU = N-1(PD stressed) - N-1(PD baseline) | C10: =NORMSINV(C9)-NORMSINV(C5) -> 0.0020609753
B12: DISCARDED ANCHORS, for the record. The v2 register carried 2.0% to 4.0% with an intensity of 20,000 t/$m. Both trace to OP 281 Section 5.4: coal mining (NACE B05) PDs rise to 4% under disorderly transition, a 100% increase, and coal mining emits upward of 20,000 tCO2 per million dollars of revenue on a SCOPE 3 basis. They were a self-consistent COAL MINING pair, not a contradiction. They are not median-firm figures and are not used.
B16: B. Emission intensity of the median European firm
B17: THE PROBLEM. OP 281 reports intensity per unit of TURNOVER. Oman publishes value added by activity but not turnover, so the model runs on GVA. v2 calibrated on one basis and applied on the other, which inflated every Oman cost ratio. Two routes are provided; both are computed, and the selector below chooses which feeds k.
B19: ROUTE 1, THE WORKAROUND (default). Rather than converting the EU turnover figure onto a GVA basis with an unsourced ratio, build the EU intensity the SAME WAY the Oman intensity is built: national territorial Scope 1 emissions divided by national gross value added. National territorial emissions ARE Scope 1 by construction, so the two sides become structurally identical and the turnover conversion never enters. One documented adjustment is then applied for median firm versus economy average.
B21: EU27 total GHG emissions (MtCO2e) | C21: 3000 | F21: TO VERIFY: European Environment Agency EU27 GHG inventory, latest reporting year, total excluding LULUCF. Match the reporting year to the GVA year below.
B22: Household and own-account share to exclude | C22: 0.2 | F22: Residential heating plus private road transport. Removed so the EU figure covers the corporate economy only, exactly as the Oman figure does via the Households column on Emissions_Allocation.
B23: EU27 total gross value added (EUR bn) | C23: 15200 | F23: TO VERIFY: Eurostat nama_10_a10, value added at basic prices, current prices, same year as the emissions figure.
B24: EU corporate Scope 1 intensity (tCO2e per EURm GVA) | C24: =C21*(1-C22)*1000/C23 -> 157.89474
B25: Median firm to economy average intensity ratio | C25: 0.57 | F25: Basis: OP 281 Chart 12 reports about 600 tCO2e/EURm for micro firms against about 1,100 for large firms, and states that large firms produce roughly 90% of total emissions. The emissions-weighted average therefore sits close to the large-firm figure, and the ratio of a typical smaller firm to that average is about 600/1,050, i.e. 0.57. Without this adjustment the calibration would attribute the emissions of the largest firms to the median one.
B26: ROUTE 1 intensity (tCO2e per EURm GVA) | C26: =C24*C25 -> 90
B28: ROUTE 2, FIRM-LEVEL. Retained for comparison. It needs three assumptions instead of one adjustment, and reintroduces the turnover-to-GVA conversion that caused the original defect.
B29: Median firm total intensity, Scope 1+2+3 (tCO2e per EURm turnover) | C29: 850 | F29: OP 281 Chart 12 reports about 1,100 for large firms and about 600 for micro, Scope 1+2+3. 850 is the mid-point.
B30: Scope 1 share of total emissions | C30: 0.12 | F30: Not published. Charts 12 and 13 both show Scope 3 dominating for every firm size and almost every sector, so a share of 5% to 20% is consistent.
B31: EU turnover / GVA ratio | C31: 3 | F31: Source from Eurostat Structural Business Statistics sbs_na_ind_r2. Set to 1.00 if the Sector_Master basis is switched to TURNOVER.
B32: ROUTE 2 intensity (tCO2e per EURm of the model's denominator) | C32: =IF(Sector_Master!$C$4="TURNOVER",C29*C30,C29*C30*C31) -> 306
B34: INTENSITY ROUTE IN USE (1 or 2) | C34: 1
B35: Selected EU intensity | C35: =IF(C34=1,C26,C32) -> 90
B36: Route 1 is the default because it removes the unit conversion entirely and because its inputs are published national aggregates rather than unpublished firm statistics. Route 1 assumes the Sector_Master basis is GVA; if the basis is switched to TURNOVER, use Route 2.
B39: C. Carbon price paired with the anchor [ASSUMPTION - scenario vintage mismatch]
B40: OP 281 Section 3.1 states the ECB exercise uses the NGFS PHASE I scenarios (NGFS 2020b), not Phase V. The price paired with the PD response must therefore be the Phase I orderly-transition price at the anchor horizon. v2 paired the ECB PD response with a Phase V NDC price of US$80, which is a vintage mismatch. The cell below makes the assumption visible and testable.
B42: NGFS Phase I orderly-transition carbon price at the anchor horizon (US$/tCO2) | C42: 100
B43: USD / EUR | C43: 0.8741
B44: Anchor carbon price (EUR/tCO2) | C44: =C42*C43 -> 87.41
B45: EU pass-through | C45: 0 | F45: CORRECTED, VERIFIED: OP 281 Section 5.1 applies the carbon tax to operating costs with no cost relief; any demand response runs separately through Scope 3 revenues. There is no pass-through in the ECB cost channel. v2 used 50%, inconsistent with how the anchor was generated.
B48: D. Result
B49: cost_ratio_EU = price x intensity x (1 - PT) / 1,000,000 | C49: =C44*C35*(1-C45)/1000000 -> 0.0078669
B50: k SELECTED (feeds StressedPD_Sector) | C50: =C10/LN(1+C49) -> 0.26300976
B53: E. Sensitivity of k to the EU intensity and the anchor
B54: EU intensity (t/EURm) | C54: k (Anchor A) | D54: k (Anchor B)
B55: 50 | C55: =(NORMSINV($C$5*(1+$C$6))-NORMSINV($C$5))/LN(1+$C$44*B55*(1-$C$45)/1000000) -> 0.47259485 | D55: =(NORMSINV($C$5*(1+$C$7))-NORMSINV($C$5))/LN(1+$C$44*B55*(1-$C$45)/1000000) -> 2.34326
B56: 90 | C56: =(NORMSINV($C$5*(1+$C$6))-NORMSINV($C$5))/LN(1+$C$44*B56*(1-$C$45)/1000000) -> 0.26300976 | D56: =(NORMSINV($C$5*(1+$C$7))-NORMSINV($C$5))/LN(1+$C$44*B56*(1-$C$45)/1000000) -> 1.3040774
B57: 150 | C57: =(NORMSINV($C$5*(1+$C$6))-NORMSINV($C$5))/LN(1+$C$44*B57*(1-$C$45)/1000000) -> 0.15821662 | D57: =(NORMSINV($C$5*(1+$C$7))-NORMSINV($C$5))/LN(1+$C$44*B57*(1-$C$45)/1000000) -> 0.78448311
B58: 250 | C58: =(NORMSINV($C$5*(1+$C$6))-NORMSINV($C$5))/LN(1+$C$44*B58*(1-$C$45)/1000000) -> 0.095339798 | D58: =(NORMSINV($C$5*(1+$C$7))-NORMSINV($C$5))/LN(1+$C$44*B58*(1-$C$45)/1000000) -> 0.4727219
B59: 400 | C59: =(NORMSINV($C$5*(1+$C$6))-NORMSINV($C$5))/LN(1+$C$44*B59*(1-$C$45)/1000000) -> 0.059970225 | D59: =(NORMSINV($C$5*(1+$C$7))-NORMSINV($C$5))/LN(1+$C$44*B59*(1-$C$45)/1000000) -> 0.29734947
B61: k moves by roughly a factor of eight across this grid and by a further factor of five between the two anchors. That range is the honest measure of how much public sources can pin down. The two ways to narrow it are (a) three or more PD anchors from OP 281 across sectors of differing intensity, which would also give the LN(1+x) curvature some empirical support instead of imposing it, and (b) a median-firm Scope 1 intensity, which would need the underlying Urgentem data.
B65: F. Extrapolation range
B66: Cost ratio at the calibration point | C66: =C49 -> 0.0078669
B67: Maximum cost ratio applied to Oman | C67: =MAX(StressedPD_Sector!O16:R25) -> 1.0203788
B68: Extrapolation multiple | C68: =IF(C66=0,0,C67/C66) -> 129.70533
B69: k is calibrated at an EU cost ratio of well under 1% of GVA and applied to Oman cost ratios approaching 100% of GVA, so the extrapolation multiple is large by construction: the EU median firm faces a trivial carbon bill while Omani utilities and refiners face an existential one. The LN(1+x) form does the whole job of bridging that gap and it is not empirically supported over that range. Two responses, both defensible: disclose the multiple in the methodology note as a stated limitation, or cap the applied cost ratio at a level the bank is willing to defend and report the cap. Do not present a point estimate of stressed PD for the utilities sector without one of the two.

Sheet k_MultiAnchor
B1: Multi-anchor calibration of k and the curvature parameter
B2: Option 3. A single anchor identifies a SCALE only; the shape of push = k x g(cost ratio) is imposed. This tab extracts every usable PD anchor from ECB Occasional Paper 281, generalises the functional form to one curvature parameter, and reports what the anchors can and cannot identify.
B4: A. Anchors extracted from ECB OP 281
B5: # | C5: Group | D5: Baseline PD | E5: Relative PD change | F5: Stressed PD | G5: push | H5: Identification | I5: Mechanism generating the response | J5: Use
B6: 1 | C6: Median European firm | D6: 0.02 | E6: 0.005 | F6: =D6*(1+E6) -> 0.0201 | G6: =NORMSINV(F6)-NORMSINV(D6) -> 0.0020609753 | H6: Orderly transition vs hot house world, policy implementation phase (Section 5.3). Hot house world has no transition policy, so this is a clean transition-only difference. | I6: Scope 1 carbon cost into operating expenses (Section 5.1). | J6: FIT
B7: 2 | C7: High-emitting firms (top 10% by intensity) | D7: 0.02 | E7: 0.02 | F7: =D7*(1+E7) -> 0.0204 | G7: =NORMSINV(F7)-NORMSINV(D7) -> 0.0081921569 | H7: Orderly transition vs no policy action, short term (Section 5.4). Stated in the same sentence as the median 0.5% figure, so it is the same identification. | I7: Scope 1 carbon cost into operating expenses. | J7: FIT
B8: 3 | C8: Coal mining NACE B05, orderly | D8: 0.02 | E8: 1.5 | F8: =D8*(1+E8) -> 0.05 | G8: =NORMSINV(F8)-NORMSINV(D8) -> 0.40889528 | H8: PD rises to 5.0%, a 150% increase on current values (Section 5.4). Measured against the 2020 starting point, not against hot house world. | I8: MAINLY Scope 3 abatement investment raising leverage, stated explicitly in Section 5.4. NOT a Scope 1 cost response. | J8: CHECK
B9: 4 | C9: Coal mining NACE B05, disorderly | D9: 0.02 | E9: 1 | F9: =D9*(1+E9) -> 0.04 | G9: =NORMSINV(F9)-NORMSINV(D9) -> 0.30306284 | H9: PD rises to 4.0%, a 100% increase on current values (Section 5.4). | I9: As anchor 3. | J9: CHECK
B11: All four are VERIFIED against the paper. Anchors 1 and 2 are the only pair on a common identification AND a common mechanism, so they are the only pair that can fit a Scope 1 cost curve. Anchors 3 and 4 are retained as an out-of-sample check.
B14: B. Functional form and fit
B15: Generalised family: push = k x g(x, theta), where g(x, theta) = ((1+x)^theta - 1)/theta, and g = LN(1+x) at theta = 0. theta = +1 is linear, theta = 0 is the logarithmic form used in v4, theta = -1 is saturating x/(1+x). One parameter spans the whole plausible range of shapes.
B17: CURVATURE PARAMETER theta | C17: 0
B18: EU median firm cost ratio (anchor 1) | C18: =EU_k_Calibration!C49 -> 0.0078669
B19: g(x, theta) at anchor 1 | C19: =IF(ABS($C$17)<0.000000000001,LN(1+C18),((1+C18)^$C$17-1)/$C$17) -> 0.0078361173
B20: k FITTED on anchor 1 | C20: =G6/C19 -> 0.26300976
B23: C. What the second anchor actually identifies
B24: push ratio, high emitters / median | C24: =G7/G6 -> 3.9748932
B25: Implied intensity multiple of the top decile over the median | C25: =IFERROR(IF(ABS($C$17)<0.000000000001,(EXP($C$19*C24)-1)/$C$18,((1+$C$17*$C$19*C24)^(1/$C$17)-1)/$C$18),"n/a") -> 4.0216471
B26: THIS IS THE RESULT THAT MATTERS. The second anchor does not pin down theta. It pins down the intensity multiple that theta implies, and that multiple barely moves: 3.97 at theta = +1, 4.02 at theta = 0, 4.07 at theta = -1. A spread of 2.5% across the entire plausible range of shapes.
B29: The reason is that both anchors sit at cost ratios below 4% of value added, where every smooth function is indistinguishable from a straight line. Curvature is a property of behaviour at LARGE cost ratios, and neither anchor is anywhere near that region.
B32: What the second anchor does give you is a VALIDATION rather than an identification. The implied top-decile-to-median intensity multiple of about 4 is entirely plausible for a firm-level emissions distribution, so the anchors are consistent with the form in use. They simply cannot discriminate between it and the alternatives.
B36: D. Out-of-sample check against the coal anchors
B37: push ratio, coal (orderly) / median | C37: =G8/G6 -> 198.39892
B38: Intensity multiple coal would need, at the current theta | C38: =IFERROR(IF(ABS($C$17)<0.000000000001,(EXP($C$19*C37)-1)/$C$18,((1+$C$17*$C$19*C37)^(1/$C$17)-1)/$C$18),"unreachable at this theta") -> 474.5908
B39: Plausible coal Scope 1 intensity multiple over the median firm | C39: 10 | H39: OP 281 Section 5.4 puts coal mining above 20,000 tCO2 per million dollars of revenue on a SCOPE 3 basis, against under 3,000 for every other sector. Coal's Scope 1 (mine methane, machinery) is a small fraction of that. Ten times the median firm's Scope 1 intensity is generous.
B40: Discrepancy factor | C40: =IFERROR(C38/C39,"n/a") -> 47.45908
B41: Verdict | C41: =IF(NOT(ISNUMBER(C38)),"REJECTED - form cannot reach the coal anchor at any intensity",IF(C40>3,"REJECTED - coal response is not a Scope 1 cost response","consistent")) -> REJECTED - coal response is not a Scope 1 cost response
B42: The coal anchor demands an intensity 20 to 50 times higher than coal mining plausibly has, and at theta = -1 the saturating form cannot reach it at any intensity at all. That is not a failure of the fit: it confirms what OP 281 states directly, that coal's PD impact is driven mainly by the need to fund abatement of very high SCOPE 3 emissions, which raises leverage. It is not a Scope 1 operating-cost response, so it cannot calibrate a Scope 1 cost curve and must not be forced into one.
B46: E. Consequence for the Oman result
B47: Maximum Oman cost ratio (post-cap) | C47: =MAX(StressedPD_Sector!O16:R25) -> 1.0203788
B48: theta | C48: Form | D48: k | E48: Implied top-decile multiple | F48: push at max Oman cost ratio | G48: PD at MR5 (2.00% base) | H48: PD multiple
B49: 1 | C49: linear | D49: =$G$6/IF(ABS(B49)<0.000000000001,LN(1+$C$18),((1+$C$18)^B49-1)/B49) -> 0.26198062 | E49: =IFERROR(IF(ABS(B49)<0.000000000001,(EXP(IF(ABS(B49)<0.000000000001,LN(1+$C$18),((1+$C$18)^B49-1)/B49)*$C$24)-1)/$C$18,((1+B49*IF(ABS(B49)<0.000000000001,LN(1+$C$18),((1+$C$18)^B49-1)/B49)*$C$24)^(1/B49)-1)/$C$18),"n/a") -> 3.9748932 | F49: =D49*IF(ABS(B49)<0.000000000001,LN(1+$C$47),((1+$C$47)^B49-1)/B49) -> 0.26731948 | G49: =NORMSDIST(NORMSINV(0.02)+F49) -> 0.037014877 | H49: =G49/0.02 -> 1.8507439
B50: 0.5 | D50: =$G$6/IF(ABS(B50)<0.000000000001,LN(1+$C$18),((1+$C$18)^B50-1)/B50) -> 0.26249485 | E50: =IFERROR(IF(ABS(B50)<0.000000000001,(EXP(IF(ABS(B50)<0.000000000001,LN(1+$C$18),((1+$C$18)^B50-1)/B50)*$C$24)-1)/$C$18,((1+B50*IF(ABS(B50)<0.000000000001,LN(1+$C$18),((1+$C$18)^B50-1)/B50)*$C$24)^(1/B50)-1)/$C$18),"n/a") -> 3.9980585 | F50: =D50*IF(ABS(B50)<0.000000000001,LN(1+$C$47),((1+$C$47)^B50-1)/B50) -> 0.22123083 | G50: =NORMSDIST(NORMSINV(0.02)+F50) -> 0.033437135 | H50: =G50/0.02 -> 1.6718567
B51: 0 | C51: log (in use in v4) | D51: =$G$6/IF(ABS(B51)<0.000000000001,LN(1+$C$18),((1+$C$18)^B51-1)/B51) -> 0.26300976 | E51: =IFERROR(IF(ABS(B51)<0.000000000001,(EXP(IF(ABS(B51)<0.000000000001,LN(1+$C$18),((1+$C$18)^B51-1)/B51)*$C$24)-1)/$C$18,((1+B51*IF(ABS(B51)<0.000000000001,LN(1+$C$18),((1+$C$18)^B51-1)/B51)*$C$24)^(1/B51)-1)/$C$18),"n/a") -> 4.0216471 | F51: =D51*IF(ABS(B51)<0.000000000001,LN(1+$C$47),((1+$C$47)^B51-1)/B51) -> 0.18497083 | G51: =NORMSDIST(NORMSINV(0.02)+F51) -> 0.030826848 | H51: =G51/0.02 -> 1.5413424
B52: -0.5 | D52: =$G$6/IF(ABS(B52)<0.000000000001,LN(1+$C$18),((1+$C$18)^B52-1)/B52) -> 0.26352534 | E52: =IFERROR(IF(ABS(B52)<0.000000000001,(EXP(IF(ABS(B52)<0.000000000001,LN(1+$C$18),((1+$C$18)^B52-1)/B52)*$C$24)-1)/$C$18,((1+B52*IF(ABS(B52)<0.000000000001,LN(1+$C$18),((1+$C$18)^B52-1)/B52)*$C$24)^(1/B52)-1)/$C$18),"n/a") -> 4.0456723 | F52: =D52*IF(ABS(B52)<0.000000000001,LN(1+$C$47),((1+$C$47)^B52-1)/B52) -> 0.15625389 | G52: =NORMSDIST(NORMSINV(0.02)+F52) -> 0.028881317 | H52: =G52/0.02 -> 1.4440659
B53: -1 | C53: saturating | D53: =$G$6/IF(ABS(B53)<0.000000000001,LN(1+$C$18),((1+$C$18)^B53-1)/B53) -> 0.26404159 | E53: =IFERROR(IF(ABS(B53)<0.000000000001,(EXP(IF(ABS(B53)<0.000000000001,LN(1+$C$18),((1+$C$18)^B53-1)/B53)*$C$24)-1)/$C$18,((1+B53*IF(ABS(B53)<0.000000000001,LN(1+$C$18),((1+$C$18)^B53-1)/B53)*$C$24)^(1/B53)-1)/$C$18),"n/a") -> 4.0701476 | F53: =D53*IF(ABS(B53)<0.000000000001,LN(1+$C$47),((1+$C$47)^B53-1)/B53) -> 0.13335244 | G53: =NORMSDIST(NORMSINV(0.02)+F53) -> 0.02740392 | H53: =G53/0.02 -> 1.370196
B55: The Omani utilities PD multiple spans 1.37x to 1.84x across the full curvature range, and nothing in OP 281 narrows it. Option 3 has therefore delivered a second verified anchor and a plausibility validation, but it has NOT closed the extrapolation problem, and it now shows precisely why: every usable anchor lives in the near-linear region, and the only high-intensity anchor is generated by a different mechanism.
B59: F. Practical control
B60: Cost ratio cap (999 = off) | C60: 999
B61: Sectors and scenarios where the cap binds | C61: =COUNTIF(StressedPD_Sector!O16:R25,">="&C60) -> 0
B62: Wired but switched off. Given section E, a cap is the only mechanism that bounds the answer, because the curvature that governs behaviour above the calibration range cannot be estimated from the available anchors. Set it at a cost ratio the bank is prepared to defend, report the level, and report how many sector-scenario cells it binds on. A cap of 0.25 to 0.50 would bind on utilities and manufacturing in the Net Zero scenario and leave every other cell untouched.

Sheet Regression_Tests
B1: Macro leg: specification testing
B2: Dependent variable: probit of the Oman banking-system gross NPL ratio, 2014 to 2024 (11 annual observations). Regressor: Oman real GDP growth (EIU). Seventeen specifications tested; estimation data on Regression_Data.
B4: # | C4: Specification | D4: Form | E4: n | F4: R2 | G4: adj R2 | H4: beta | I4: t | J4: p | K4: DW | L4: Assessment
B5: S1 | C5: N-1(NPLR) ~ g | D5: level | E5: 11 | F5: 0.028 | G5: -0.079 | H5: -0.984 | I5: -0.51 | J5: 0.62 | K5: 0.16 | L5: Specification used in v2. Durbin-Watson 0.16: severe positive residual autocorrelation, the level series is near non-stationary, the fit is spurious.
B6: S2 | C6: N-1(NPLR) ~ g(-1) | D6: level | E6: 11 | F6: 0.1 | G6: 0 | H6: -1.761 | I6: -1 | J6: 0.344 | K6: 0.29 | L6: Autocorrelation unresolved.
B7: S3 | C7: N-1(NPLR) ~ g(-2) | D7: level | E7: 11 | F7: 0.206 | G7: 0.118 | H7: -2.184 | I7: -1.53 | J7: 0.161 | K7: 0.38 | L7: Autocorrelation unresolved.
B8: S4 | C8: N-1(NPLR) ~ MA2(g,g-1) | D8: level | E8: 11 | F8: 0.102 | G8: 0.002 | H8: -2.385 | I8: -1.01 | J8: 0.338 | K8: 0.21 | L8: Autocorrelation unresolved.
B9: S5 | C9: N-1(NPLR) ~ MA2(g-1,g-2) | D9: level | E9: 11 | F9: 0.236 | G9: 0.151 | H9: -3.128 | I9: -1.67 | J9: 0.13 | K9: 0.37 | L9: Autocorrelation unresolved.
B10: S6 | C10: N-1(NPLR) ~ MA3(g..g-2) | D10: level | E10: 11 | F10: 0.277 | G10: 0.197 | H10: -4.62 | I10: -1.86 | J10: 0.096 | K10: 0.23 | L10: Highest level-form R2, but DW 0.23 makes the standard errors uninterpretable. Rejected.
B11: S7 | C11: N-1(NPLR) ~ g + g(-1) | D11: level | E11: 11 | F11: 0.114 | G11: -0.108 | H11: -0.698 | I11: -0.35 | J11: 0.732 | K11: 0.25 | L11: Adding a lag lowers adjusted R2.
B12: S8 | C12: D N-1(NPLR) ~ g | D12: difference | E12: 10 | F12: 0.28 | G12: 0.19 | H12: -0.952 | I12: -1.76 | J12: 0.116 | K12: 1.886 | L12: SELECTED. Differencing removes the near unit root. DW 1.89, correct sign, correlation -0.53. Implied mapping runs from the GDP LEVEL to the probit default rate, which is exactly what an NGFS GDP level deviation supplies.
B13: S9 | C13: D N-1(NPLR) ~ g(-1) | D13: difference | E13: 10 | F13: 0.044 | G13: -0.076 | H13: -0.376 | I13: -0.6 | J13: 0.562 | K13: 1.09 | L13: Lagging destroys the fit.
B14: S10 | C14: D N-1(NPLR) ~ MA2(g,g-1) | D14: difference | E14: 10 | F14: 0.227 | G14: 0.131 | H14: -1.108 | I14: -1.53 | J14: 0.163 | K14: 1.58 | L14: Close second; smoothing adds nothing over S8.
B15: S11 | C15: D N-1(NPLR) ~ Dg | D15: difference | E15: 10 | F15: 0.063 | G15: -0.054 | H15: -0.357 | I15: -0.74 | J15: 0.483 | K15: 1.16 | L15: Over-differenced.
B16: S12 | C16: D N-1(NPLR) ~ Dg(-1) | D16: difference | E16: 10 | F16: 0.007 | G16: -0.117 | H16: -0.114 | I16: -0.24 | J16: 0.818 | K16: 1 | L16: No relationship.
... B21: S17 | C21: D N-1(NPLR) ~ output gap(-1) | D21: difference | E21: 10 | F21: 0.063 | G21: -0.054 | H21: -0.467 | I21: -0.74 | J21: 0.483 | K21: 1.14 | L21: Correct sign, no explanatory power.
B23: SELECTED S8: D N-1(NPLR_t) = a + beta x g_t
B25: 1. UNIT CONSISTENCY, the decisive reason. Cumulating D y = a + b g, where y = N-1(default rate) and g = D ln(GDP), gives y_t = y_0 + a.t + b.ln(GDP_t / GDP_0). So y depends on the LEVEL of log GDP. An NGFS GDP deviation is a LEVEL deviation, so the scenario shift is simply b times the deviation, with no further derivation. v2 estimated b on a GROWTH rate and applied it to a LEVEL deviation, which is not a valid mapping.
B28: 2. STATIONARITY. An ARDL fit (S13) returns an autoregressive coefficient of 0.93 with p below 0.001, i.e. the probit NPL series is close to a unit root. Every level specification therefore has Durbin-Watson between 0.16 and 0.38, and its standard errors are not interpretable whatever R2 says. S6 has the highest level-form R2 at 0.277 and is still unusable.
B31: 3. FIT WITHIN THE VALID SET. Among the difference forms, which are the only ones with acceptable residual behaviour, S8 has the highest R2 (0.280) and the highest absolute correlation (-0.53), with the correct sign.
B34: NOT ADOPTED, AND WHY. Non-hydrocarbon GDP growth and the Brent price both fit Oman's credit cycle better than headline GDP, because headline GDP tracks hydrocarbon VOLUME under OPEC+ quota rather than domestic demand (2022: GDP +7.99% with NPLs rising). Neither is used because NGFS produces a TOTAL GDP deviation, so either would need a bridge equation from the scenario variable to the regressor. That bridge is the recommended next enhancement.
B37: NOT TESTED: quarterly data. CBO publishes banking-system aggregates quarterly, taking the sample from 10 observations to roughly 40. That is the cheapest available way to sharpen this estimate. A GCC panel with country fixed effects is the second option; Espinoza and Prasad (2010), IMF WP/10/224, is exactly that specification.
B40: CAVEAT ON THE DEPENDENT VARIABLE. The gross NPL ratio is a STOCK with a sticky numerator (write-off and provisioning policy, restructuring, forbearance) and a moving denominator (credit growth). The probit shift concerns a default FLOW. The 2020 observation, GDP -3.4% with the NPL ratio flat at 4.2%, is a write-off-policy artefact rather than evidence of no relationship. Replacing it with (new NPL inflows + write-offs) / performing loans at t-1 needs only internal bank data and would improve this materially.

Sheet Regression_Data
B1: Estimation data
B5: Year | C5: Gross NPL ratio | D5: N-1(NPLR) | E5: D N-1(NPLR) | F5: Real GDP growth
B6: 2014 | C6: 0.019 | D6: =NORMSINV(C6) -> -2.0748547 | F6: 0.012922523
B7: 2015 | C7: 0.017 | D7: =NORMSINV(C7) -> -2.1200717 | E7: =D7-D6 -> -0.045216955 | F7: 0.05017058
B8: 2016 | C8: 0.018 | D8: =NORMSINV(C8) -> -2.0969274 | E8: =D8-D7 -> 0.023144261 | F8: 0.050464239
B9: 2017 | C9: 0.019 | D9: =NORMSINV(C9) -> -2.0748547 | E9: =D9-D8 -> 0.022072695 | F9: 0.0030405757
B10: 2018 | C10: 0.027 | D10: =NORMSINV(C10) -> -1.9268366 | E10: =D10-D9 -> 0.14801816 | F10: 0.012871039
B11: 2019 | C11: 0.035 | D11: =NORMSINV(C11) -> -1.8119107 | E11: =D11-D10 -> 0.1149259 | F11: -0.01128638
B12: 2020 | C12: 0.042 | D12: =NORMSINV(C12) -> -1.7279343 | E12: =D12-D11 -> 0.083976351 | F12: -0.033797205
B13: 2021 | C13: 0.042 | D13: =NORMSINV(C13) -> -1.7279343 | E13: =D13-D12 -> 0 | F13: 0.025824725
B14: 2022 | C14: 0.044 | D14: =NORMSINV(C14) -> -1.7060434 | E14: =D14-D13 -> 0.021890925 | F14: 0.079853941
B15: 2023 | C15: 0.045 | D15: =NORMSINV(C15) -> -1.6953977 | E15: =D15-D14 -> 0.010645687 | F15: 0.014140872
B16: 2024 | C16: 0.045 | D16: =NORMSINV(C16) -> -1.6953977 | E16: =D16-D15 -> 0 | F16: 0.01631664
B18: Correlation | E18: =CORREL(E7:E16,F7:F16) -> -0.52910368
B19: Slope (OLS) | E19: =SLOPE(E7:E16,F7:F16) -> -0.95201856
B20: Intercept | E20: =INTERCEPT(E7:E16,F7:F16) -> 0.057709515
B21: R2 | E21: =RSQ(E7:E16,F7:F16) -> 0.2799507
B22: St dev of D N-1(NPLR) | E22: =STDEV(E7:E16) -> 0.059095572
B23: St dev of GDP growth | E23: =STDEV(F7:F16) -> 0.032843566
B25: NPL ratio: as entered in the v2 workbook, no citation was recorded. TO VERIFY against the CBO Annual Report or Financial Stability Report.
B27: GDP growth: Economist Intelligence Unit, Oman, Real GDP (% change, period on period), series DGDP. VERIFIED, source and extract date present in the v2 file.

Sheet Macro_Shift
B1: Macro leg: probit shift from the GDP level deviation
B2: macro_shift = beta x GDP level deviation x macro_beta(sector). Only the DEVIATION enters, so the regression intercept and any baseline growth assumption cancel. v2 carried both, and used a different baseline for Net Zero (2023 growth) from the other three scenarios (the 11-year mean).
B4: Beta
B5: beta, OLS point estimate (S8) | C5: =Regression_Data!E19 -> -0.95201856
B6: correlation, estimated | C6: =Regression_Data!E18 -> -0.52910368
B7: st dev of D N-1(NPLR) | C7: =Regression_Data!E22 -> 0.059095572
B8: st dev of GDP growth | C8: =Regression_Data!E23 -> 0.032843566
B9: CORRELATION IN USE | C9: -0.5291 | G9: Set equal to the estimated correlation, so the model reproduces the OLS slope. It is exposed separately because the correlation is the part of beta the sample cannot pin down (p = 0.116 on ten observations), whereas the two standard deviations are estimated adequately. A disclosure band of -0.35 to -0.70 is defensible.
B10: beta IN USE = correlation x sd(D probit NPLR) / sd(GDP growth) | C10: =C9*C7/C8 -> -0.95201194
B13: Scenario shifts at the selected horizon
B14: Scenario | C14: GDP deviation (%) | D14: GDP deviation (fraction) | E14: macro_shift (probit, before macro_beta)
B15: Net Zero 2050 | C15: =INDEX(Scenario_Mapping!$D$20:$G$23,MATCH($B15,Scenario_Mapping!$B$20:$B$23,0),MATCH(Scenario_Mapping!$C$39,Scenario_Mapping!$D$19:$G$19,0)) -> -1 | D15: =C15/100 -> -0.01 | E15: =$C$10*D15 -> 0.0095201194
B16: Delayed Transition | C16: =INDEX(Scenario_Mapping!$D$20:$G$23,MATCH($B16,Scenario_Mapping!$B$20:$B$23,0),MATCH(Scenario_Mapping!$C$39,Scenario_Mapping!$D$19:$G$19,0)) -> -2 | D16: =C16/100 -> -0.02 | E16: =$C$10*D16 -> 0.019040239
B17: Current Policies | C17: =INDEX(Scenario_Mapping!$D$20:$G$23,MATCH($B17,Scenario_Mapping!$B$20:$B$23,0),MATCH(Scenario_Mapping!$C$39,Scenario_Mapping!$D$19:$G$19,0)) -> 0 | D17: =C17/100 -> 0 | E17: =$C$10*D17 -> 0
B18: Fragmented World | C18: =INDEX(Scenario_Mapping!$D$20:$G$23,MATCH($B18,Scenario_Mapping!$B$20:$B$23,0),MATCH(Scenario_Mapping!$C$39,Scenario_Mapping!$D$19:$G$19,0)) -> 0 | D18: =C18/100 -> 0 | E18: =$C$10*D18 -> 0
B20: Sign convention: beta is negative and a GDP deviation is negative, so the product is POSITIVE and raises the probit, i.e. raises PD. Current Policies carries a zero TRANSITION deviation by construction, so it has a zero macro shift here; its physical GDP damage is not modelled.
B23: Scale reference
B24: One standard deviation of Oman GDP growth | C24: =C8 -> 0.032843566
B25: Net Zero 2050: deviation in standard deviations | C25: =IF($C$8=0,0,D15/$C$8) -> -0.30447364
B26: Delayed Transition: deviation in standard deviations | C26: =IF($C$8=0,0,D16/$C$8) -> -0.60894727
B27: Current Policies: deviation in standard deviations | C27: =IF($C$8=0,0,D17/$C$8) -> 0
B28: Fragmented World: deviation in standard deviations | C28: =IF($C$8=0,0,D18/$C$8) -> 0
B30: Expressing the scenario in standard deviations communicates far better to a credit committee than a regression p-value, and makes the modesty of the transition macro shock explicit.

Sheet RatingGrades
B1: Master rating scale
B2: ILLUSTRATIVE SAMPLE. Replace column C with the bank's master scale; the whole workbook recalculates.
B5: Grade | C5: Baseline PD | D5: Note
B6: MR1 | C6: 0.001 | D6: Ladder typical of a 7-grade wholesale master scale. Demonstration only.
B7: MR2 | C7: 0.0025
B8: MR3 | C8: 0.005
B9: MR4 | C9: 0.01
B10: MR5 | C10: 0.02
B11: MR6 | C11: 0.045
B12: MR7 | C12: 0.1
B15: UNRESOLVED: the workbook treats these as point-in-time PDs, which is what an IFRS 9 ECL requires. If the bank's master scale is through-the-cycle, a TTC-to-PIT step is needed before the scenario shift.

Sheet Source_Register
B1: Source register
B4: # | C4: Value | D4: Cell reference | E4: Source | F4: Note | G4: Status
B5: 1 | C5: NGFS quadrant mapping and warming | D5: Scenario_Mapping B6:D9 | E5: NGFS Phase V, Scenarios at a glance | F5: All four warming figures match the source. | G5: VERIFIED
B6: 2 | C6: NGFS shadow carbon price | D6: NGFS_CarbonPrice C6:F9 | E6: NGFS Phase V, IIASA Scenario Explorer | F6: US$2010/tCO2, global weighted. Net Zero 2035 verified at 294. Other cells chart-read. | G6: PART VERIFIED
B7: 3 | C7: Transition GDP deviation | D7: Scenario_Mapping D20:G23 | E7: NGFS Phase V, NiGEM NGFS v1.23.2 | F7: Net Zero and Delayed Transition plausible against the published chart and corroborated by ECB OP 281. Fragmented World unverifiable. | G7: PART VERIFIED
B8: 4 | C8: US GDP deflator | D8: Scenario_Mapping C15 | E8: US Bureau of Economic Analysis | F8: Implicit price deflator for GDP, target year over 2010. | G8: TO VERIFY
B9: 5 | C9: Oman sector GVA | D9: Sector_Master E8:E17 | E9: UN SNA Table 2.4, Oman, value added by industry at basic prices, 2023 current prices | F9: Sums exactly to 41,963.9 OMR m; net of FISIM and taxes this gives 40,716.9, matching published 2023 GDP of about RO 40.7bn. | G9: VERIFIED
B10: 6 | C10: Split of ISIC B | D10: Sector_Master E9:E10 | E10: NCSI GDP by economic activity | F10: Non-oil Mining 205.8 OMR m (2023). Residual is oil and gas extraction. | G10: VERIFIED
B11: 7 | C11: Oman sector emissions | D11: Emissions_Allocation D6:D11 | E11: EDGAR, as entered in the v2 workbook | F11: All-gas CO2e, Scope 1, territorial, 2024. Buildings figure flagged as implausible. | G11: TO VERIFY
B12: 8 | C12: Oman national total GHG | D12: Emissions_Allocation D14 | E12: EDGAR | F12: 132.27 MtCO2e, about 25 tCO2e per head. High but consistent with Oman's position among the highest per-capita emitters. | G12: PLAUSIBLE
B13: 9 | C13: EDGAR to sector allocation shares | D13: Emissions_Allocation F6:P12 | E13: Analyst judgement | F13: Four rows carry judgement: industrial combustion, transport, buildings, and the residual. Replace with an EDGAR sub-sector download or an ISIC-basis account from Eora, EXIOBASE or GTAP. | G13: JUDGEMENT
B14: 10 | C14: Pass-through by sector | D14: Sector_Master I8:I17 | E14: Analyst judgement on trade exposure, informed by Cludius et al. (2020), Sijm et al. (2006), Alexeeva-Talebi (2011) | F14: Rationale recorded per sector in column K. Base rate 45% for an unassessed sector. | G14: JUDGEMENT
B15: 11 | C15: macro_beta | D15: Sector_Master J8:J17 | E15: Bank input, default 1.00 | F15: Differentiation needs sector-level default history. | G15: INPUT
... B28: 24 | C28: Emissions intensity and denominator indices | D28: Dynamic_Adjust C6:D9 | E28: Bank input, default 1.00 | F28: Sources named on the tab. | G28: INPUT

Sheet Assumption_Register
B1: Assumption register
B2: Rebuilt from the live cells, with the governing cell reference against every entry.
B4: ID | C4: Assumption | D4: Cell reference | E4: Value / status | F4: Rationale and limitation
B5: A01 | C5: Pure probit shift | D5: StressedPD_Sector G29:J98 | E5: NORMSDIST(NORMSINV(PD0)+push+macro) | F5: Returns PD0 exactly at zero stress. The conditional-Vasicek form used in v2 maps an unconditional PD to a conditional PD and returns values BELOW baseline at zero stress.
B6: A02 | C6: rho not used in the PD channel | D6: n/a | E6: Removed | F6: Basel CRE31.5 correlations are prudential parameters for a 99.9% capital quantile, not empirical asset correlations for scenario translation. Not required under a probit shift.
B7: A03 | C7: Transition risk only | D7: whole model | E7: Design | F7: No physical risk in PD or LGD, no customer layer, no ECL.
B8: A04 | C8: Denominator is GVA | D8: Sector_Master C4 | E8: GVA on both sides | F8: Oman publishes value added by activity but not turnover; output at basic prices needs the supply-use table, which is not public. GVA is the only denominator that exists for every sector. Switch C4 to TURNOVER and populate column G if the bank obtains it.
B9: A05 | C9: EU intensity built symmetrically | D9: EU_k_Calibration C21:C26 | E9: Route 1 | F9: EU national Scope 1 emissions over EU GVA, exactly as the Oman intensity is built, so the turnover conversion never enters. One documented adjustment for median firm versus economy average.
B10: A06 | C10: Median to average intensity ratio | D10: EU_k_Calibration C25 | E10: 0.57 | F10: From OP 281 Chart 12. Without it the calibration would attribute the emissions of the largest firms to the median one.
B11: A07 | C11: k transfers from the EU to Oman unchanged | D11: EU_k_Calibration C50 | E11: Applied to Oman cost ratios | F11: Holding the cost ratio constant, the probit PD response to a cost shock is assumed the same in both economies. Not testable on Omani data. The largest transfer assumption in the model.
B12: A08 | C12: k is a scale, not a shape | D12: EU_k_Calibration | E12: LN(1+x) imposed | F12: One anchor pair identifies a multiplier only. Three or more anchors would give the curvature support.
B13: A09 | C13: Anchor carbon price vintage | D13: EU_k_Calibration C42 | E13: Assumption | F13: The ECB exercise uses NGFS Phase I, so a Phase I price is required. v2 paired the ECB PD response with a Phase V price.
B14: A10 | C14: No abatement response | D14: StressedPD_Sector G16:J25 | E14: Full current emissions charged | F14: The NGFS shadow price is a marginal abatement cost, not a tax bill. Conservative.
B15: A11 | C15: Static intensity and denominator | D15: Dynamic_Adjust C6:D9 | E15: Both indices 1.00 | F15: The two omissions bias the cost ratio in opposite directions and do not reliably cancel.
... B37: A33 | C37: Exposure weights are relative, not absolute | D37: Physical_Exposure H6:J15 | E37: Normalised to a mean of 1.00 | F37: They redistribute the national annual average loss across sectors without changing its total, so an error in the weights misallocates risk between sectors but cannot inflate or deflate system-wide risk.
